Workbook

Sheet Kebutuhan Data
A1: Sumber Data | B1: Indikator | C1: Granularitas | D1: Level Data | E1: Literature Review | F1: Arah korelasi terhadap PHK | G1: R-squared
A2: Data Ketenagakerjaan
A3: Sakernas | B3: Jumlah penduduk bekerja | C3: Triwulanan | D3: Provinsi | F3: + | G3: 0.44
B4: % TPT | C4: Triwulanan | D4: Provinsi | F4: + | G4: 0.15
B5: % TPT Laki-laki | C5: Triwulanan | D5: Provinsi | F5: + | G5: 0.2
B6: % TPT Perempuan | C6: Triwulanan | D6: Provinsi | F6: + | G6: 0.04
B7: % TPAK | C7: Triwulanan | D7: Provinsi | F7: - | G7: 0.02
B8: % TPAK Laki-laki | C8: Triwulanan | D8: Provinsi | F8: - | G8: 0
B9: % TPAK Perempuan | C9: Triwulanan | D9: Provinsi | F9: - | G9: 0.02
B10: % Pekerja Formal | C10: Triwulanan | D10: Provinsi | E10: Sebagai proxy PHK -- tenaga kerja formal menurun. "Implikasi adanya potensi tambahan jumlah PHK ini adalah naiknya jumlah angkatan kerja yang menganggur dan/atau naiknya tenaga kerja di sektor informal, yang per Februari 2026 sudah mencapai 87,74 juta jiwa, atau kurang lebih 59,42 persen dari total tenaga kerja aktif di Indonesia." Bu vivi: agak banyak efek lainnya | F10: + | G10: 0.09
B11: Berusaha Sendiri | C11: Triwulanan | D11: Provinsi | F11: + | G11: 0.46
B12: Buruh/karyawan/pegawai | C12: Triwulanan | D12: Provinsi | F12: + | G12: 0.53
B13: Pekerja Keluarga Tidak Dibayar | C13: Triwulanan | D13: Provinsi | F13: + | G13: 0.27
B14: % Setengah pengangguran | C14: Triwulanan | D14: Provinsi | F14: - | G14: 0.05
B15: Penduduk Bekerja Setengah Penganggur | C15: Triwulanan | D15: Provinsi | F15: + | G15: 0.42
B16: Jam Kerja | C16: Triwulanan | D16: Provinsi | E16: Sebagai proxy "PHK" -- perusahaan yang tertekan biaya produksi diperkirakan akan menempuh langkah seperti tidak memperpanjang kontrak PKWT, memotong jam kerja, atau menahan rekruitmen pengganti karyawan yang mengundurkan diri. Saluran-saluran non-PHK tersebut tidak masuk pelaporan PHK formal di Kemenaker. | F16: + | G16: 0.11
B17: UMP (IDR th) | C17: Triwulanan | D17: Provinsi | F17: - | G17: 0.01
B18: Growth UMP | C18: Triwulanan | D18: Provinsi | F18: + | G18: 0.01
B19: Upah buruh/karyawan/pegawai (IDR) | C19: Triwulanan | D19: Provinsi | F19: + | G19: 0.11
B20: Kaitz Index | C20: Triwulanan | D20: Provinsi | F20: - | G20: 0.21
B21: Proporsi Lapangan Kerja Informal Sektor Non-Pertanian | C21: Triwulanan | D21: Provinsi | F21: - | G21: 0.02
B22: Proporsi Lapangan Kerja Informal | C22: Triwulanan | D22: Provinsi | F22: - | G22: 0.07
B23: Pencari Kerja Terdaftar - Jumlah | D23: Provinsi | F23: + | G23: 0.5
B24: Lowongan Kerja Terdaftar - Jumlah | D24: Provinsi | F24: + | G24: 0.45
B25: Penempatan/Pemenuhan Tenaga Kerja - Jumlah | D25: Provinsi | F25: + | G25: 0.58
A26: BPJS Ketenagakerjaan | B26: BPJSTK - Peserta Aktif PU | C26: Bulanan | D26: Provinsi | F26: + | G26: 0.57
B27: BPJSTK - Peserta Aktif BPU | C27: Bulanan | D27: Provinsi | F27: + | G27: 0.59
B28: BPJSTK - PHK | C28: Bulanan | D28: Provinsi | F28: + | G28: 0.61
B29: BPJSTK - JHT PHK | C29: Bulanan | D29: Provinsi | F29: + | G29: 0.17
B30: BPJSTK - JKP PHK | C30: Bulanan | D30: Provinsi | F30: + | G30: 0.81
A31: Satudata Kemnaker | B31: PHK | C31: Bulanan | D31: Provinsi
A32: Data Makroekonomi
A33: CEIC | B33: PDRB | C33: Triwulanan | E33: PDRB ↑ → output & permintaan tenaga kerja ↑ → PHK ↓
B34: PDRB per sektor | C34: Triwulanan | E34: Output sektor ↑ → kebutuhan tenaga kerja ↑ → PHK ↓
B35: FDI | C35: Triwulanan | E35: FDI ↑ → investasi & ekspansi usaha ↑ → tenaga kerja ↑ → PHK ↓
B36: Manufacturing share (%) | C36: Triwulanan | E36: Manufacturing share ↑ → peran sektor manufaktur dalam ekonomi ↑ → aktivitas produksi & penyerapan tenaga kerja ↑ → PHK ↓
B37: GDP per worker | E37: ILO - Economic factor for wage setting
A38: BPS | B38: Inflasi | C38: Bulanan | E38: Inflasi ↑ → daya beli/profit turun → PHK ↑
B39: ICOR | C39: Tahunan | E39: ICOR ↑ → efisiensi investasi ↓ → pertumbuhan melambat → PHK ↑
B40: Export value
B41: Import value | C41: Bulanan | E41: Impor bahan baku ↑ → produksi ↑ → PHK ↓
B42: Neraca perdagangan | C42: Bulanan | E42: Surplus perdagangan ↑ → produksi ↑ → tenaga kerja ↑ → PHK ↓
B43: Pertumbuhan Ekspor | E43: Export growth ↑ → permintaan luar negeri ↑ → produksi perusahaan ↑ → kebutuhan tenaga kerja ↑ → PHK ↓
B44: Perubahan harga produsen (%) | C44: Bulanan | E44: Biaya produksi ↑ → profit turun → PHK ↑
B45: Perubahan harga konsumen (%) | C45: Bulanan | E45: Daya beli ↓ → permintaan ↓ → PHK ↑
B46: Indeks Harga Produsen (IHP) | C46: Bulanan | E46: Harga produsen ↑ → biaya produksi ↑ → PHK ↑
B47: Indeks Harga Konsumen (IHK) | C47: Bulanan | E47: Inflasi ↑ → konsumsi melemah → PHK ↑
B48: Tabel input output (IO) | C48: 10 Tahunan | E48: Multiplier sektor ↑ → penyerapan tenaga kerja ↑ → PHK ↓
B49: Laju Pertumbuhan PDB Per Tenaga Kerja | C49: Tahunan | E49: ILO - Economic factor for wage setting
A50: BI | B50: NPL | C50: Bulanan | E50: NPL ↑ → kredit macet ↑ → ekspansi usaha ↓ → PHK ↑
B51: Suku bunga | C51: Bulanan | E51: Suku bunga ↑ → investasi ↓ → PHK ↑
B52: Nilai tukar | C52: Harian | E52: Depresiasi ↑ → biaya impor & ketidakpastian ↑ → PHK ↑
B53: Indeks Keyakinan Konsumen (IKK) | C53: Bulanan | E53: Keyakinan konsumsi ↑ → permintaan ↑ → PHK ↓
A54: Data Industri
A55: Sensus Ekonomi
A56: Survei Industri | B56: Perusahaan Industri Sedang | C56: Tahunan | D56: Provinsi | F56: + | G56: 0.61
B57: Perusahaan Industri Besar | C57: Tahunan | D57: Provinsi | F57: + | G57: 0.65
B58: Jumlah Perusahaan | C58: Tahunan | D58: Provinsi | F58: + | G58: 0.53
B59: Tenaga Kerja Industri Sedang | C59: Tahunan | D59: Provinsi | F59: + | G59: 0.66
B60: Tenaga Kerja Industri Besar | C60: Tahunan | D60: Provinsi | F60: + | G60: 0.54
B61: Jumlah Tenaga Kerja Produksi | C61: Tahunan | D61: Provinsi | F61: + | G61: 0.63
B62: Jumlah Tenaga Kerja Lainnya | C62: Tahunan | D62: Provinsi | F62: + | G62: 0.66
B63: Jumlah Tenaga Kerja | C63: Tahunan | D63: Provinsi | F63: + | G63: 0.58
B64: Pengeluaran untuk Pekerja Produksi Upah/Gaji, Upah Lembur, Tunjangan | C64: Tahunan | D64: Provinsi | F64: + | G64: 0.63
B65: Pengeluaran untuk Pekerja Produksi Lainnya | C65: Tahunan | D65: Provinsi | F65: + | G65: 0.6
B66: Jumlah Pengeluaran untuk Pekerja Produksi | C66: Tahunan | D66: Provinsi | F66: + | G66: 0.56
B67: Pengeluaran untuk Pekerja Lainnya Upah/Gaji, Upah Lembur, Tunjangan | C67: Tahunan | D67: Provinsi | F67: + | G67: 0.68
B68: Pengeluaran untuk Pekerja Lainnya Lainnya | C68: Tahunan | D68: Provinsi | F68: + | G68: 0.74
... B76: Jumlah Perusahaan PMA | C76: Tahunan | D76: Provinsi | F76: + | G76: 0.64
A77: Survei Industri, diolah | B77: Jumlah Tenaga Kerja/Jumlah Perusahaan | C77: Tahunan | D77: Provinsi | E77: Rata-rata jumlah tenaga kerja di perusahaan
B78: Jumlah Tenaga Kerja Produksi/Jumlah Tenaga Kerja | C78: Tahunan | D78: Provinsi | E78: Proporsi pekerja produksi
B79: Jumlah Tenaga Kerja/Biaya Input | C79: Tahunan | D79: Provinsi | E79: Tenaga Kerja per Biaya Input
B80: Jumlah Tenaga Kerja/Nilai Output | C80: Tahunan | D80: Provinsi | E80: Tenaga Kerja per Nilai Output- Labor intensity. Semakin tinggi, semakin labor-intensive kegiatan produksi
B81: Jumlah Tenaga Kerja/Nilai Tambah | C81: Tahunan | D81: Provinsi | E81: Tenaga Kerja per Value Added- Jumlah pekerja relatif terhadap nilai tambah yang dihasilkan. Mengukur intensitas penggunaan pekerja terhadap nilai ekonomi yang diciptakan
B82: Biaya Pekerja/Biaya Input | C82: Tahunan | D82: Provinsi | E82: Mengukur beban biaya tenaga kerja terhadap biaya input yang dikeluarkan perusahaan
B83: Biaya Pekerja/Nilai Output | C83: Tahunan | D83: Provinsi | E83: Mengukur beban biaya tenaga kerja terhadap nilai produksi
B84: Biaya Pekerja/Nilai Tambah Pasar | C84: Tahunan | D84: Provinsi | E84: Mengukur seberapa besar bagian nilai tambah yang digunakan untuk membayar pekerja
B85: Biaya Pekerja/Nilai Tambah Produksi | C85: Tahunan | D85: Provinsi | E85: Mengukur seberapa besar bagian nilai tambah yang digunakan untuk membayar pekerja
B86: Biaya Pekerja/Tenaga Kerja | C86: Tahunan | D86: Provinsi | E86: Menggambarkan biaya pekerja rata-rata yang ditanggung perusahaan
B87: Nilai Output/Tenaga Kerja | C87: Tahunan | D87: Provinsi | E87: Produktivitas | F87: - | G87: 0.01
B88: Nilai Tambah Pasar/Tenaga Kerja | C88: Tahunan | D88: Provinsi | E88: Produktivitas | F88: - | G88: 0.01
B89: Nilai Tambah Produksi/Tenaga Kerja | C89: Tahunan | D89: Provinsi | E89: Produktivitas | F89: - | G89: 0.01
B90: Biaya Input/Nilai Output | C90: Tahunan | D90: Provinsi | E90: Proporsi nilai output yang terserap oleh biaya input - Nilai tinggi menunjukkan biaya input menyerap bagian besar dari output
B91: Nilai Tambah/Nilai Output | C91: Tahunan | D91: Provinsi | E91: Proporsi nilai tambah terhadap output - Menggambarkan ruang nilai tambah yang tersisa setelah memperhitungkan input
B92: Biaya Pekerja Produksi/Total Biaya Pekerja | C92: Tahunan | D92: Provinsi | E92: Menunjukkan apakah biaya tenaga kerja terutama berasal dari pekerja produksi
B93: Biaya Pekerja Lainnya/Total Biaya Pekerja | C93: Tahunan | D93: Provinsi | E93: Menggambarkan struktur biaya tenaga kerja nonproduksi
B94: Upah Pekerja Produksi/Jumlah Tenaga Kerja Produksi
B95: Upah Pekerja Lainnya/Jumlah Tenaga Kerja Lainnya
B96: Proporsi Perusahaan PMDN | C96: Tahunan | D96: Provinsi | E96: Share PMA
B97: Proporsi Perusahaan PMA | C97: Tahunan | D97: Provinsi | E97: Share PMDN
A98: Survei Industri, diolah perubahan tahunan | B98: Pertumbuhan Nilai Output
B99: Pertumbuhan Biaya Input
B100: Pertumbuhan Nilai Tambah
B101: Pertumbuhan Tenaga Kerja
B102: Pertumbuhan Jumlah Perusahaan
B103: Pertumbuhan Pengeluaran Tenaga Kerja
B104: Pertumbuhan Produktivitas Tenaga Kerja (Nilai Tambah)
B105: Selisih Pertumbuhan Biaya Input dan Pertumbuhan Nilai Output | E105: Nilai tinggi menunjukkan biaya naik lebih cepat daripada output
B106: Selisih Pertumbuhan Biaya Pekerja dan Nilai Output | E106: Nilai tinggi menunjukkan biaya pekerja meningkat lebih cepat daripada produksi
B108: Capital/labor | C108: Tahunan | D108: Provinsi | E108: Untuk melihat capital intensity -- semakin tinggi, semakin capital intensive --> kemungkinan PHK semakin tinggi
...

Sheet Kesimpulan Awal
A1: 1. PHK terutama terlihat sebagai fenomena pasar kerja formal
A2: Indikator | B2: Arah korelasi | C2: R-squared | D2: Kesimpulan awal
A3: Jumlah penduduk bekerja | B3: + | C3: 0.44 | D3: PHK tercatat cenderung lebih terkonsentrasi pada wilayah dengan struktur pasar kerja yang relatif formal dan basis pekerja penerima upah yang lebih besar.
A4: Buruh/karyawan/pegawai | B4: + | C4: 0.53
A5: % Pekerja Formal | B5: + | C5: 0.09
A6: Proporsi Lapangan Kerja Informal Sektor Non-Pertanian | B6: - | C6: 0.02
A7: Proporsi Lapangan Kerja Informal | B7: - | C7: 0.07
A30: 2. PHK mengikuti skala industri
A31: Indikator | B31: Arah korelasi | C31: R-squared | D31: Kesimpulan awal
A32: Jumlah perusahaan industri sedang dan besar | B32: + | C32: 0.53–0.65 | D32: PHK saat ini tercatat banyak muncul di wilayah dengan ekosistem industri yang besar: Lebih banyak perusahaan industri → lebih banyak pekerja industri → lebih besar exposure terhadap shock usaha → jumlah PHK tercatat lebih tinggi
A33: Tenaga kerja industri sedang dan besar | B33: + | C33: 0.54-0.65
A34: Pengeluaran untuk pekerja | B34: + | C34: 0.63
A35: Biaya input | B35: + | C35: 0.55
A36: Nilai output | B36: + | C36: 0.59
A37: Nilai tambah | B37: + | C37: 0.62
A38: Jumlah perusahaan PMDN | B38: + | C38: 0.47
A39: Jumlah perusahaan PMA | B39: + | C39: 0.64
A73: 3. Tekanan pasar kerja
A74: Indikator | B74: Arah korelasi | C74: R-squared | D74: Kesimpulan awal
A75: % Pekerja Formal | B75: + | C75: 0.09 | D75: Tekanan pasar kerja tidak selalu muncul dalam bentuk kehilangan pekerjaan secara eksplisit. Di wilayah dengan pasar kerja formal, tekanan lebih mudah terlihat sebagai PHK. Di wilayah dengan pasar kerja informal, penyesuaian dapat terjadi tanpa pekerja sepenuhnya keluar dari pekerjaan.
A76: Proporsi Lapangan Kerja Informal | B76: - | C76: 0.07
A77: Penduduk Bekerja Setengah Penganggur | B77: + | C77: 0.42
A78: % Setengah Pengangguran | B78: - | C78: 0.05
A79: TPT | B79: + | C79: 0.15
A80: TPT Laki-laki | B80: + | C80: 0.2
A99: 4. Pencari kerja, lowongan kerja, dll
A100: Indikator | B100: Arah korelasi | C100: R-squared | D100: Kesimpulan awal
A101: Pencari Kerja Terdaftar - Jumlah | B101: + | C101: 0.5 | D101: Angka PHK tinggi → lebih banyak orang mencari pekerjaan baru → jumlah pencari kerja terdaftar meningkat
A102: Lowongan Kerja Terdaftar - Jumlah | B102: + | C102: 0.45
A103: Penempatan/Pemenuhan Tenaga Kerja - Jumlah | B103: + | C103: 0.58
A122: 5. Data BPJS sebagai alternatif indikator PHK
A123: Indikator | B123: Arah korelasi | C123: R-squared
A124: BPJSTK - Peserta Aktif PU | B124: + | C124: 0.57
A125: BPJSTK - Peserta Aktif BPU | B125: + | C125: 0.59
A126: BPJSTK - PHK | B126: + | C126: 0.61
A127: BPJSTK - JHT PHK | B127: + | C127: 0.17
A128: BPJSTK - JKP PHK | B128: + | C128: 0.81

Sheet Database (Tahun)
A1: Provinsi | B1: Tahun | C1: PHK | D1: % Pekerja Formal | E1: % Pekerja Formal (2019) | F1: % Pekerja Formal (Growth from 2019, pp) | G1: Jumlah Pekerja Memiliki Kontrak Tertulis | H1: Jumlah Pekerja Formal | I1: % Pekerja Memiliki Kontrak Tertulis | J1: % Pekerja Memiliki Kontrak Tertulis (2019) | K1: % Pekerja Memiliki Kontrak Tertulis (Growth from 2019, pp) | L1: Jumlah Penduduk Bekerja | M1: % TPT | N1: % TPT Laki-laki | O1: % TPT Perempuan | P1: % TPAK | Q1: % TPAK Laki-laki | R1: % TPAK Perempuan | S1: Berusaha Sendiri | T1: Buruh/karyawan/pegawai | U1: Pekerja Keluarga Tidak Dibayar | V1: Penduduk Bekerja Setengah Penganggur | W1: % Pekerja Penuh Waktu | X1: % Pekerja Paruh Waktu | Y1: % Setengah Pengangguran | Z1: Tenaga Kerja - Pertanian, Kehutanan dan Perikanan | AA1: Tenaga Kerja - Pertambangan dan Penggalian | AB1: Tenaga Kerja - Industri Pengolahan | AC1: Tenaga Kerja - Pengadaan Listrik dan Gas | AD1: Tenaga Kerja - Pengadaan Air, Pengelolaan Sampah, Limbah dan Daur Ulang | AE1: Tenaga Kerja - Konstruksi | AF1: Tenaga Kerja - Perdagangan Besar dan Eceran, Reparasi Mobil dan Sepeda Motor | AG1: Tenaga Kerja - Transportasi dan Pergudangan | AH1: Tenaga Kerja - Penyediaan Akomodasi dan Makan Minum | AI1: Tenaga Kerja - Informasi dan Komunikasi | AJ1: Tenaga Kerja - Jasa Keuangan dan Asuransi | AK1: Tenaga Kerja - Real Estate | AL1: Tenaga Kerja - Jasa Perusahaan | AM1: Tenaga Kerja - Administrasi Pemerintahan, Pertahanan dan Jaminan Sosial Wajib | AN1: Tenaga Kerja - Jasa Pendidikan | AO1: Tenaga Kerja - Jasa Kesehatan dan Kegiatan Sosial | AP1: Tenaga Kerja - Jasa Lainnya | AQ1: % Share Tenaga Kerja - Pertanian, Kehutanan dan Perikanan | AR1: % Share Tenaga Kerja - Pertambangan dan Penggalian | AS1: % Share Tenaga Kerja - Industri Pengolahan | AT1: % Share Tenaga Kerja - Pengadaan Listrik dan Gas | AU1: % Share Tenaga Kerja - Pengadaan Air, Pengelolaan Sampah, Limbah dan Daur Ulang | AV1: % Share Tenaga Kerja - Konstruksi | AW1: % Share Tenaga Kerja - Perdagangan Besar dan Eceran, Reparasi Mobil dan Sepeda Motor | AX1: % Share Tenaga Kerja - Transportasi dan Pergudangan | AY1: % Share Tenaga Kerja - Penyediaan Akomodasi dan Makan Minum | AZ1: % Share Tenaga Kerja - Informasi dan Komunikasi | BA1: % Share Tenaga Kerja - Jasa Keuangan dan Asuransi | BB1: % Share Tenaga Kerja - Real Estate | BC1: % Share Tenaga Kerja - Jasa Perusahaan | BD1: % Share Tenaga Kerja - Administrasi Pemerintahan, Pertahanan dan Jaminan Sosial Wajib | BE1: % Share Tenaga Kerja - Jasa Pendidikan | BF1: % Share Tenaga Kerja - Jasa Kesehatan dan Kegiatan Sosial | BG1: % Share Tenaga Kerja - Jasa Lainnya | BH1: Jam Kerja | BI1: UMP (IDR) | BJ1: Growth UMP | BK1: Upah buruh/karyawan/pegawai (IDR) | BL1: Kaitz Index | BM1: Proporsi Lapangan Kerja Informal Sektor Non-Pertanian | BN1: Proporsi Lapangan Kerja Informal | BO1: Pencari Kerja Terdaftar - Jumlah | BP1: Lowongan Kerja Terdaftar - Jumlah | BQ1: Penempatan/Pemenuhan Tenaga Kerja - Jumlah | BR1: BPJSTK - Peserta Aktif PU | BS1: BPJSTK - Peserta Aktif BPU | BT1: BPJSTK - PHK | BU1: BPJSTK - JHT PHK | BV1: BPJSTK - JKP PHK | BW1: Pertumbuhan Bekerja | BX1: Pertumbuhan Buruh/Karyawan/Pegawai | BY1: Pertumbuhan Pekerja Keluarga Tidak Dibayar | BZ1: Pertumbuhan % Pekerja Formal | CA1: Pertumbuhan % Pekerja Memiliki Kontrak Tertulis | CB1: Pertumbuhan % Pekerja Penuh Waktu | CC1: Pertumbuhan % Pekerja Paruh Waktu | CD1: Pertumbuhan % Setengah Pengangguran | CE1: Pertumbuhan Jam Kerja | CF1: Pertumbuhan TPT | CG1: Pertumbuhan TPT Laki-laki | CH1: Pertumbuhan TPT Perempuan | CI1: Pertumbuhan TPAK | CJ1: Pertumbuhan TPAK Laki-laki | CK1: Pertumbuhan TPAK Perempuan | CL1: Pertumbuhan Upah | CM1: Pertumbuhan BPJSTK - Peserta Aktif PU | CN1: Pertumbuhan BPJSTK - Peserta Aktif BPU | CO1: Pertumbuhan BPJSTK - PHK | CP1: Pertumbuhan BPJSTK - JHT PHK | CQ1: Pertumbuhan BPJSTK - JKP PHK | CR1: Lag_1 PHK | CS1: Lag_1 % Pekerja Formal | CT1: Lag_1 % Pekerja Memiliki Kontrak Tertulis | CU1: Lag_1 Growth UMP | CV1: Lag_1 BPJSTK - Peserta Aktif PU | CW1: Lag_1 BPJSTK - Peserta Aktif BPU | CX1: Lag_1 BPJSTK - PHK | CY1: Lag_1 BPJSTK - JHT PHK | CZ1: Lag_1 BPJSTK - JKP PHK | DA1: Perusahaan Industri Sedang | DB1: Perusahaan Industri Besar | DC1: Jumlah Perusahaan | DD1: Tenaga Kerja Industri Sedang | DE1: Tenaga Kerja Industri Besar | DF1: Jumlah Tenaga Kerja Produksi | DG1: Jumlah Tenaga Kerja Lainnya | DH1: Jumlah Tenaga Kerja | DI1: Pengeluaran untuk Pekerja Produksi Upah/Gaji, Upah Lembur, Tunjangan | DJ1: Pengeluaran untuk Pekerja Produksi Lainnya | DK1: Jumlah Pengeluaran untuk Pekerja Produksi | DL1: Pengeluaran untuk Pekerja Lainnya Upah/Gaji, Upah Lembur, Tunjangan | DM1: Pengeluaran untuk Pekerja Lainnya Lainnya | DN1: Jumlah Pengeluaran untuk Pekerja Lainnya | DO1: Jumlah Pengeluaran Seluruh Pekerja | DP1: Biaya Input | DQ1: Nilai Output | DR1: Nilai Tambah (harga pasar) | DS1: Nilai Tambah (biaya faktor produksi) | DT1: Jumlah Perusahaan PMDN | DU1: Jumlah Perusahaan PMA | DV1: Jumlah Tenaga Kerja/Jumlah Perusahaan | DW1: Jumlah Tenaga Kerja Produksi/Jumlah Tenaga Kerja | DX1: Jumlah Tenaga Kerja/Biaya Input | DY1: Jumlah Tenaga Kerja/Nilai Output | DZ1: Jumlah Tenaga Kerja/Nilai Tambah (harga pasar) | EA1: Jumlah Tenaga Kerja/Nilai Tambah (biaya faktor produksi) | EB1: Biaya Pekerja/Biaya Input | EC1: Biaya Pekerja/Nilai Output | ED1: Biaya Pekerja/Nilai Tambah Pasar | EE1: Biaya Pekerja/Nilai Tambah Produksi | EF1: Biaya Pekerja/Tenaga Kerja | EG1: Nilai Output/Tenaga Kerja | EH1: Nilai Tambah Pasar/Tenaga Kerja | EI1: Nilai Tambah Produksi/Tenaga Kerja | EJ1: Biaya Input/Nilai Output | EK1: Nilai Tambah Pasar/Nilai Output | EL1: Nilai Tambah Produksi/Nilai Output | EM1: Biaya Pekerja Produksi/Total Biaya Pekerja | EN1: Biaya Pekerja Lainnya/Total Biaya Pekerja | EO1: Upah Pekerja Produksi/Jumlah Tenaga Kerja Produksi | EP1: Upah Pekerja Lainnya/Jumlah Tenaga Kerja Lainnya | EQ1: Proporsi Perusahaan PMDN | ER1: Proporsi Perusahaan PMA | ES1: Pertumbuhan Nilai Output | ET1: Pertumbuhan Biaya Input | EU1: Pertumbuhan Nilai Tambah Pasar | EV1: Pertumbuhan Nilai Tambah Produksi | EW1: Pertumbuhan Tenaga Kerja | EX1: Pertumbuhan Jumlah Perusahaan | EY1: Pertumbuhan Pengeluaran Tenaga Kerja | EZ1: Pertumbuhan Produktivitas (Nilai Tambah Pasar) Tenaga Kerja | FA1: Pertumbuhan Produktivitas (Nilai Tambah Produksi) Tenaga Kerja | FB1: Selisih Pertumbuhan Biaya Input dan Pertumbuhan Nilai Output | FC1: Selisih Pertumbuhan Biaya Pekerja dan Nilai Output | FD1: PDRB Riil (IDR miliar) | FE1: PDRB Riil (IDR juta) | FF1: PDRB Manufaktur (IDR juta) | FG1: Manufacturing Share | FH1: Laju Pertumbuhan PDB Industri Manufaktur | FI1: PMI Manufaktur | FJ1: FDI | FK1: PDRB/Pekerja | FL1: Laju Pertumbuhan PDB Per Tenaga Kerja | FM1: ICOR | FN1: Inflasi YoY (per IV) | FO1: Inflasi YoY (Average) | FP1: IHP (2016=100) | FQ1: IHK (2010=100) | FR1: Perubahan harga produsen (%) | FS1: Perubahan harga konsumen (%) | FT1: Nilai Ekspor BPS | FU1: Nilai Ekspor | FV1: Nilai Impor | FW1: Neraca Perdagangan | FX1: NPL | FY1: BI Rate (Average)* | FZ1: Kurs | GA1: IKK
A2: Aceh | B2: 2022 | C2: 84 | D2: 38.55 | E2: 0.25703192 | F2: =D2-E2 -> 38.292968 | G2: 396068 | H2: =D2*L2/100 -> 923270.19 | I2: 0.46985719 | J2: 0.49237172 | K2: =I2-J2 -> -0.022514528 | L2: 2394994 | M2: 6.17 | N2: 5.68 | O2: 7.02 | P2: 63.5 | Q2: 81.06 | R2: 46.15 | S2: 604272 | T2: 842954 | U2: 300164 | V2: 250455 | W2: =100-X2-Y2 -> 61.5 | X2: 28.04 | Y2: 10.46 | Z2: 969992 | AA2: 21670 | AB2: 175231 | AC2: 5769 | AD2: 3586 | AE2: 158823 | AF2: 320127 | AG2: 75172 | AH2: 118304 | AI2: 9444 | AJ2: 10724 | AK2: 870 | AL2: 26719 | AM2: 159044 | AN2: 176663 | AO2: 66276 | AP2: 96580 | AQ2: =Z2/sum($Z2:$AP2) -> 0.40500811 | AR2: =AA2/sum($Z2:$AP2) -> 0.0090480394 | AS2: =AB2/sum($Z2:$AP2) -> 0.073165528 | AT2: =AC2/sum($Z2:$AP2) -> 0.0024087743 | AU2: =AD2/sum($Z2:$AP2) -> 0.0014972898 | AV2: =AE2/sum($Z2:$AP2) -> 0.066314571 | AW2: =AF2/sum($Z2:$AP2) -> 0.13366505 | AX2: =AG2/sum($Z2:$AP2) -> 0.031387135 | ... BG2: =AP2/sum($Z2:$AP2) -> 0.04032578 | BH2: 38 | BI2: 3166.46 | BJ2: 0.045149637 | BK2: 2327990 | BL2: =BI2*1000/BK2 -> 1.3601691 | BM2: 44.13 | BN2: 61.45 | BO2: 11600 | BP2: 1553 | BQ2: 1549 | BR2: 315935 | BS2: 56888 | BT2: 1448 | BU2: 3939 | DA2: 57 | DB2: 30 | DC2: 87 | DD2: 1849 | DE2: 8755 | DF2: 7168 | DG2: 3436 | DH2: 10604 | DI2: 397366109 | DJ2: 34909199 | DK2: 432275308 | DL2: 193818007 | DM2: 11138177 | DN2: 204956184 | DO2: 637231492 | DP2: 10652661077 | DQ2: 21273885572 | DR2: =DQ2-DP2 -> 10621224495 | DS2: 10379820664 | DT2: 81 | DU2: 6 | DV2: =DH2/DC2 -> 121.88506 | DW2: =DF2/DH2 -> 0.67597133 | DX2: =DH2/DP2 -> 9.9543203e-07 | DY2: =DH2/DQ2 -> 4.9845149e-07 | DZ2: =DH2/DR2 -> 9.9837829e-07 | EA2: =DH2/DS2 -> 1.0215976e-06 | EB2: =DO2/DP2 -> 0.059818996 | EC2: =DO2/DQ2 -> 0.029953696 | ED2: =DO2/DR2 -> 0.059996048 | EE2: =DO2/DS2 -> 0.061391378 | EF2: =DO2/DH2 -> 60093.502 | EG2: =DQ2/DH2 -> 2006213.3 | EH2: =DR2/DH2 -> 1001624.3 | EI2: =DS2/DH2 -> 978858.98 | EJ2: =DP2/DQ2 -> 0.50073885 | EK2: =DR2/DQ2 -> 0.49926115 | EL2: =DS2/DQ2 -> 0.48791372 | EM2: =DK2/DO2 -> 0.67836463 | EN2: =DN2/DO2 -> 0.32163537 | EO2: =DI2/DF2 -> 55436.12 | EP2: =DL2/DG2 -> 56408.035 | EQ2: =DT2/DC2 -> 0.93103448 | ER2: =DU2/DC2 -> 0.068965517 | FD2: 140971.7 | FE2: 140971700 | FF2: 6472363.2 | FG2: =(FF2/FE2)*100 -> 4.59125 | FH2: 4.19 | FI2: 51.8 | FJ2: 127.6 | FK2: =FD2/L2 -> 0.058860983 | FL2: 2.75 | FM2: 6.02 | FN2: 5.94 | FO2: 4.48 | FP2: 130.8 | FQ2: 163.1 | FR2: 10 | FS2: 4.2 | FT2: 745.8 | FU2: 692.5 | FV2: 167.3 | FW2: =FU2-FV2 -> 525.2 | FX2: 605.4 | FY2: 4 | FZ2: 14875.93 | GA2: 119.9
A3: Sumatera Utara | B3: 2022 | C3: 70 | D3: 40.93 | E3: 0.29822611 | F3: =D3-E3 -> 40.631774 | G3: 1158119 | H3: =D3*L3/100 -> 2945885.2 | I3: 0.43182733 | J3: 0.40538524 | K3: =I3-J3 -> 0.026442083 | L3: 7197374 | M3: 6.16 | N3: 5.9 | O3: 6.55 | P3: 69.53 | Q3: 83.89 | R3: 55.37 | S3: 1442845 | T3: 2681903 | U3: 1119422 | V3: 491786 | W3: =100-X3-Y3 -> 68.93 | X3: 24.24 | Y3: 6.83 | Z3: 2493755 | AA3: 32908 | AB3: 720482 | AC3: 16080 | AD3: 18074 | AE3: 435285 | AF3: 1304741 | AG3: 316982 | AH3: 542897 | AI3: 42634 | AJ3: 57805 | AK3: 14570 | AL3: 90623 | AM3: 312989 | AN3: 366511 | AO3: 107116 | AP3: 323922 | AQ3: =Z3/sum(Z3:AP3) -> 0.34648123 | AR3: =AA3/sum($Z3:$AP3) -> 0.0045722231 | AS3: =AB3/sum($Z3:$AP3) -> 0.10010345 | AT3: =AC3/sum($Z3:$AP3) -> 0.0022341482 | AU3: =AD3/sum($Z3:$AP3) -> 0.0025111937 | AV3: =AE3/sum($Z3:$AP3) -> 0.060478308 | AW3: =AF3/sum($Z3:$AP3) -> 0.18128014 | AX3: =AG3/sum($Z3:$AP3) -> 0.044041341 | AY3: =AH3/sum($Z3:$AP3) -> 0.075429872 | ... BG3: =AP3/sum($Z3:$AP3) -> 0.045005581 | BH3: 42 | BI3: 2522.6099 | BJ3: 0.92769171 | BK3: 2576442 | BL3: =BI3*1000/BK3 -> 0.97910605 | BM3: 46.45 | BN3: 59.07 | BO3: 27722 | BP3: 1526 | BQ3: 1368 | BR3: 1201977 | BS3: 282555 | BT3: 10740 | BU3: 25807 | DA3: 832 | DB3: 432 | DC3: 1264 | DD3: 32479 | DE3: 138586 | DF3: 137378 | DG3: 33767 | DH3: 171145 | DI3: 6546111198 | DJ3: 439161312 | DK3: 6985272510 | DL3: 2301046792 | DM3: 153495166 | DN3: 2454541958 | DO3: 9439814468 | DP3: 196870314607 | DQ3: 288425631608 | DR3: =DQ3-DP3 -> 91555317001 | DS3: 89561384425 | DT3: 1178 | DU3: 86 | DV3: =DH3/DC3 -> 135.39953 | DW3: =DF3/DH3 -> 0.80269947 | DX3: =DH3/DP3 -> 8.6932863e-07 | DY3: =DH3/DQ3 -> 5.9337653e-07 | DZ3: =DH3/DR3 -> 1.8693071e-06 | EA3: =DH3/DS3 -> 1.910924e-06 | EB3: =DO3/DP3 -> 0.047949405 | EC3: =DO3/DQ3 -> 0.032728764 | ED3: =DO3/DR3 -> 0.10310504 | EE3: =DO3/DS3 -> 0.1054005 | EF3: =DO3/DH3 -> 55156.823 | EG3: =DQ3/DH3 -> 1685270.6 | EH3: =DR3/DH3 -> 534957.59 | EI3: =DS3/DH3 -> 523307.05 | EJ3: =DP3/DQ3 -> 0.68256872 | EK3: =DR3/DQ3 -> 0.31743128 | EL3: =DS3/DQ3 -> 0.31051812 | EM3: =DK3/DO3 -> 0.73997985 | EN3: =DN3/DO3 -> 0.26002015 | EO3: =DI3/DF3 -> 47650.36 | EP3: =DL3/DG3 -> 68144.839 | EQ3: =DT3/DC3 -> 0.93196203 | ER3: =DU3/DC3 -> 0.068037975 | FD3: 573528.8 | FE3: 573528800 | FF3: 99869074 | FG3: =(FF3/FE3)*100 -> 17.413088 | FH3: 1.98 | FI3: 51.8 | FJ3: 1316.1 | FK3: =FD3/L3 -> 0.079685841 | FL3: 2.37 | FM3: 6.02 | FN3: 6.12 | FO3: 4.84 | FP3: 130.8 | FQ3: 163.1 | FR3: 10 | FS3: 4.2 | FT3: 12717 | FU3: 12108.9 | FV3: 6837.5 | FW3: =FU3-FV3 -> 5271.4 | FX3: 5638.3 | FY3: 4 | FZ3: 14875.93 | GA3: 119.9
A4: Sumatera Barat | B4: 2022 | C4: 35 | D4: 34.74 | E4: 0.23942157 | F4: =D4-E4 -> 34.500578 | G4: 429172 | H4: =D4*L4/100 -> 933868.17 | I4: 0.51049242 | J4: 0.46317085 | K4: =I4-J4 -> 0.047321577 | L4: 2688164 | M4: 6.28 | N4: 6.2 | O4: 6.39 | P4: 69.3 | Q4: 82.58 | R4: 56.28 | S4: 653862 | T4: 840702 | U4: 387302 | V4: 233244 | W4: =100-X4-Y4 -> 65.74 | X4: 25.58 | Y4: 8.68 | Z4: 939746 | AA4: 38347 | AB4: 230775 | AC4: 7828 | AD4: 4751 | AE4: 117992 | AF4: 543335 | AG4: 89098 | AH4: 212594 | AI4: 18413 | AJ4: 23335 | AK4: 1388 | AL4: 32739 | AM4: 122595 | AN4: 169700 | AO4: 55036 | AP4: 80492 | AQ4: =Z4/sum(Z4:AP4) -> 0.34958656 | AR4: =AA4/sum($Z4:$AP4) -> 0.014265127 | AS4: =AB4/sum($Z4:$AP4) -> 0.085848557 | AT4: =AC4/sum($Z4:$AP4) -> 0.0029120247 | AU4: =AD4/sum($Z4:$AP4) -> 0.0017673773 | AV4: =AE4/sum($Z4:$AP4) -> 0.043893155 | AW4: =AF4/sum($Z4:$AP4) -> 0.20212122 | AX4: =AG4/sum($Z4:$AP4) -> 0.033144555 | AY4: =AH4/sum($Z4:$AP4) -> 0.079085205 | ... BG4: =AP4/sum($Z4:$AP4) -> 0.029943114 | BH4: 39 | BI4: 2512.539 | BJ4: 1.1472435 | BK4: 2655767 | BL4: =BI4*1000/BK4 -> 0.94606906 | BM4: 52.38 | BN4: 65.26 | BO4: 20304 | BP4: 1907 | BQ4: 1725 | BR4: 373923 | BS4: 111406 | BT4: 2681 | BU4: 7889 | DA4: 136 | DB4: 60 | DC4: 196 | DD4: 4139 | DE4: 12644 | DF4: 13030 | DG4: 3753 | DH4: 16783 | DI4: 586601645 | DJ4: 34221055 | DK4: 620822700 | DL4: 199240416 | DM4: 19188839 | DN4: 218429255 | DO4: 839251955 | DP4: 40419965393 | DQ4: 64948317682 | DR4: =DQ4-DP4 -> 24528352289 | DS4: 24215698280 | DT4: 179 | DU4: 17 | DV4: =DH4/DC4 -> 85.627551 | DW4: =DF4/DH4 -> 0.77638086 | DX4: =DH4/DP4 -> 4.152156e-07 | DY4: =DH4/DQ4 -> 2.5840546e-07 | DZ4: =DH4/DR4 -> 6.8422859e-07 | EA4: =DH4/DS4 -> 6.9306281e-07 | EB4: =DO4/DP4 -> 0.020763302 | EC4: =DO4/DQ4 -> 0.012921843 | ED4: =DO4/DR4 -> 0.034215586 | EE4: =DO4/DS4 -> 0.034657351 | EF4: =DO4/DH4 -> 50006.075 | EG4: =DQ4/DH4 -> 3869887.2 | EH4: =DR4/DH4 -> 1461499.9 | EI4: =DS4/DH4 -> 1442870.7 | EJ4: =DP4/DQ4 -> 0.62234045 | EK4: =DR4/DQ4 -> 0.37765955 | EL4: =DS4/DQ4 -> 0.37284566 | EM4: =DK4/DO4 -> 0.7397334 | EN4: =DN4/DO4 -> 0.2602666 | EO4: =DI4/DF4 -> 45019.313 | EP4: =DL4/DG4 -> 53088.307 | EQ4: =DT4/DC4 -> 0.91326531 | ER4: =DU4/DC4 -> 0.086734694 | FD4: 182628.3 | FE4: 182628300 | FF4: 16918566 | FG4: =(FF4/FE4)*100 -> 9.2639346 | FH4: 1.75 | FI4: 51.8 | FJ4: 95.6 | FK4: =FD4/L4 -> 0.067937931 | FL4: 0.22 | FM4: 6.02 | FN4: 5.88 | FO4: 4.55 | FP4: 130.8 | FQ4: 163.1 | FR4: 10 | FS4: 4.2 | FT4: 2868.4 | FU4: 2617.8 | FV4: 710.3 | FW4: =FU4-FV4 -> 1907.5 | FX4: 1147 | FY4: 4 | FZ4: 14875.93 | GA4: 119.9
A5: Riau | B5: 2022 | C5: 916 | D5: 45.98 | E5: 0.29519579 | F5: =D5-E5 -> 45.684804 | G5: 649948 | H5: =D5*L5/100 -> 1457073.6 | I5: 0.50870224 | J5: 0.50865168 | K5: =I5-J5 -> 5.0563141e-05 | L5: 3168929 | M5: 4.37 | N5: 3.72 | O5: 5.68 | P5: 63.86 | Q5: 83.59 | R5: 43.28 | S5: 694008 | T5: 1277659 | U5: 334746 | V5: 235115 | W5: =100-X5-Y5 -> 63.61 | X5: 28.97 | Y5: 7.42 | Z5: 1266219 | AA5: 34966 | AB5: 230084 | AC5: 6679 | AD5: 18642 | AE5: 164959 | AF5: 568587 | AG5: 93309 | AH5: 179718 | AI5: 18560 | AJ5: 30956 | AK5: 9593 | AL5: 58862 | AM5: 130044 | AN5: 191647 | AO5: 54396 | AP5: 111708 | AQ5: =Z5/sum(Z5:AP5) -> 0.39957317 | AR5: =AA5/sum($Z5:$AP5) -> 0.011034012 | AS5: =AB5/sum($Z5:$AP5) -> 0.072606234 | AT5: =AC5/sum($Z5:$AP5) -> 0.0021076521 | AU5: =AD5/sum($Z5:$AP5) -> 0.0058827446 | AV5: =AE5/sum($Z5:$AP5) -> 0.052055127 | AW5: =AF5/sum($Z5:$AP5) -> 0.1794256 | AX5: =AG5/sum($Z5:$AP5) -> 0.029444964 | AY5: =AH5/sum($Z5:$AP5) -> 0.056712536 | ... BG5: =AP5/sum($Z5:$AP5) -> 0.035251026 | BH5: 40 | BI5: 2938.564 | BJ5: 1.7309639 | BK5: 2889691 | BL5: =BI5*1000/BK5 -> 1.0169129 | BM5: 44.3 | BN5: 54.02 | BO5: 16477 | BP5: 555 | BQ5: 420 | BR5: 593002 | BS5: 173909 | BT5: 4751 | BU5: 10388 | DA5: 150 | DB5: 236 | DC5: 386 | DD5: 7827 | DE5: 74441 | DF5: 63748 | DG5: 18520 | DH5: 82268 | DI5: 4266561754 | DJ5: 554351386 | DK5: 4820913140 | DL5: 1557667859 | DM5: 336737446 | DN5: 1894405305 | DO5: 6715318445 | DP5: 413662869319 | DQ5: 591999174685 | DR5: =DQ5-DP5 -> 178336305366 | DS5: 176663812892 | DT5: 344 | DU5: 42 | DV5: =DH5/DC5 -> 213.12953 | DW5: =DF5/DH5 -> 0.77488209 | DX5: =DH5/DP5 -> 1.9887693e-07 | DY5: =DH5/DQ5 -> 1.3896641e-07 | DZ5: =DH5/DR5 -> 4.613082e-07 | EA5: =DH5/DS5 -> 4.6567545e-07 | EB5: =DO5/DP5 -> 0.016233796 | EC5: =DO5/DQ5 -> 0.011343459 | ED5: =DO5/DR5 -> 0.037655364 | EE5: =DO5/DS5 -> 0.03801185 | EF5: =DO5/DH5 -> 81627.345 | EG5: =DQ5/DH5 -> 7195983.5 | EH5: =DR5/DH5 -> 2167748.2 | EI5: =DS5/DH5 -> 2147418.4 | EJ5: =DP5/DQ5 -> 0.69875582 | EK5: =DR5/DQ5 -> 0.30124418 | EL5: =DS5/DQ5 -> 0.29841902 | EM5: =DK5/DO5 -> 0.71789792 | EN5: =DN5/DO5 -> 0.28210208 | EO5: =DI5/DF5 -> 66928.559 | EP5: =DL5/DG5 -> 84107.336 | EQ5: =DT5/DC5 -> 0.89119171 | ER5: =DU5/DC5 -> 0.10880829 | FD5: 529533 | FE5: 529533000 | FF5: 1.701169e+08 | FG5: =(FF5/FE5)*100 -> 32.125836 | FH5: 4.73 | FI5: 51.8 | FJ5: 2748.7 | FK5: =FD5/L5 -> 0.16710157 | FL5: 3.89 | FM5: 6.02 | FN5: 5.67 | FO5: 4.23 | FP5: 130.8 | FQ5: 163.1 | FR5: 10 | FS5: 4.2 | FT5: 22596 | FU5: 20690.9 | FV5: 4899.4 | FW5: =FU5-FV5 -> 15791.5 | FX5: 1795.1 | FY5: 4 | FZ5: 14875.93 | GA5: 119.9
A6: Jambi | B6: 2022 | C6: 92 | D6: 40.02 | E6: 0.27593228 | F6: =D6-E6 -> 39.744068 | G6: 299736 | H6: =D6*L6/100 -> 719487.16 | I6: 0.47659526 | J6: 0.42800893 | K6: =I6-J6 -> 0.048586327 | L6: 1797819 | M6: 4.59 | N6: 4.33 | O6: 5.05 | P6: 67.84 | Q6: 86.17 | R6: 48.97 | S6: 440747 | T6: 628911 | U6: 257486 | V6: 134140 | W6: =100-X6-Y6 -> 61.86 | X6: 30.68 | Y6: 7.46 | Z6: 862275 | AA6: 56641 | AB6: 94420 | AC6: 1520 | AD6: 4093 | AE6: 85331 | AF6: 260547 | AG6: 62670 | AH6: 90857 | AI6: 4866 | AJ6: 16043 | AK6: 2139 | AL6: 19974 | AM6: 74381 | AN6: 91169 | AO6: 26537 | AP6: 44356 | AQ6: =Z6/sum(Z6:AP6) -> 0.47962281 | AR6: =AA6/sum($Z6:$AP6) -> 0.031505396 | AS6: =AB6/sum($Z6:$AP6) -> 0.052519191 | AT6: =AC6/sum($Z6:$AP6) -> 0.00084546887 | AU6: =AD6/sum($Z6:$AP6) -> 0.0022766474 | AV6: =AE6/sum($Z6:$AP6) -> 0.047463621 | AW6: =AF6/sum($Z6:$AP6) -> 0.14492393 | AX6: =AG6/sum($Z6:$AP6) -> 0.034858904 | AY6: =AH6/sum($Z6:$AP6) -> 0.050537346 | ... BG6: =AP6/sum($Z6:$AP6) -> 0.024672117 | BH6: 39 | BI6: 2649.0342 | BJ6: 0.71752649 | BK6: 2520767 | BL6: =BI6*1000/BK6 -> 1.0508842 | BM6: 44.76 | BN6: 59.98 | BO6: 11203 | BP6: 978 | BQ6: 870 | BR6: 268570 | BS6: 112330 | BT6: 1925 | BU6: 3123 | DA6: 103 | DB6: 90 | DC6: 193 | DD6: 4344 | DE6: 23509 | DF6: 22318 | DG6: 5535 | DH6: 27853 | DI6: 1223247536 | DJ6: 81227879 | DK6: 1304475415 | DL6: 448817027 | DM6: 48993694 | DN6: 497810721 | DO6: 1802286136 | DP6: 37826829189 | DQ6: 62457166353 | DR6: =DQ6-DP6 -> 24630337164 | DS6: 24425409709 | DT6: 178 | DU6: 15 | DV6: =DH6/DC6 -> 144.31606 | DW6: =DF6/DH6 -> 0.80127814 | DX6: =DH6/DP6 -> 7.3632923e-07 | DY6: =DH6/DQ6 -> 4.4595363e-07 | DZ6: =DH6/DR6 -> 1.1308412e-06 | EA6: =DH6/DS6 -> 1.1403289e-06 | EB6: =DO6/DP6 -> 0.04764571 | EC6: =DO6/DQ6 -> 0.028856355 | ED6: =DO6/DR6 -> 0.073173425 | EE6: =DO6/DS6 -> 0.073787345 | EF6: =DO6/DH6 -> 64707.074 | EG6: =DQ6/DH6 -> 2242385.6 | EH6: =DR6/DH6 -> 884297.46 | EI6: =DS6/DH6 -> 876940 | EJ6: =DP6/DQ6 -> 0.60564434 | EK6: =DR6/DQ6 -> 0.39435566 | EL6: =DS6/DQ6 -> 0.39107457 | EM6: =DK6/DO6 -> 0.7237893 | EN6: =DN6/DO6 -> 0.2762107 | EO6: =DI6/DF6 -> 54809.908 | EP6: =DL6/DG6 -> 81087.087 | EQ6: =DT6/DC6 -> 0.92227979 | ER6: =DU6/DC6 -> 0.077720207 | FD6: 161731.9 | FE6: 161731900 | FF6: 16213293 | FG6: =(FF6/FE6)*100 -> 10.024796 | FH6: 3.12 | FI6: 51.8 | FJ6: 39.2 | FK6: =FD6/L6 -> 0.089960057 | FL6: 2.15 | FM6: 6.02 | FN6: 5.36 | FO6: 3.97 | FP6: 130.8 | FQ6: 163.1 | FR6: 10 | FS6: 4.2 | FT6: 3001.9 | FU6: 2719.4 | FV6: 310.1 | FW6: =FU6-FV6 -> 2409.3 | FX6: 907.1 | FY6: 4 | FZ6: 14875.93 | GA6: 119.9
A7: Sumatera Selatan | B7: 2022 | C7: 160 | D7: 36.72 | E7: 0.25679714 | F7: =D7-E7 -> 36.463203 | G7: 649448 | H7: =D7*L7/100 -> 1575179.3 | I7: 0.44178784 | J7: 0.40187735 | K7: =I7-J7 -> 0.039910486 | L7: 4289704 | M7: 4.63 | N7: 4.53 | O7: 4.8 | P7: 69.31 | Q7: 84.95 | R7: 53.32 | S7: 1012639 | T7: 1470045 | U7: 785338 | V7: 303829 | W7: =100-X7-Y7 -> 64.54 | X7: 28.38 | Y7: 7.08 | Z7: 1992257 | AA7: 75036 | AB7: 267855 | AC7: 12971 | AD7: 8130 | AE7: 201842 | AF7: 694992 | AG7: 133528 | AH7: 193235 | AI7: 23012 | AJ7: 25256 | AK7: 4843 | AL7: 57558 | AM7: 194644 | AN7: 195620 | AO7: 58745 | AP7: 150180 | AQ7: =Z7/sum(Z7:AP7) -> 0.46442762 | AR7: =AA7/sum($Z7:$AP7) -> 0.017492116 | AS7: =AB7/sum($Z7:$AP7) -> 0.062441371 | AT7: =AC7/sum($Z7:$AP7) -> 0.0030237518 | AU7: =AD7/sum($Z7:$AP7) -> 0.0018952357 | AV7: =AE7/sum($Z7:$AP7) -> 0.047052664 | AW7: =AF7/sum($Z7:$AP7) -> 0.16201398 | AX7: =AG7/sum($Z7:$AP7) -> 0.031127556 | AY7: =AH7/sum($Z7:$AP7) -> 0.045046232 | ... BG7: =AP7/sum($Z7:$AP7) -> 0.035009409 | BH7: 41 | BI7: 3144.446 | BJ7: 3.3299804 | BK7: 2630695 | BL7: =BI7*1000/BK7 -> 1.195291 | BM7: 45.1 | BN7: 63.28 | BO7: 23589 | BP7: 1212 | BQ7: 1119 | BR7: 573899 | BS7: 95170 | BT7: 4681 | BU7: 16715 | DA7: 172 | DB7: 139 | DC7: 311 | DD7: 6958 | DE7: 64350 | DF7: 46106 | DG7: 22690 | DH7: 68796 | DI7: 3059524810 | DJ7: 383126877 | DK7: 3442651687 | DL7: 1372343204 | DM7: 215366011 | DN7: 1587709215 | DO7: 5030360902 | DP7: 89734205396 | DQ7: 183833254610 | DR7: =DQ7-DP7 -> 94099049214 | DS7: 92936472024 | DT7: 284 | DU7: 27 | DV7: =DH7/DC7 -> 221.209 | DW7: =DF7/DH7 -> 0.67018431 | DX7: =DH7/DP7 -> 7.6666417e-07 | DY7: =DH7/DQ7 -> 3.7423044e-07 | DZ7: =DH7/DR7 -> 7.3110197e-07 | EA7: =DH7/DS7 -> 7.402476e-07 | EB7: =DO7/DP7 -> 0.056058455 | EC7: =DO7/DQ7 -> 0.027363716 | ED7: =DO7/DR7 -> 0.053458148 | EE7: =DO7/DS7 -> 0.054126876 | EF7: =DO7/DH7 -> 73119.962 | EG7: =DQ7/DH7 -> 2672150.3 | EH7: =DR7/DH7 -> 1367798.3 | EI7: =DS7/DH7 -> 1350899.4 | EJ7: =DP7/DQ7 -> 0.48812825 | EK7: =DR7/DQ7 -> 0.51187175 | EL7: =DS7/DQ7 -> 0.50554766 | EM7: =DK7/DO7 -> 0.68437469 | EN7: =DN7/DO7 -> 0.31562531 | EO7: =DI7/DF7 -> 66358.496 | EP7: =DL7/DG7 -> 60482.292 | EQ7: =DT7/DC7 -> 0.91318328 | ER7: =DU7/DC7 -> 0.08681672 | FD7: 343503.6 | FE7: 343503600 | FF7: 63307615 | FG7: =(FF7/FE7)*100 -> 18.429971 | FH7: 4.39 | FI7: 51.8 | FJ7: 1226.3 | FK7: =FD7/L7 -> 0.080076294 | FL7: 2.53 | FM7: 6.02 | FN7: 5.34 | FO7: 4.05 | FP7: 130.8 | FQ7: 163.1 | FR7: 10 | FS7: 4.2 | FT7: 7583.3 | FU7: 6789.8 | FV7: 1704.8 | FW7: =FU7-FV7 -> 5085 | FX7: 2902.5 | FY7: 4 | FZ7: 14875.93 | GA7: 119.9
A8: Bengkulu | B8: 2022 | C8: 26 | D8: 32.46 | E8: 0.24193566 | F8: =D8-E8 -> 32.218064 | G8: 172272 | H8: =D8*L8/100 -> 336771.2 | I8: 0.57859683 | J8: 0.49588197 | K8: =I8-J8 -> 0.082714864 | L8: 1037496 | M8: 3.59 | N8: 3.39 | O8: 3.91 | P8: 69.81 | Q8: 84.72 | R8: 54.36 | S8: 225584 | T8: 297741 | U8: 181804 | V8: 83167 | W8: =100-X8-Y8 -> 63.06 | X8: 28.92 | Y8: 8.02 | Z8: 499641 | AA8: 11121 | AB8: 53218 | AC8: 2605 | AD8: 4169 | AE8: 45823 | AF8: 165220 | AG8: 28769 | AH8: 36180 | AI8: 5769 | AJ8: 8766 | AK8: 1705 | AL8: 10074 | AM8: 66540 | AN8: 50633 | AO8: 19352 | AP8: 27911 | AQ8: =Z8/sum(Z8:AP8) -> 0.48158354 | AR8: =AA8/sum($Z8:$AP8) -> 0.010719077 | AS8: =AB8/sum($Z8:$AP8) -> 0.051294656 | AT8: =AC8/sum($Z8:$AP8) -> 0.0025108531 | AU8: =AD8/sum($Z8:$AP8) -> 0.0040183287 | AV8: =AE8/sum($Z8:$AP8) -> 0.044166917 | AW8: =AF8/sum($Z8:$AP8) -> 0.15924881 | AX8: =AG8/sum($Z8:$AP8) -> 0.027729264 | AY8: =AH8/sum($Z8:$AP8) -> 0.034872424 | ... BG8: =AP8/sum($Z8:$AP8) -> 0.026902272 | BH8: 38 | BI8: 2238.0943 | BJ8: 1.0426325 | BK8: 2737834 | BL8: =BI8*1000/BK8 -> 0.81746896 | BM8: 47.72 | BN8: 67.54 | BO8: 4246 | BP8: 664 | BQ8: 662 | BR8: 117043 | BS8: 24826 | BT8: 834 | BU8: 1958 | DA8: 39 | DB8: 35 | DC8: 74 | DD8: 1488 | DE8: 4940 | DF8: 5264 | DG8: 1164 | DH8: 6428 | DI8: 250451827 | DJ8: 7680719 | DK8: 258132546 | DL8: 53961108 | DM8: 780743 | DN8: 54741851 | DO8: 312874397 | DP8: 11430107228 | DQ8: 17116441144 | DR8: =DQ8-DP8 -> 5686333916 | DS8: 5584631012 | DT8: 65 | DU8: 9 | DV8: =DH8/DC8 -> 86.864865 | DW8: =DF8/DH8 -> 0.81891724 | DX8: =DH8/DP8 -> 5.6237443e-07 | DY8: =DH8/DQ8 -> 3.7554536e-07 | DZ8: =DH8/DR8 -> 1.1304296e-06 | EA8: =DH8/DS8 -> 1.1510161e-06 | EB8: =DO8/DP8 -> 0.027372831 | EC8: =DO8/DQ8 -> 0.018279173 | ED8: =DO8/DR8 -> 0.055022164 | EE8: =DO8/DS8 -> 0.056024184 | EF8: =DO8/DH8 -> 48673.677 | EG8: =DQ8/DH8 -> 2662794.2 | EH8: =DR8/DH8 -> 884619.46 | EI8: =DS8/DH8 -> 868797.61 | EJ8: =DP8/DQ8 -> 0.66778527 | EK8: =DR8/DQ8 -> 0.33221473 | EL8: =DS8/DQ8 -> 0.32627291 | EM8: =DK8/DO8 -> 0.8250357 | EN8: =DN8/DO8 -> 0.1749643 | EO8: =DI8/DF8 -> 47578.235 | EP8: =DL8/DG8 -> 46358.34 | EQ8: =DT8/DC8 -> 0.87837838 | ER8: =DU8/DC8 -> 0.12162162 | FD8: 49916.1 | FE8: 49916100 | FF8: 2863150.6 | FG8: =(FF8/FE8)*100 -> 5.7359261 | FH8: 3.08 | FI8: 51.8 | FJ8: 52.2 | FK8: =FD8/L8 -> 0.048112089 | FL8: 2.73 | FM8: 6.02 | FN8: 5.89 | FO8: 4.42 | FP8: 130.8 | FQ8: 163.1 | FR8: 10 | FS8: 4.2 | FT8: 311.2 | FU8: 5418.9 | FV8: 22.4 | FW8: =FU8-FV8 -> 5396.5 | FX8: 391.9 | FY8: 4 | FZ8: 14875.93 | GA8: 119.9
A9: Lampung | B9: 2022 | C9: 30 | D9: 28.49 | E9: 0.20955681 | F9: =D9-E9 -> 28.280443 | G9: 462137 | H9: =D9*L9/100 -> 1250131.5 | I9: 0.40715912 | J9: 0.40821017 | K9: =I9-J9 -> -0.0010510504 | L9: 4387966 | M9: 4.52 | N9: 4.1 | O9: 5.24 | P9: 70.06 | Q9: 85.84 | R9: 53.54 | S9: 878210 | T9: 1135028 | U9: 807884 | V9: 303546 | W9: =100-X9-Y9 -> 63.38 | X9: 29.7 | Y9: 6.92 | Z9: 1914133 | AA9: 17131 | AB9: 409629 | AC9: 4742 | AD9: 20707 | AE9: 216667 | AF9: 865967 | AG9: 147397 | AH9: 183528 | AI9: 18878 | AJ9: 27928 | AK9: 2577 | AL9: 37241 | AM9: 120485 | AN9: 191652 | AO9: 63328 | AP9: 145976 | AQ9: =Z9/sum(Z9:AP9) -> 0.4362233 | AR9: =AA9/sum($Z9:$AP9) -> 0.0039040868 | AS9: =AB9/sum($Z9:$AP9) -> 0.09335282 | AT9: =AC9/sum($Z9:$AP9) -> 0.0010806829 | AU9: =AD9/sum($Z9:$AP9) -> 0.0047190429 | AV9: =AE9/sum($Z9:$AP9) -> 0.049377548 | AW9: =AF9/sum($Z9:$AP9) -> 0.19735044 | AX9: =AG9/sum($Z9:$AP9) -> 0.03359119 | AY9: =AH9/sum($Z9:$AP9) -> 0.041825301 | ... BG9: =AP9/sum($Z9:$AP9) -> 0.03326735 | BH9: 40 | BI9: 2440.4862 | BJ9: 0.34887354 | BK9: 2322728 | BL9: =BI9*1000/BK9 -> 1.0506982 | BM9: 55.67 | BN9: 71.51 | BO9: 15790 | BP9: 928 | BQ9: 866 | BR9: 467278 | BS9: 95808 | BT9: 3193 | BU9: 11782 | DA9: 289 | DB9: 127 | DC9: 416 | DD9: 10608 | DE9: 49857 | DF9: 48628 | DG9: 11837 | DH9: 60465 | DI9: 1900350146 | DJ9: 69056397 | DK9: 1969406543 | DL9: 576905524 | DM9: 32071632 | DN9: 608977156 | DO9: 2578383699 | DP9: 52285233457 | DQ9: 79891922824 | DR9: =DQ9-DP9 -> 27606689367 | DS9: 27070434111 | DT9: 388 | DU9: 28 | DV9: =DH9/DC9 -> 145.34856 | DW9: =DF9/DH9 -> 0.80423385 | DX9: =DH9/DP9 -> 1.1564451e-06 | DY9: =DH9/DQ9 -> 7.5683496e-07 | DZ9: =DH9/DR9 -> 2.19023e-06 | EA9: =DH9/DS9 -> 2.2336177e-06 | EB9: =DO9/DP9 -> 0.049313803 | EC9: =DO9/DQ9 -> 0.032273396 | ED9: =DO9/DR9 -> 0.093397063 | EE9: =DO9/DS9 -> 0.095247224 | EF9: =DO9/DH9 -> 42642.582 | EG9: =DQ9/DH9 -> 1321292 | EH9: =DR9/DH9 -> 456573.05 | EI9: =DS9/DH9 -> 447704.19 | EJ9: =DP9/DQ9 -> 0.65444956 | EK9: =DR9/DQ9 -> 0.34555044 | EL9: =DS9/DQ9 -> 0.33883818 | EM9: =DK9/DO9 -> 0.76381438 | EN9: =DN9/DO9 -> 0.23618562 | EO9: =DI9/DF9 -> 39079.34 | EP9: =DL9/DG9 -> 48737.478 | EQ9: =DT9/DC9 -> 0.93269231 | ER9: =DU9/DC9 -> 0.067307692 | FD9: 257534.2 | FE9: 257534200 | FF9: 46589527 | FG9: =(FF9/FE9)*100 -> 18.090617 | FH9: 0.4 | FI9: 51.8 | FJ9: 247.8 | FK9: =FD9/L9 -> 0.05869102 | FL9: 1.82 | FM9: 6.02 | FN9: 5.12 | FO9: 3.8 | FP9: 130.8 | FQ9: 163.1 | FR9: 10 | FS9: 4.2 | FT9: 5601.1 | FU9: 288.8 | FV9: 2706.4 | FW9: =FU9-FV9 -> -2417.6 | FX9: 2968.5 | FY9: 4 | FZ9: 14875.93 | GA9: 119.9
A10: Bangka Belitung | B10: 2022 | C10: 380 | D10: 50.37 | E10: 0.3520311 | F10: =D10-E10 -> 50.017969 | G10: 144140 | H10: =D10*L10/100 -> 368190.6 | I10: 0.4434422 | J10: 0.36799907 | K10: =I10-J10 -> 0.075443131 | L10: 730972 | M10: 4.77 | N10: 4.33 | O10: 5.62 | P10: 67.38 | Q10: 86.02 | R10: 47.55 | S10: 206869 | T10: 325048 | U10: 59517 | V10: 24598 | W10: =100-X10-Y10 -> 74.93 | X10: 21.7 | Y10: 3.37 | Z10: 183099 | AA10: 138969 | AB10: 50185 | AC10: 2012 | AD10: 254 | AE10: 33381 | AF10: 128709 | AG10: 15143 | AH10: 36734 | AI10: 5849 | AJ10: 6771 | AK10: 551 | AL10: 7933 | AM10: 40359 | AN10: 37193 | AO10: 16265 | AP10: 27565 | AQ10: =Z10/sum(Z10:AP10) -> 0.25048702 | AR10: =AA10/sum($Z10:$AP10) -> 0.19011535 | AS10: =AB10/sum($Z10:$AP10) -> 0.068655161 | AT10: =AC10/sum($Z10:$AP10) -> 0.0027524994 | AU10: =AD10/sum($Z10:$AP10) -> 0.00034748253 | AV10: =AE10/sum($Z10:$AP10) -> 0.045666592 | AW10: =AF10/sum($Z10:$AP10) -> 0.17607925 | AX10: =AG10/sum($Z10:$AP10) -> 0.020716252 | AY10: =AH10/sum($Z10:$AP10) -> 0.050253635 | ... BG10: =AP10/sum($Z10:$AP10) -> 0.037710063 | BH10: 41 | BI10: 3264.884 | BJ10: 1.0792596 | BK10: 2969146 | BL10: =BI10*1000/BK10 -> 1.0996037 | BM10: 43.49 | BN10: 49.63 | BO10: 4483 | BP10: 532 | BQ10: 501 | BR10: 105071 | BS10: 49780 | BT10: 780 | BU10: 1560 | DA10: 67 | DB10: 43 | DC10: 110 | DD10: 2668 | DE10: 11621 | DF10: 12086 | DG10: 2203 | DH10: 14289 | DI10: 600383912 | DJ10: 45933461 | DK10: 646317373 | DL10: 126200136 | DM10: 4380611 | DN10: 130580747 | DO10: 776898120 | DP10: 21574166843 | DQ10: 49270238495 | DR10: =DQ10-DP10 -> 27696071652 | DS10: 27136704101 | DT10: 99 | DU10: 11 | DV10: =DH10/DC10 -> 129.9 | DW10: =DF10/DH10 -> 0.84582546 | DX10: =DH10/DP10 -> 6.623199e-07 | DY10: =DH10/DQ10 -> 2.900128e-07 | DZ10: =DH10/DR10 -> 5.1592154e-07 | EA10: =DH10/DS10 -> 5.2655621e-07 | EB10: =DO10/DP10 -> 0.036010573 | EC10: =DO10/DQ10 -> 0.015768101 | ED10: =DO10/DR10 -> 0.028050842 | EE10: =DO10/DS10 -> 0.028629052 | EF10: =DO10/DH10 -> 54370.363 | EG10: =DQ10/DH10 -> 3448123.6 | EH10: =DR10/DH10 -> 1938279.2 | EI10: =DS10/DH10 -> 1899132.5 | EJ10: =DP10/DQ10 -> 0.43787421 | EK10: =DR10/DQ10 -> 0.56212579 | EL10: =DS10/DQ10 -> 0.55077274 | EM10: =DK10/DO10 -> 0.83192037 | EN10: =DN10/DO10 -> 0.16807963 | EO10: =DI10/DF10 -> 49675.981 | EP10: =DL10/DG10 -> 57285.581 | EQ10: =DT10/DC10 -> 0.9 | ER10: =DU10/DC10 -> 0.1 | FD10: 57804.2 | FE10: 57804200 | FF10: 12484719 | FG10: =(FF10/FE10)*100 -> 21.598291 | FH10: 5.14 | FI10: 51.8 | FJ10: 129.7 | FK10: =FD10/L10 -> 0.079078542 | FL10: 0.18 | FM10: 6.02 | FN10: 4.98 | FO10: 3.68 | FP10: 130.8 | FQ10: 163.1 | FR10: 10 | FS10: 4.2 | FT10: 2634.4 | FU10: 2510.2 | FV10: 206.6 | FW10: =FU10-FV10 -> 2303.6 | FX10: 466.1 | FY10: 4 | FZ10: 14875.93 | GA10: 119.9
A11: Kepulauan Riau | B11: 2022 | C11: 863 | D11: 63.68 | E11: 0.41825896 | F11: =D11-E11 -> 63.261741 | G11: 472030 | H11: =D11*L11/100 -> 736138.89 | I11: 0.67544209 | J11: 0.6034253 | K11: =I11-J11 -> 0.072016782 | L11: 1155997 | N11: 7.78 | O11: 9.03 | P11: 68.94 | Q11: 80.02 | R11: 50.68 | S11: 228843 | T11: 698846 | U11: 76616 | V11: 57246 | W11: =100-X11-Y11 -> 79.32 | X11: 15.73 | Y11: 4.95 | Z11: 90120 | AA11: 9630 | AB11: 297852 | AC11: 3976 | AD11: 1692 | AE11: 82574 | AF11: 201209 | AG11: 73239 | AH11: 117832 | AI11: 10787 | AJ11: 17249 | AK11: 13137 | AL11: 30991 | AM11: 59649 | AN11: 52821 | AO11: 18953 | AP11: 74286 | AQ11: =Z11/sum(Z11:AP11) -> 0.07795868 | AR11: =AA11/sum($Z11:$AP11) -> 0.0083304714 | AS11: =AB11/sum($Z11:$AP11) -> 0.25765811 | AT11: =AC11/sum($Z11:$AP11) -> 0.0034394553 | AU11: =AD11/sum($Z11:$AP11) -> 0.0014636716 | AV11: =AE11/sum($Z11:$AP11) -> 0.071430981 | AW11: =AF11/sum($Z11:$AP11) -> 0.17405668 | AX11: =AG11/sum($Z11:$AP11) -> 0.063355701 | AY11: =AH11/sum($Z11:$AP11) -> 0.10193106 | ... BG11: =AP11/sum($Z11:$AP11) -> 0.064261412 | BH11: 44 | BI11: 3050.172 | BJ11: 1.4876924 | BK11: 4155520 | BL11: =BI11*1000/BK11 -> 0.73400489 | BM11: 32.57 | BN11: 36.32 | BO11: 11382 | BP11: 414 | BQ11: 320 | BR11: 310171 | BS11: 87054 | BT11: 4036 | BU11: 13680 | DA11: 408 | DB11: 249 | DC11: 657 | DD11: 16544 | DE11: 150239 | DF11: 136253 | DG11: 30530 | DH11: 166783 | DI11: 9665342982 | DJ11: 777284513 | DK11: 10442627495 | DL11: 2309612411 | DM11: 340304548 | DN11: 2649916959 | DO11: 13092544454 | DP11: 101760034034 | DQ11: 191481513754 | DR11: =DQ11-DP11 -> 89721479720 | DS11: 88241194262 | DT11: 323 | DU11: 334 | DV11: =DH11/DC11 -> 253.8554 | DW11: =DF11/DH11 -> 0.81694777 | DX11: =DH11/DP11 -> 1.6389833e-06 | DY11: =DH11/DQ11 -> 8.7101359e-07 | DZ11: =DH11/DR11 -> 1.8588971e-06 | EA11: =DH11/DS11 -> 1.8900809e-06 | EB11: =DO11/DP11 -> 0.12866097 | EC11: =DO11/DQ11 -> 0.068374979 | ED11: =DO11/DR11 -> 0.1459243 | EE11: =DO11/DS11 -> 0.14837225 | EF11: =DO11/DH11 -> 78500.473 | EG11: =DQ11/DH11 -> 1148087.7 | EH11: =DR11/DH11 -> 537953.39 | EI11: =DS11/DH11 -> 529077.87 | EJ11: =DP11/DQ11 -> 0.53143529 | EK11: =DR11/DQ11 -> 0.46856471 | EL11: =DS11/DQ11 -> 0.46083401 | EM11: =DK11/DO11 -> 0.79760107 | EN11: =DN11/DO11 -> 0.20239893 | EO11: =DI11/DF11 -> 70936.735 | EP11: =DL11/DG11 -> 75650.587 | EQ11: =DT11/DC11 -> 0.49162861 | ER11: =DU11/DC11 -> 0.50837139 | FD11: 190111.1 | FE11: 190111100 | FF11: 79348156 | FG11: =(FF11/FE11)*100 -> 41.737782 | FH11: 4.55 | FI11: 51.8 | FJ11: 934 | FK11: =FD11/L11 -> 0.1644564 | FL11: -1.14 | FM11: 6.02 | FN11: 5.83 | FO11: 4.29 | FP11: 130.8 | FQ11: 163.1 | FR11: 10 | FS11: 4.2 | FT11: 18217 | FU11: 18260.6 | FV11: 16715.5 | FW11: =FU11-FV11 -> 1545.1 | FX11: 1234.1 | FY11: 4 | FZ11: 14875.93 | GA11: 119.9
A12: DKI Jakarta | B12: 2022 | C12: 1655 | D12: 63.12 | E12: 0.416744 | F12: =D12-E12 -> 62.703256 | G12: 1858151 | H12: =D12*L12/100 -> 3077164.4 | I12: 0.63566561 | J12: 0.56201476 | K12: =I12-J12 -> 0.07365085 | L12: 4875102 | M12: 7.18 | N12: 7.5 | O12: 6.65 | P12: 63.08 | Q12: 80.02 | R12: 46.62 | S12: 1183102 | T12: 2923158 | U12: 242452 | V12: 131936 | W12: =100-X12-Y12 -> 81.81 | X12: 15.48 | Y12: 2.71 | Z12: 25474 | AA12: 17005 | AB12: 500278 | AC12: 14533 | AD12: 18719 | AE12: 218962 | AF12: 1177618 | AG12: 598473 | AH12: 603860 | AI12: 125605 | AJ12: 209146 | AK12: 94734 | AL12: 278664 | AM12: 202342 | AN12: 207039 | AO12: 120537 | AP12: 462113 | AQ12: =Z12/sum(Z12:AP12) -> 0.0052253266 | AR12: =AA12/sum($Z12:$AP12) -> 0.0034881321 | AS12: =AB12/sum($Z12:$AP12) -> 0.10261898 | AT12: =AC12/sum($Z12:$AP12) -> 0.0029810658 | AU12: =AD12/sum($Z12:$AP12) -> 0.0038397145 | AV12: =AE12/sum($Z12:$AP12) -> 0.044914342 | AW12: =AF12/sum($Z12:$AP12) -> 0.24155761 | AX12: =AG12/sum($Z12:$AP12) -> 0.12276112 | AY12: =AH12/sum($Z12:$AP12) -> 0.12386613 | ... BG12: =AP12/sum($Z12:$AP12) -> 0.094790427 | BH12: 44 | BI12: 4641.854 | BJ12: 5.1100072 | BK12: 5255824 | BL12: =BI12*1000/BK12 -> 0.88318292 | BM12: 36.82 | BN12: 36.88 | BO12: 36647 | BP12: 919 | BQ12: 499 | BR12: 1735860 | BS12: 362562 | BT12: 18116 | BU12: 49475 | DA12: 1134 | DB12: 475 | DC12: 1609 | DD12: 45692 | DE12: 204332 | DF12: 199411 | DG12: 50613 | DH12: 250024 | DI12: 11123576269 | DJ12: 523340072 | DK12: 11646916341 | DL12: 4314758321 | DM12: 251690746 | DN12: 4566449067 | DO12: 16213365408 | DP12: 281738511256 | DQ12: 491567212461 | DR12: =DQ12-DP12 -> 209828701205 | DS12: 208718425904 | DT12: 1487 | DU12: 122 | DV12: =DH12/DC12 -> 155.39093 | DW12: =DF12/DH12 -> 0.79756743 | DX12: =DH12/DP12 -> 8.8743281e-07 | DY12: =DH12/DQ12 -> 5.0862627e-07 | DZ12: =DH12/DR12 -> 1.1915624e-06 | EA12: =DH12/DS12 -> 1.1979009e-06 | EB12: =DO12/DP12 -> 0.057547565 | EC12: =DO12/DQ12 -> 0.032983008 | ED12: =DO12/DR12 -> 0.077269531 | EE12: =DO12/DS12 -> 0.077680566 | EF12: =DO12/DH12 -> 64847.236 | EG12: =DQ12/DH12 -> 1966080.1 | EH12: =DR12/DH12 -> 839234.24 | EI12: =DS12/DH12 -> 834793.56 | EJ12: =DP12/DQ12 -> 0.57314342 | EK12: =DR12/DQ12 -> 0.42685658 | EL12: =DS12/DQ12 -> 0.42459794 | EM12: =DK12/DO12 -> 0.71835279 | EN12: =DN12/DO12 -> 0.28164721 | EO12: =DI12/DF12 -> 55782.16 | EP12: =DL12/DG12 -> 85250.001 | EQ12: =DT12/DC12 -> 0.92417651 | ER12: =DU12/DC12 -> 0.075823493 | FD12: 1953489 | FE12: 1953489000 | FF12: 2.2874159e+08 | FG12: =(FF12/FE12)*100 -> 11.709387 | FH12: 5.88 | FI12: 51.8 | FJ12: 3744.1 | FK12: =FD12/L12 -> 0.40070731 | FL12: 2.27 | FM12: 6.02 | FN12: 5.89 | FO12: 4.31 | FP12: 130.8 | FQ12: 163.1 | FR12: 10 | FS12: 4.2 | FT12: 11502.7 | FU12: 19962.9 | FV12: 100108.1 | FW12: =FU12-FV12 -> -80145.2 | FX12: 77566 | FY12: 4 | FZ12: 14875.93 | GA12: 119.9
A13: Jawa Barat | B13: 2022 | C13: 4629 | D13: 45.39 | E13: 0.29916394 | F13: =D13-E13 -> 45.090836 | G13: 5740015 | H13: =D13*L13/100 -> 10645121 | I13: 0.58296511 | J13: 0.61476186 | K13: =I13-J13 -> -0.031796746 | L13: 23452568 | M13: 8.31 | N13: 8.55 | O13: 7.89 | P13: 66.15 | Q13: 83.93 | R13: 48.01 | S13: 5139406 | T13: 9846241 | U13: 2077898 | V13: 1318780 | W13: =100-X13-Y13 -> 73.88 | X13: 20.5 | Y13: 5.62 | Z13: 3585851 | AA13: 147242 | AB13: 4522840 | AC13: 58362 | AD13: 149206 | AE13: 1710514 | AF13: 5439021 | AG13: 1218505 | AH13: 2148541 | AI13: 260602 | AJ13: 352782 | AK13: 136561 | AL13: 503286 | AM13: 566135 | AN13: 1024834 | AO13: 333273 | AP13: 1295013 | AQ13: =Z13/sum(Z13:AP13) -> 0.15289801 | AR13: =AA13/sum($Z13:$AP13) -> 0.006278289 | AS13: =AB13/sum($Z13:$AP13) -> 0.19285052 | AT13: =AC13/sum($Z13:$AP13) -> 0.0024885121 | AU13: =AD13/sum($Z13:$AP13) -> 0.0063620325 | AV13: =AE13/sum($Z13:$AP13) -> 0.072935041 | AW13: =AF13/sum($Z13:$AP13) -> 0.2319158 | AX13: =AG13/sum($Z13:$AP13) -> 0.051956144 | AY13: =AH13/sum($Z13:$AP13) -> 0.091612185 | ... BG13: =AP13/sum($Z13:$AP13) -> 0.055218388 | BH13: 42 | BI13: 1841.4873 | BJ13: 1.7198844 | BK13: 3533613 | BL13: =BI13*1000/BK13 -> 0.52113441 | BM13: 48.57 | BN13: 54.61 | BO13: 292753 | BP13: 7624 | BQ13: 6979 | BR13: 4203172 | BS13: 988063 | BT13: 46782 | BU13: 159117 | DA13: 5422 | DB13: 3292 | DC13: 8714 | DD13: 218730 | DE13: 1675154 | DF13: 1621420 | DG13: 272463 | DH13: 1893883 | DI13: 84854901379 | DJ13: 4609404736 | DK13: 89464306115 | DL13: 22038333959 | DM13: 1820909372 | DN13: 23859243331 | DO13: 113323549446 | DP13: 1048762806704 | DQ13: 2010401338411 | DR13: =DQ13-DP13 -> 961638531707 | DS13: 954400094642 | DT13: 7489 | DU13: 1225 | DV13: =DH13/DC13 -> 217.33796 | DW13: =DF13/DH13 -> 0.85613525 | DX13: =DH13/DP13 -> 1.8058259e-06 | DY13: =DH13/DQ13 -> 9.4204225e-07 | DZ13: =DH13/DR13 -> 1.9694334e-06 | EA13: =DH13/DS13 -> 1.9843701e-06 | EB13: =DO13/DP13 -> 0.10805451 | EC13: =DO13/DQ13 -> 0.05636862 | ED13: =DO13/DR13 -> 0.11784423 | EE13: =DO13/DS13 -> 0.11873799 | EF13: =DO13/DH13 -> 59836.616 | EG13: =DQ13/DH13 -> 1061523.5 | EH13: =DR13/DH13 -> 507760.26 | EI13: =DS13/DH13 -> 503938.26 | EJ13: =DP13/DQ13 -> 0.52166838 | EK13: =DR13/DQ13 -> 0.47833162 | EL13: =DS13/DQ13 -> 0.47473113 | EM13: =DK13/DO13 -> 0.78945909 | EN13: =DN13/DO13 -> 0.21054091 | EO13: =DI13/DF13 -> 52333.696 | EP13: =DL13/DG13 -> 80885.603 | EQ13: =DT13/DC13 -> 0.85942162 | ER13: =DU13/DC13 -> 0.14057838 | FD13: 1589984.9 | FE13: 1589984900 | FF13: 6.8342025e+08 | FG13: =(FF13/FE13)*100 -> 42.982814 | FH13: 7 | FI13: 51.8 | FJ13: 6534.5 | FK13: =FD13/L13 -> 0.06779577 | FL13: 0.33 | FM13: 6.02 | FN13: 5.87 | FO13: 4.27 | FP13: 130.8 | FQ13: 163.1 | FR13: 10 | FS13: 4.2 | FT13: 38546.6 | FU13: 35808.3 | FV13: 8661.1 | FW13: =FU13-FV13 -> 27147.2 | FX13: 17681.7 | FY13: 4 | FZ13: 14875.93 | GA13: 119.9
A14: Jawa Tengah | B14: 2022 | C14: 467 | D14: 39.84 | E14: 0.27466822 | F14: =D14-E14 -> 39.565332 | G14: 3097275 | H14: =D14*L14/100 -> 7326758.9 | I14: 0.45749959 | J14: 0.43353259 | K14: =I14-J14 -> 0.023967001 | L14: 18390459 | M14: 5.57 | N14: 5.75 | O14: 5.31 | P14: 70.84 | Q14: 83.74 | R14: 58.31 | S14: 3922691 | T14: 6770006 | U14: 2261830 | V14: 991581 | W14: =100-X14-Y14 -> 71.41 | X14: 23.2 | Y14: 5.39 | Z14: 4557468 | AA14: 84993 | AB14: 4025810 | AC14: 27545 | AD14: 57093 | AE14: 1482142 | AF14: 3565465 | AG14: 512175 | AH14: 1405347 | AI14: 103731 | AJ14: 201499 | AK14: 17209 | AL14: 177173 | AM14: 357097 | AN14: 749980 | AO14: 249877 | AP14: 815855 | AQ14: =Z14/sum(Z14:AP14) -> 0.24781698 | AR14: =AA14/sum($Z14:$AP14) -> 0.0046215812 | AS14: =AB14/sum($Z14:$AP14) -> 0.21890753 | AT14: =AC14/sum($Z14:$AP14) -> 0.0014977875 | AU14: =AD14/sum($Z14:$AP14) -> 0.0031044902 | AV14: =AE14/sum($Z14:$AP14) -> 0.080592986 | AW14: =AF14/sum($Z14:$AP14) -> 0.1938758 | AX14: =AG14/sum($Z14:$AP14) -> 0.027850039 | AY14: =AH14/sum($Z14:$AP14) -> 0.076417179 | ... BG14: =AP14/sum($Z14:$AP14) -> 0.044362949 | BH14: 42 | BI14: 1812.9354 | BJ14: 0.77579055 | BK14: 2200716 | BL14: =BI14*1000/BK14 -> 0.82379345 | BM14: 49.99 | BN14: 60.16 | BO14: 111970 | BP14: 12269 | BQ14: 11639 | BR14: 3128875 | BS14: 544331 | BT14: 19204 | BU14: 77386 | DA14: 2936 | DB14: 1483 | DC14: 4419 | DD14: 101848 | DE14: 1070684 | DF14: 1047281 | DG14: 125251 | DH14: 1172532 | DI14: 37852635657 | DJ14: 2029117558 | DK14: 39881753215 | DL14: 7086941006 | DM14: 764390117 | DN14: 7851331123 | DO14: 47733084338 | DP14: 313227608019 | DQ14: 634748049891 | DR14: =DQ14-DP14 -> 321520441872 | DS14: 313952880091 | DT14: 3973 | DU14: 446 | DV14: =DH14/DC14 -> 265.33876 | DW14: =DF14/DH14 -> 0.89317903 | DX14: =DH14/DP14 -> 3.7433865e-06 | DY14: =DH14/DQ14 -> 1.84724e-06 | DZ14: =DH14/DR14 -> 3.646835e-06 | EA14: =DH14/DS14 -> 3.7347388e-06 | EB14: =DO14/DP14 -> 0.15239105 | EC14: =DO14/DQ14 -> 0.075200049 | ED14: =DO14/DR14 -> 0.1484605 | EE14: =DO14/DS14 -> 0.15203901 | EF14: =DO14/DH14 -> 40709.409 | EG14: =DQ14/DH14 -> 541348.17 | EH14: =DR14/DH14 -> 274210.38 | EI14: =DS14/DH14 -> 267756.34 | EJ14: =DP14/DQ14 -> 0.49346762 | EK14: =DR14/DQ14 -> 0.50653238 | EL14: =DS14/DQ14 -> 0.49461023 | EM14: =DK14/DO14 -> 0.83551595 | EN14: =DN14/DO14 -> 0.16448405 | EO14: =DI14/DF14 -> 36143.724 | EP14: =DL14/DG14 -> 56581.912 | EQ14: =DT14/DC14 -> 0.89907219 | ER14: =DU14/DC14 -> 0.10092781 | FD14: 1050278.1 | FE14: 1.0502781e+09 | FF14: 3.4616965e+08 | FG14: =(FF14/FE14)*100 -> 32.959809 | FH14: 3.88 | FI14: 51.8 | FJ14: 2362 | FK14: =FD14/L14 -> 0.057109945 | FL14: 2.14 | FM14: 6.02 | FN14: 5.63 | FO14: 4.09 | FP14: 130.8 | FQ14: 163.1 | FR14: 10 | FS14: 4.2 | FT14: 11740.2 | FU14: 12362.9 | FV14: 14428.6 | FW14: =FU14-FV14 -> -2065.7 | FX14: 16130.5 | FY14: 4 | FZ14: 14875.93 | GA14: 119.9
A15: DI Yogyakarta | B15: 2022 | C15: 113 | D15: 46.62 | E15: 0.34176924 | F15: =D15-E15 -> 46.278231 | G15: 466370 | H15: =D15*L15/100 -> 1044815.3 | I15: 0.4847009 | J15: 0.46780594 | K15: =I15-J15 -> 0.016894965 | L15: 2241131 | M15: 4.06 | N15: 3.9 | O15: 4.27 | P15: 72.6 | Q15: 82.22 | R15: 63.38 | S15: 468305 | T15: 962181 | U15: 269489 | V15: 106775 | W15: =100-X15-Y15 -> 67.06 | X15: 28.18 | Y15: 4.76 | Z15: 402044 | AA15: 6939 | AB15: 387207 | AC15: 1568 | AD15: 7272 | AE15: 159070 | AF15: 444742 | AG15: 100671 | AH15: 225614 | AI15: 22693 | AJ15: 24400 | AK15: 4693 | AL15: 52282 | AM15: 67735 | AN15: 141321 | AO15: 53210 | AP15: 139670 | AQ15: =Z15/sum(Z15:AP15) -> 0.17939335 | AR15: =AA15/sum($Z15:$AP15) -> 0.0030962045 | AS15: =AB15/sum($Z15:$AP15) -> 0.17277303 | AT15: =AC15/sum($Z15:$AP15) -> 0.00069964674 | AU15: =AD15/sum($Z15:$AP15) -> 0.0032447902 | AV15: =AE15/sum($Z15:$AP15) -> 0.070977556 | AW15: =AF15/sum($Z15:$AP15) -> 0.19844534 | AX15: =AG15/sum($Z15:$AP15) -> 0.04491973 | AY15: =AH15/sum($Z15:$AP15) -> 0.10066971 | ... BG15: =AP15/sum($Z15:$AP15) -> 0.062321212 | BH15: 40 | BI15: 1840.9155 | BJ15: 4.3011632 | BK15: 2462583 | BL15: =BI15*1000/BK15 -> 0.74755471 | BM15: 44.19 | BN15: 53.38 | BO15: 13310 | BP15: 1825 | BQ15: 1704 | BR15: 364326 | BS15: 63441 | BT15: 2086 | BU15: 8253 | DA15: 425 | DB15: 132 | DC15: 557 | DD15: 14437 | DE15: 65329 | DF15: 68730 | DG15: 11036 | DH15: 79766 | DI15: 2282222594 | DJ15: 158259089 | DK15: 2440481683 | DL15: 568953912 | DM15: 56467038 | DN15: 625420950 | DO15: 3065902633 | DP15: 9267062908 | DQ15: 22600612278 | DR15: =DQ15-DP15 -> 13333549370 | DS15: 13168113764 | DT15: 503 | DU15: 54 | DV15: =DH15/DC15 -> 143.20646 | DW15: =DF15/DH15 -> 0.86164531 | DX15: =DH15/DP15 -> 8.6074737e-06 | DY15: =DH15/DQ15 -> 3.5293734e-06 | DZ15: =DH15/DR15 -> 5.9823531e-06 | EA15: =DH15/DS15 -> 6.0575115e-06 | EB15: =DO15/DP15 -> 0.33083866 | EC15: =DO15/DQ15 -> 0.13565573 | ED15: =DO15/DR15 -> 0.22993897 | EE15: =DO15/DS15 -> 0.23282778 | EF15: =DO15/DH15 -> 38436.209 | EG15: =DQ15/DH15 -> 283336.41 | EH15: =DR15/DH15 -> 167158.31 | EI15: =DS15/DH15 -> 165084.29 | EJ15: =DP15/DQ15 -> 0.41003592 | EK15: =DR15/DQ15 -> 0.58996408 | EL15: =DS15/DQ15 -> 0.58264412 | EM15: =DK15/DO15 -> 0.79600756 | EN15: =DN15/DO15 -> 0.20399244 | EO15: =DI15/DF15 -> 33205.625 | EP15: =DL15/DG15 -> 51554.36 | EQ15: =DT15/DC15 -> 0.90305206 | ER15: =DU15/DC15 -> 0.096947935 | FD15: 112901.3 | FE15: 112901300 | FF15: 12890390 | FG15: =(FF15/FE15)*100 -> 11.417397 | FH15: 1.76 | FI15: 51.8 | FJ15: 113.9 | FK15: =FD15/L15 -> 0.05037693 | FL15: 4.55 | FM15: 6.02 | FN15: 6.29 | FO15: 4.59 | FP15: 130.8 | FQ15: 163.1 | FR15: 10 | FS15: 4.2 | FT15: 581.6 | FU15: 536 | FV15: 63 | FW15: =FU15-FV15 -> 473 | FX15: 1320.4 | FY15: 4 | FZ15: 14875.93 | GA15: 119.9
A16: Jawa Timur | B16: 2022 | C16: 3574 | D16: 36.14 | E16: 0.26344642 | F16: =D16-E16 -> 35.876554 | G16: 3713936 | H16: =D16*L16/100 -> 7811044.1 | I16: 0.51467058 | J16: 0.45991361 | K16: =I16-J16 -> 0.054756974 | L16: 21613293 | M16: 5.49 | N16: 5.74 | O16: 5.13 | P16: 71.23 | Q16: 85.76 | R16: 57.28 | S16: 4436795 | T16: 7216142 | U16: 3108951 | V16: 1246057 | W16: =100-X16-Y16 -> 66.2 | X16: 28.03 | Y16: 5.77 | Z16: 6766440 | AA16: 108273 | AB16: 3221241 | AC16: 43101 | AD16: 69351 | AE16: 1396816 | AF16: 4340444 | AG16: 705855 | AH16: 1556876 | AI16: 126854 | AJ16: 204139 | AK16: 37368 | AL16: 285802 | AM16: 462128 | AN16: 998127 | AO16: 313930 | AP16: 976548 | AQ16: =Z16/sum(Z16:AP16) -> 0.31306844 | AR16: =AA16/sum($Z16:$AP16) -> 0.0050095559 | AS16: =AB16/sum($Z16:$AP16) -> 0.14903981 | AT16: =AC16/sum($Z16:$AP16) -> 0.0019941894 | AU16: =AD16/sum($Z16:$AP16) -> 0.0032087197 | AV16: =AE16/sum($Z16:$AP16) -> 0.064627634 | AW16: =AF16/sum($Z16:$AP16) -> 0.20082289 | AX16: =AG16/sum($Z16:$AP16) -> 0.032658374 | AY16: =AH16/sum($Z16:$AP16) -> 0.072033262 | ... BG16: =AP16/sum($Z16:$AP16) -> 0.045182749 | BH16: 41 | BI16: 1891.5671 | BJ16: 1.2195162 | BK16: 2638752 | BL16: =BI16*1000/BK16 -> 0.71684157 | BM16: 50.73 | BN16: 63.86 | BO16: 95978 | BP16: 8497 | BQ16: 8073 | BR16: 2919531 | BS16: 633773 | BT16: 26691 | BU16: 58254 | DA16: 4535 | DB16: 1763 | DC16: 6298 | DD16: 159337 | DE16: 814816 | DF16: 803823 | DG16: 170320 | DH16: 974143 | DI16: 36540371120 | DJ16: 1649052621 | DK16: 38189423741 | DL16: 11201234381 | DM16: 731213480 | DN16: 11932447861 | DO16: 50121871602 | DP16: 584879871386 | DQ16: 1041827274222 | DR16: =DQ16-DP16 -> 456947402836 | DS16: 447184958620 | DT16: 5914 | DU16: 384 | DV16: =DH16/DC16 -> 154.67498 | DW16: =DF16/DH16 -> 0.82515914 | DX16: =DH16/DP16 -> 1.6655437e-06 | DY16: =DH16/DQ16 -> 9.3503311e-07 | DZ16: =DH16/DR16 -> 2.1318493e-06 | EA16: =DH16/DS16 -> 2.1783895e-06 | EB16: =DO16/DP16 -> 0.085696011 | EC16: =DO16/DQ16 -> 0.048109579 | ED16: =DO16/DR16 -> 0.10968849 | EE16: =DO16/DS16 -> 0.11208309 | EF16: =DO16/DH16 -> 51452.273 | EG16: =DQ16/DH16 -> 1069480.8 | EH16: =DR16/DH16 -> 469076.31 | EI16: =DS16/DH16 -> 459054.74 | EJ16: =DP16/DQ16 -> 0.56139812 | EK16: =DR16/DQ16 -> 0.43860188 | EL16: =DS16/DQ16 -> 0.42923138 | EM16: =DK16/DO16 -> 0.76193132 | EN16: =DN16/DO16 -> 0.23806868 | EO16: =DI16/DF16 -> 45458.23 | EP16: =DL16/DG16 -> 65765.82 | EQ16: =DT16/DC16 -> 0.93902826 | ER16: =DU16/DC16 -> 0.060971737 | FD16: 1757874.9 | FE16: 1757874900 | FF16: 5.3639403e+08 | FG16: =(FF16/FE16)*100 -> 30.513777 | FH16: 6.27 | FI16: 51.8 | FJ16: 3134 | FK16: =FD16/L16 -> 0.081333044 | FL16: 2.53 | FM16: 6.02 | FN16: 6.13 | FO16: 4.5 | FP16: 130.8 | FQ16: 163.1 | FR16: 10 | FS16: 4.2 | FT16: 24963.2 | FU16: 25898.6 | FV16: 31946.5 | FW16: =FU16-FV16 -> -6047.9 | FX16: 19233.8 | FY16: 4 | FZ16: 14875.93 | GA16: 119.9
A17: Banten | B17: 2022 | C17: 3703 | D17: 52.04 | E17: 0.34930725 | F17: =D17-E17 -> 51.690693 | G17: 2002153 | H17: =D17*L17/100 -> 3091497.6 | I17: 0.67605884 | J17: 0.71547278 | K17: =I17-J17 -> -0.039413935 | L17: 5940618 | M17: 8.09 | N17: 7.39 | O17: 9.35 | P17: 64.72 | Q17: 81.69 | R17: 47.17 | S17: 1302970 | T17: 2961507 | U17: 473435 | V17: 271703 | W17: =100-X17-Y17 -> 76.98 | X17: 18.45 | Y17: 4.57 | Z17: 670880 | AA17: 38623 | AB17: 1368588 | AC17: 22227 | AD17: 56523 | AE17: 353551 | AF17: 1240325 | AG17: 410961 | AH17: 461408 | AI17: 71074 | AJ17: 116204 | AK17: 70604 | AL17: 211101 | AM17: 141346 | AN17: 283139 | AO17: 93029 | AP17: 331035 | AQ17: =Z17/sum(Z17:AP17) -> 0.11293101 | AR17: =AA17/sum($Z17:$AP17) -> 0.0065015121 | AS17: =AB17/sum($Z17:$AP17) -> 0.23037805 | AT17: =AC17/sum($Z17:$AP17) -> 0.0037415299 | AU17: =AD17/sum($Z17:$AP17) -> 0.0095146667 | AV17: =AE17/sum($Z17:$AP17) -> 0.059514178 | AW17: =AF17/sum($Z17:$AP17) -> 0.2087872 | AX17: =AG17/sum($Z17:$AP17) -> 0.069178156 | AY17: =AH17/sum($Z17:$AP17) -> 0.077670034 | ... BG17: =AP17/sum($Z17:$AP17) -> 0.055724 | BH17: 42 | BI17: 2501.2031 | BJ17: 1.6337516 | BK17: 4370278 | BL17: =BI17*1000/BK17 -> 0.57232128 | BM17: 42.5 | BN17: 47.96 | BO17: 58778 | BP17: 1473 | BQ17: 1265 | BR17: 1412620 | BS17: 354431 | BT17: 20709 | BU17: 50271 | DA17: 2269 | DB17: 1557 | DC17: 3826 | DD17: 108033 | DE17: 708364 | DF17: 687697 | DG17: 128700 | DH17: 816397 | DI17: 37163271204 | DJ17: 1894329577 | DK17: 39057600781 | DL17: 10173136678 | DM17: 983149570 | DN17: 11156286248 | DO17: 50213887029 | DP17: 625806114712 | DQ17: 1087303142410 | DR17: =DQ17-DP17 -> 461497027698 | DS17: 458588270958 | DT17: 3384 | DU17: 442 | DV17: =DH17/DC17 -> 213.38134 | DW17: =DF17/DH17 -> 0.84235611 | DX17: =DH17/DP17 -> 1.3045526e-06 | DY17: =DH17/DQ17 -> 7.508458e-07 | DZ17: =DH17/DR17 -> 1.769019e-06 | EA17: =DH17/DS17 -> 1.7802396e-06 | EB17: =DO17/DP17 -> 0.080238729 | EC17: =DO17/DQ17 -> 0.046182049 | ED17: =DO17/DR17 -> 0.10880652 | EE17: =DO17/DS17 -> 0.10949667 | EF17: =DO17/DH17 -> 61506.702 | EG17: =DQ17/DH17 -> 1331831.4 | EH17: =DR17/DH17 -> 565285.06 | EI17: =DS17/DH17 -> 561722.14 | EJ17: =DP17/DQ17 -> 0.57555809 | EK17: =DR17/DQ17 -> 0.42444191 | EL17: =DS17/DQ17 -> 0.42176671 | EM17: =DK17/DO17 -> 0.77782468 | EN17: =DN17/DO17 -> 0.22217532 | EO17: =DI17/DF17 -> 54040.182 | EP17: =DL17/DG17 -> 79045.351 | EQ17: =DT17/DC17 -> 0.88447465 | ER17: =DU17/DC17 -> 0.11552535 | FD17: 484129.4 | FE17: 484129400 | FF17: 1.6063946e+08 | FG17: =(FF17/FE17)*100 -> 33.1811 | FH17: 3.6 | FI17: 51.8 | FJ17: 3410.7 | FK17: =FD17/L17 -> 0.081494787 | FL17: 0.75 | FM17: 6.02 | FN17: 5.08 | FO17: 3.75 | FP17: 130.8 | FQ17: 163.1 | FR17: 10 | FS17: 4.2 | FT17: 14084.2 | FU17: 14565.5 | FV17: 17688.7 | FW17: =FU17-FV17 -> -3123.2 | FX17: 3754.2 | FY17: 4 | FZ17: 14875.93 | GA17: 119.9
A18: Bali | B18: 2022 | C18: 706 | D18: 46.57 | E18: 0.36544958 | F18: =D18-E18 -> 46.20455 | G18: 630921 | H18: =D18*L18/100 -> 1214112.5 | I18: 0.5543902 | J18: 0.51377084 | K18: =I18-J18 -> 0.040619368 | L18: 2607070 | M18: 4.8 | N18: 5.17 | O18: 4.35 | P18: 76.86 | Q18: 84.06 | R18: 69.62 | S18: 449057 | T18: 1138045 | U18: 362084 | V18: 102339 | W18: =100-X18-Y18 -> 66.4 | X18: 29.67 | Y18: 3.93 | Z18: 518584 | AA18: 6250 | AB18: 403698 | AC18: 6480 | AD18: 8928 | AE18: 176488 | AF18: 553557 | AG18: 85949 | AH18: 314733 | AI18: 16943 | AJ18: 62632 | AK18: 3559 | AL18: 51297 | AM18: 125737 | AN18: 97073 | AO18: 60284 | AP18: 114878 | AQ18: =Z18/sum(Z18:AP18) -> 0.19891449 | AR18: =AA18/sum($Z18:$AP18) -> 0.0023973273 | AS18: =AB18/sum($Z18:$AP18) -> 0.1548474 | AT18: =AC18/sum($Z18:$AP18) -> 0.0024855489 | AU18: =AD18/sum($Z18:$AP18) -> 0.0034245341 | AV18: =AE18/sum($Z18:$AP18) -> 0.067695919 | AW18: =AF18/sum($Z18:$AP18) -> 0.21232917 | AX18: =AG18/sum($Z18:$AP18) -> 0.032967661 | AY18: =AH18/sum($Z18:$AP18) -> 0.12072288 | ... BG18: =AP18/sum($Z18:$AP18) -> 0.044064026 | BH18: 42 | BI18: 2516.971 | BJ18: 0.92105052 | BK18: 3002534 | BL18: =BI18*1000/BK18 -> 0.83828226 | BM18: 43.45 | BN18: 53.43 | BO18: 11851 | BP18: 1066 | BQ18: 978 | BR18: 449550 | BS18: 161362 | BT18: 3667 | BU18: 8597 | DA18: 359 | DB18: 66 | DC18: 425 | DD18: 12253 | DE18: 16412 | DF18: 22524 | DG18: 6141 | DH18: 28665 | DI18: 838582662 | DJ18: 93708837 | DK18: 932291499 | DL18: 363984991 | DM18: 37071302 | DN18: 401056293 | DO18: 1333347792 | DP18: 5171132885 | DQ18: 11396155395 | DR18: =DQ18-DP18 -> 6225022510 | DS18: 5990907704 | DT18: 375 | DU18: 50 | DV18: =DH18/DC18 -> 67.447059 | DW18: =DF18/DH18 -> 0.78576661 | DX18: =DH18/DP18 -> 5.5432727e-06 | DY18: =DH18/DQ18 -> 2.515322e-06 | DZ18: =DH18/DR18 -> 4.6048026e-06 | EA18: =DH18/DS18 -> 4.7847507e-06 | EB18: =DO18/DP18 -> 0.25784443 | EC18: =DO18/DQ18 -> 0.11699979 | ED18: =DO18/DR18 -> 0.21419164 | EE18: =DO18/DS18 -> 0.2225619 | EF18: =DO18/DH18 -> 46514.837 | EG18: =DQ18/DH18 -> 397563.42 | EH18: =DR18/DH18 -> 217164.57 | EI18: =DS18/DH18 -> 208997.3 | EJ18: =DP18/DQ18 -> 0.45376118 | EK18: =DR18/DQ18 -> 0.54623882 | EL18: =DS18/DQ18 -> 0.52569551 | EM18: =DK18/DO18 -> 0.69921104 | EN18: =DN18/DO18 -> 0.30078896 | EO18: =DI18/DF18 -> 37230.628 | EP18: =DL18/DG18 -> 59271.29 | EQ18: =DT18/DC18 -> 0.88235294 | ER18: =DU18/DC18 -> 0.11764706 | FD18: 150830.8 | FE18: 150830800 | FF18: 10240402 | FG18: =(FF18/FE18)*100 -> 6.7893309 | FH18: 5.56 | FI18: 51.8 | FJ18: 449.5 | FK18: =FD18/L18 -> 0.057854526 | FL18: -1.81 | FM18: 6.02 | FN18: 6.51 | FO18: 4.67 | FP18: 130.8 | FQ18: 163.1 | FR18: 10 | FS18: 4.2 | FT18: 617 | FU18: 574.7 | FV18: 115.7 | FW18: =FU18-FV18 -> 459 | FX18: 2406.5 | FY18: 4 | FZ18: 14875.93 | GA18: 119.9
A19: Nusa Tenggara Barat | B19: 2022 | C19: 396 | D19: 24.64 | E19: 0.19290546 | F19: =D19-E19 -> 24.447095 | G19: 388630 | H19: =D19*L19/100 -> 669800.21 | I19: 0.62288035 | J19: 0.52784637 | K19: =I19-J19 -> 0.095033983 | L19: 2718345 | M19: 2.89 | N19: 3.61 | O19: 1.91 | P19: 70.93 | Q19: 83.27 | R19: 59.16 | S19: 544562 | T19: 623924 | U19: 470125 | V19: 361473 | W19: =100-X19-Y19 -> 61.4 | X19: 25.3 | Y19: 13.3 | Z19: 939781 | AA19: 40748 | AB19: 274744 | AC19: 4500 | AD19: 7905 | AE19: 168178 | AF19: 599230 | AG19: 76649 | AH19: 130054 | AI19: 11814 | AJ19: 28698 | AK19: 1388 | AL19: 25834 | AM19: 111588 | AN19: 148439 | AO19: 39835 | AP19: 108960 | AQ19: =Z19/sum(Z19:AP19) -> 0.34571807 | AR19: =AA19/sum($Z19:$AP19) -> 0.014990003 | AS19: =AB19/sum($Z19:$AP19) -> 0.10107032 | AT19: =AC19/sum($Z19:$AP19) -> 0.001655419 | AU19: =AD19/sum($Z19:$AP19) -> 0.0029080194 | AV19: =AE19/sum($Z19:$AP19) -> 0.061867791 | AW19: =AF19/sum($Z19:$AP19) -> 0.22043927 | AX19: =AG19/sum($Z19:$AP19) -> 0.028196936 | AY19: =AH19/sum($Z19:$AP19) -> 0.047843081 | ... BG19: =AP19/sum($Z19:$AP19) -> 0.040083212 | BH19: 38 | BI19: 3016.738 | BJ19: 0.53099103 | BK19: 2218414 | BL19: =BI19*1000/BK19 -> 1.3598625 | BM19: 63.17 | BN19: 75.36 | BO19: 14393 | BP19: 1809 | BQ19: 1757 | BR19: 287204 | BS19: 87690 | BT19: 2353 | BU19: 4297 | DA19: 194 | DB19: 18 | DC19: 212 | DD19: 5632 | DE19: 3452 | DF19: 7560 | DG19: 1524 | DH19: 9084 | DI19: 156855095 | DJ19: 10504974 | DK19: 167360069 | DL19: 50583692 | DM19: 3666257 | DN19: 54249949 | DO19: 221610018 | DP19: 3437989190 | DQ19: 5065948264 | DR19: =DQ19-DP19 -> 1627959074 | DS19: 1599891485 | DT19: 212 | DV19: =DH19/DC19 -> 42.849057 | DW19: =DF19/DH19 -> 0.8322325 | DX19: =DH19/DP19 -> 2.6422422e-06 | DY19: =DH19/DQ19 -> 1.793149e-06 | DZ19: =DH19/DR19 -> 5.5799929e-06 | EA19: =DH19/DS19 -> 5.6778851e-06 | EB19: =DO19/DP19 -> 0.064459196 | EC19: =DO19/DQ19 -> 0.043745022 | ED19: =DO19/DR19 -> 0.13612751 | EE19: =DO19/DS19 -> 0.13851566 | EF19: =DO19/DH19 -> 24395.643 | EG19: =DQ19/DH19 -> 557678.14 | EH19: =DR19/DH19 -> 179211.7 | EI19: =DS19/DH19 -> 176121.92 | EJ19: =DP19/DQ19 -> 0.67864672 | EK19: =DR19/DQ19 -> 0.32135328 | EL19: =DS19/DQ19 -> 0.31581284 | EM19: =DK19/DO19 -> 0.75520083 | EN19: =DN19/DO19 -> 0.24479917 | EO19: =DI19/DF19 -> 20748.028 | EP19: =DL19/DG19 -> 33191.399 | EQ19: =DT19/DC19 -> 1 | ER19: =DU19/DC19 -> 0 | FD19: 102073.7 | FE19: 102073700 | FF19: 4530839 | FG19: =(FF19/FE19)*100 -> 4.4387918 | FH19: 1.98 | FI19: 51.8 | FJ19: 704.6 | FK19: =FD19/L19 -> 0.037549943 | FL19: 4.56 | FM19: 6.02 | FN19: 5.5 | FO19: 4.04 | FP19: 130.8 | FQ19: 163.1 | FR19: 10 | FS19: 4.2 | FT19: 3099.8 | FU19: 2746.9 | FV19: 563.6 | FW19: =FU19-FV19 -> 2183.3 | FX19: 973.4 | FY19: 4 | FZ19: 14875.93 | GA19: 119.9
A20: Nusa Tenggara Timur | B20: 2022 | C20: 62 | D20: 24.76 | E20: 0.18185505 | F20: =D20-E20 -> 24.578145 | G20: 449672 | H20: =D20*L20/100 -> 721826.55 | I20: 0.65568971 | J20: 0.6016084 | K20: =I20-J20 -> 0.054081302 | L20: 2915293 | M20: 3.54 | N20: 3.82 | O20: 3.22 | P20: 75.23 | Q20: 82.85 | R20: 67.87 | S20: 700707 | T20: 685800 | U20: 702912 | V20: 364493 | W20: =100-X20-Y20 -> 52.44 | X20: 35.06 | Y20: 12.5 | Z20: 1438901 | AA20: 26739 | AB20: 333352 | AC20: 4169 | AD20: 4498 | AE20: 122888 | AF20: 321427 | AG20: 127627 | AH20: 35697 | AI20: 6450 | AJ20: 24599 | AK20: 1436 | AL20: 23259 | AM20: 149320 | AN20: 181982 | AO20: 53436 | AP20: 59513 | AQ20: =Z20/sum(Z20:AP20) -> 0.49356994 | AR20: =AA20/sum($Z20:$AP20) -> 0.0091719769 | AS20: =AB20/sum($Z20:$AP20) -> 0.11434597 | AT20: =AC20/sum($Z20:$AP20) -> 0.0014300449 | AU20: =AD20/sum($Z20:$AP20) -> 0.0015428981 | AV20: =AE20/sum($Z20:$AP20) -> 0.042152881 | AW20: =AF20/sum($Z20:$AP20) -> 0.11025547 | AX20: =AG20/sum($Z20:$AP20) -> 0.043778447 | AY20: =AH20/sum($Z20:$AP20) -> 0.012244738 | ... BG20: =AP20/sum($Z20:$AP20) -> 0.020414072 | BH20: 40 | BI20: 2434.3282 | BJ20: 1.4430787 | BK20: 2100927 | BL20: =BI20*1000/BK20 -> 1.1586924 | BM20: 52.98 | BN20: 75.24 | BO20: 6132 | BP20: 478 | BQ20: 450 | BR20: 293801 | BS20: 106266 | BT20: 1816 | BU20: 3167 | DA20: 74 | DB20: 2 | DC20: 76 | DD20: 1217 | DE20: 249 | DF20: 1111 | DG20: 355 | DH20: 1466 | DI20: 21982282 | DJ20: 1061162 | DK20: 23043444 | DL20: 8192927 | DM20: 340357 | DN20: 8533284 | DO20: 31576728 | DP20: 152049601 | DQ20: 297338342 | DR20: =DQ20-DP20 -> 145288741 | DS20: 140809687 | DT20: 74 | DU20: 2 | DV20: =DH20/DC20 -> 19.289474 | DW20: =DF20/DH20 -> 0.75784447 | DX20: =DH20/DP20 -> 9.6415906e-06 | DY20: =DH20/DQ20 -> 4.9304102e-06 | DZ20: =DH20/DR20 -> 1.0090252e-05 | EA20: =DH20/DS20 -> 1.0411216e-05 | EB20: =DO20/DP20 -> 0.20767386 | EC20: =DO20/DQ20 -> 0.10619797 | ED20: =DO20/DR20 -> 0.21733775 | EE20: =DO20/DS20 -> 0.22425111 | EF20: =DO20/DH20 -> 21539.378 | EG20: =DQ20/DH20 -> 202822.88 | EH20: =DR20/DH20 -> 99105.553 | EI20: =DS20/DH20 -> 96050.264 | EJ20: =DP20/DQ20 -> 0.51136897 | EK20: =DR20/DQ20 -> 0.48863103 | EL20: =DS20/DQ20 -> 0.4735672 | EM20: =DK20/DO20 -> 0.72976035 | EN20: =DN20/DO20 -> 0.27023965 | EO20: =DI20/DF20 -> 19786.032 | EP20: =DL20/DG20 -> 23078.668 | EQ20: =DT20/DC20 -> 0.97368421 | ER20: =DU20/DC20 -> 0.026315789 | FD20: 72711.3 | FE20: 72711300 | FF20: 877992.3 | FG20: =(FF20/FE20)*100 -> 1.2075046 | FH20: 6.67 | FI20: 51.8 | FJ20: 73.3 | FK20: =FD20/L20 -> 0.024941335 | FL20: -0.72 | FM20: 6.02 | FN20: 6.65 | FO20: 4.76 | FP20: 130.8 | FQ20: 163.1 | FR20: 10 | FS20: 4.2 | FT20: 66.6 | FU20: 61.7 | FV20: 26.7 | FW20: =FU20-FV20 -> 35 | FX20: 779 | FY20: 4 | FZ20: 14875.93 | GA20: 119.9
A21: Kalimantan Barat | B21: 2022 | C21: 1131 | D21: 41.23 | E21: 0.26146285 | F21: =D21-E21 -> 40.968537 | G21: 488240 | H21: =D21*L21/100 -> 1054466.7 | I21: 0.49966023 | J21: 0.41714139 | K21: =I21-J21 -> 0.08251884 | L21: 2557523 | M21: 5.11 | N21: 5.11 | O21: 5.1 | P21: 68.97 | Q21: 85.01 | R21: 52.51 | S21: 575269 | T21: 977144 | U21: 361740 | V21: 184287 | W21: =100-X21-Y21 -> 64.13 | X21: 28.66 | Y21: 7.21 | Z21: 1237003 | AA21: 82800 | AB21: 124005 | AC21: 7592 | AD21: 3643 | AE21: 140750 | AF21: 365010 | AG21: 82779 | AH21: 130779 | AI21: 9056 | AJ21: 14803 | AK21: 3707 | AL21: 22598 | AM21: 98454 | AN21: 122432 | AO21: 36841 | AP21: 75271 | AQ21: =Z21/sum(Z21:AP21) -> 0.48367229 | AR21: =AA21/sum($Z21:$AP21) -> 0.032375075 | AS21: =AB21/sum($Z21:$AP21) -> 0.048486367 | AT21: =AC21/sum($Z21:$AP21) -> 0.0029684973 | AU21: =AD21/sum($Z21:$AP21) -> 0.0014244251 | AV21: =AE21/sum($Z21:$AP21) -> 0.055033718 | AW21: =AF21/sum($Z21:$AP21) -> 0.14272012 | AX21: =AG21/sum($Z21:$AP21) -> 0.032366864 | AY21: =AH21/sum($Z21:$AP21) -> 0.051135024 | ... BG21: =AP21/sum($Z21:$AP21) -> 0.029431211 | BH21: 40 | BI21: 2922.516 | BJ21: 0.66725231 | BK21: 2645920 | BL21: =BI21*1000/BK21 -> 1.1045368 | BM21: 41.39 | BN21: 58.77 | BO21: 11022 | BP21: 293 | BQ21: 205 | BR21: 398535 | BS21: 90514 | BT21: 3473 | BU21: 4417 | DA21: 110 | DB21: 121 | DC21: 231 | DD21: 5654 | DE21: 36823 | DF21: 33688 | DG21: 8789 | DH21: 42477 | DI21: 1978450892 | DJ21: 101213727 | DK21: 2079664619 | DL21: 544614423 | DM21: 70121595 | DN21: 614736018 | DO21: 2694400637 | DP21: 58518737534 | DQ21: 99859406113 | DR21: =DQ21-DP21 -> 41340668579 | DS21: 40481560388 | DT21: 196 | DU21: 35 | DV21: =DH21/DC21 -> 183.88312 | DW21: =DF21/DH21 -> 0.79308802 | DX21: =DH21/DP21 -> 7.2587007e-07 | DY21: =DH21/DQ21 -> 4.2536804e-07 | DZ21: =DH21/DR21 -> 1.027487e-06 | EA21: =DH21/DS21 -> 1.0492926e-06 | EB21: =DO21/DP21 -> 0.046043383 | EC21: =DO21/DQ21 -> 0.026981941 | ED21: =DO21/DR21 -> 0.065175546 | EE21: =DO21/DS21 -> 0.066558715 | EF21: =DO21/DH21 -> 63431.99 | EG21: =DQ21/DH21 -> 2350905.3 | EH21: =DR21/DH21 -> 973248.31 | EI21: =DS21/DH21 -> 953023.06 | EJ21: =DP21/DQ21 -> 0.58601127 | EK21: =DR21/DQ21 -> 0.41398873 | EL21: =DS21/DQ21 -> 0.40538555 | EM21: =DK21/DO21 -> 0.77184684 | EN21: =DN21/DO21 -> 0.22815316 | EO21: =DI21/DF21 -> 58728.654 | EP21: =DL21/DG21 -> 61965.459 | EQ21: =DT21/DC21 -> 0.84848485 | ER21: =DU21/DC21 -> 0.15151515 | FD21: 148368.9 | FE21: 148368900 | FF21: 23649170 | FG21: =(FF21/FE21)*100 -> 15.939439 | FH21: 4.04 | FI21: 51.8 | FJ21: 745.5 | FK21: =FD21/L21 -> 0.058012733 | FL21: 1.98 | FM21: 6.02 | FN21: 5.24 | FO21: 3.88 | FP21: 130.8 | FQ21: 163.1 | FR21: 10 | FS21: 4.2 | FT21: 2959.9 | FU21: 2696.4 | FV21: 605 | FW21: =FU21-FV21 -> 2091.4 | FX21: 1403.1 | FY21: 4 | FZ21: 14875.93 | GA21: 119.9
A22: Kalimantan Tengah | B22: 2022 | C22: 37 | D22: 48.5 | E22: 0.33480539 | F22: =D22-E22 -> 48.165195 | G22: 351078 | H22: =D22*L22/100 -> 652070.38 | I22: 0.57578501 | J22: 0.55787284 | K22: =I22-J22 -> 0.017912169 | L22: 1344475 | M22: 4.26 | N22: 3.95 | O22: 4.86 | P22: 67.23 | Q22: 85.17 | R22: 47.68 | S22: 323876 | T22: 609738 | U22: 146250 | V22: 72306 | W22: =100-X22-Y22 -> 70.77 | X22: 23.85 | Y22: 5.38 | Z22: 535714 | AA22: 96980 | AB22: 52860 | AC22: 3611 | AD22: 1986 | AE22: 63415 | AF22: 212667 | AG22: 37266 | AH22: 57171 | AI22: 3916 | AJ22: 8957 | AK22: 1263 | AL22: 16457 | AM22: 115591 | AN22: 73777 | AO22: 25255 | AP22: 37589 | AQ22: =Z22/sum(Z22:AP22) -> 0.3984559 | AR22: =AA22/sum($Z22:$AP22) -> 0.072132245 | AS22: =AB22/sum($Z22:$AP22) -> 0.039316462 | AT22: =AC22/sum($Z22:$AP22) -> 0.0026858067 | AU22: =AD22/sum($Z22:$AP22) -> 0.0014771565 | AV22: =AE22/sum($Z22:$AP22) -> 0.04716711 | AW22: =AF22/sum($Z22:$AP22) -> 0.15817847 | AX22: =AG22/sum($Z22:$AP22) -> 0.027717882 | AY22: =AH22/sum($Z22:$AP22) -> 0.042522918 | ... BG22: =AP22/sum($Z22:$AP22) -> 0.027958125 | BH22: 41 | BI22: 2906.4733 | BJ22: 1.0086967 | BK22: 3195306 | BL22: =BI22*1000/BK22 -> 0.90960719 | BM22: 40.98 | BN22: 51.5 | BO22: 10402 | BP22: 694 | BQ22: 682 | BR22: 273755 | BS22: 64090 | BT22: 2109 | BU22: 3359 | DA22: 53 | DB22: 113 | DC22: 166 | DD22: 2913 | DE22: 23996 | DF22: 20034 | DG22: 6875 | DH22: 26909 | DI22: 914074533 | DJ22: 122279683 | DK22: 1036354216 | DL22: 295055315 | DM22: 75574342 | DN22: 370629657 | DO22: 1406983873 | DP22: 88356775052 | DQ22: 117149731180 | DR22: =DQ22-DP22 -> 28792956128 | DS22: 26492267636 | DT22: 135 | DU22: 31 | DV22: =DH22/DC22 -> 162.10241 | DW22: =DF22/DH22 -> 0.74450927 | DX22: =DH22/DP22 -> 3.0454937e-07 | DY22: =DH22/DQ22 -> 2.296975e-07 | DZ22: =DH22/DR22 -> 9.3456885e-07 | EA22: =DH22/DS22 -> 1.0157303e-06 | EB22: =DO22/DP22 -> 0.015923893 | EC22: =DO22/DQ22 -> 0.012010133 | ED22: =DO22/DR22 -> 0.048865558 | EE22: =DO22/DS22 -> 0.053109228 | EF22: =DO22/DH22 -> 52286.739 | EG22: =DQ22/DH22 -> 4353552 | EH22: =DR22/DH22 -> 1070012.1 | EI22: =DS22/DH22 -> 984513.27 | EJ22: =DP22/DQ22 -> 0.75422089 | EK22: =DR22/DQ22 -> 0.24577911 | EL22: =DS22/DQ22 -> 0.22614023 | EM22: =DK22/DO22 -> 0.7365786 | EN22: =DN22/DO22 -> 0.2634214 | EO22: =DI22/DF22 -> 45626.162 | EP22: =DL22/DG22 -> 42917.137 | EQ22: =DT22/DC22 -> 0.81325301 | ER22: =DU22/DC22 -> 0.18674699 | FD22: 109094.7 | FE22: 109094700 | FF22: 16913220 | FG22: =(FF22/FE22)*100 -> 15.503246 | FH22: 4.63 | FI22: 51.8 | FJ22: 548.3 | FK22: =FD22/L22 -> 0.081142974 | FL22: 6.61 | FM22: 6.02 | FN22: 5.53 | FO22: 4.09 | FP22: 130.8 | FQ22: 163.1 | FR22: 10 | FS22: 4.2 | FT22: 5852.4 | FU22: 6151.9 | FV22: 8082.4 | FW22: =FU22-FV22 -> -1930.5 | FX22: 530 | FY22: 4 | FZ22: 14875.93 | GA22: 119.9
A23: Kalimantan Selatan | B23: 2022 | C23: 1199 | D23: 42.7 | E23: 0.29359526 | F23: =D23-E23 -> 42.406405 | G23: 428936 | H23: =D23*L23/100 -> 893380.07 | I23: 0.51062047 | J23: 0.51974196 | K23: =I23-J23 -> -0.0091214978 | L23: 2092225 | M23: 4.74 | N23: 4.87 | O23: 4.52 | P23: 67.55 | Q23: 82.97 | R23: 51.9 | S23: 540516 | T23: 840029 | U23: 270706 | V23: 141470 | W23: =100-X23-Y23 -> 59.98 | X23: 33.26 | Y23: 6.76 | Z23: 678086 | AA23: 86667 | AB23: 170244 | AC23: 6687 | AD23: 4563 | AE23: 113680 | AF23: 388261 | AG23: 80610 | AH23: 152999 | AI23: 8333 | AJ23: 16273 | AK23: 4179 | AL23: 31306 | AM23: 95825 | AN23: 114424 | AO23: 35162 | AP23: 104926 | AQ23: =Z23/sum(Z23:AP23) -> 0.32409803 | AR23: =AA23/sum($Z23:$AP23) -> 0.041423365 | AS23: =AB23/sum($Z23:$AP23) -> 0.081369834 | AT23: =AC23/sum($Z23:$AP23) -> 0.003196119 | AU23: =AD23/sum($Z23:$AP23) -> 0.0021809318 | AV23: =AE23/sum($Z23:$AP23) -> 0.0543345 | AW23: =AF23/sum($Z23:$AP23) -> 0.18557325 | AX23: =AG23/sum($Z23:$AP23) -> 0.038528361 | AY23: =AH23/sum($Z23:$AP23) -> 0.073127412 | ... BG23: =AP23/sum($Z23:$AP23) -> 0.050150438 | BH23: 41 | BI23: 3014.4972 | BJ23: 1.1108451 | BK23: 2898486 | BL23: =BI23*1000/BK23 -> 1.0400248 | BM23: 43.37 | BN23: 57.3 | BO23: 10290 | BP23: 980 | BQ23: 886 | BR23: 303362 | BS23: 73548 | BT23: 2785 | BU23: 7537 | DA23: 139 | DB23: 82 | DC23: 221 | DD23: 5355 | DE23: 28813 | DF23: 26553 | DG23: 7615 | DH23: 34168 | DI23: 1812444514 | DJ23: 344704802 | DK23: 2157149316 | DL23: 907561936 | DM23: 83301234 | DN23: 990863170 | DO23: 3148012486 | DP23: 35544211184 | DQ23: 54570103776 | DR23: =DQ23-DP23 -> 19025892592 | DS23: 18471265702 | DT23: 200 | DU23: 21 | DV23: =DH23/DC23 -> 154.60633 | DW23: =DF23/DH23 -> 0.77713065 | DX23: =DH23/DP23 -> 9.6128171e-07 | DY23: =DH23/DQ23 -> 6.2613038e-07 | DZ23: =DH23/DR23 -> 1.7958684e-06 | EA23: =DH23/DS23 -> 1.849792e-06 | EB23: =DO23/DP23 -> 0.088566109 | EC23: =DO23/DQ23 -> 0.057687493 | ED23: =DO23/DR23 -> 0.16545938 | EE23: =DO23/DS23 -> 0.17042755 | EF23: =DO23/DH23 -> 92133.355 | EG23: =DQ23/DH23 -> 1597111.4 | EH23: =DR23/DH23 -> 556833.66 | EI23: =DS23/DH23 -> 540601.31 | EJ23: =DP23/DQ23 -> 0.65134953 | EK23: =DR23/DQ23 -> 0.34865047 | EL23: =DS23/DQ23 -> 0.33848691 | EM23: =DK23/DO23 -> 0.68524166 | EN23: =DN23/DO23 -> 0.31475834 | EO23: =DI23/DF23 -> 68257.617 | EP23: =DL23/DG23 -> 119180.82 | EQ23: =DT23/DC23 -> 0.90497738 | ER23: =DU23/DC23 -> 0.095022624 | FD23: 142339.2 | FE23: 142339200 | FF23: 17855337 | FG23: =(FF23/FE23)*100 -> 12.544216 | FH23: 3.31 | FI23: 51.8 | FJ23: 208.1 | FK23: =FD23/L23 -> 0.068032453 | FL23: 5.97 | FM23: 6.02 | FN23: 7.08 | FO23: 5.2 | FP23: 130.8 | FQ23: 163.1 | FR23: 10 | FS23: 4.2 | FT23: 16204.3 | FU23: 14830.4 | FV23: 2929 | FW23: =FU23-FV23 -> 11901.4 | FX23: 1498.5 | FY23: 4 | FZ23: 14875.93 | GA23: 119.9
A24: Kalimantan Timur | B24: 2022 | C24: 3082 | D24: 55.74 | E24: 0.3704286 | F24: =D24-E24 -> 55.369571 | G24: 597300 | H24: =D24*L24/100 -> 973733.21 | I24: 0.65265208 | J24: 0.62695502 | K24: =I24-J24 -> 0.025697055 | L24: 1746920 | M24: 5.71 | N24: 5.12 | O24: 6.9 | P24: 64.73 | Q24: 82.74 | R24: 45.17 | S24: 418152 | T24: 915189 | U24: 139675 | V24: 84090 | W24: =100-X24-Y24 -> 73.69 | X24: 21.5 | Y24: 4.81 | Z24: 349451 | AA24: 130564 | AB24: 131400 | AC24: 7544 | AD24: 9333 | AE24: 105395 | AF24: 350429 | AG24: 104347 | AH24: 132798 | AI24: 10973 | AJ24: 20760 | AK24: 8776 | AL24: 55065 | AM24: 111964 | AN24: 100599 | AO24: 42318 | AP24: 75204 | AQ24: =Z24/sum(Z24:AP24) -> 0.20003835 | AR24: =AA24/sum($Z24:$AP24) -> 0.074739542 | AS24: =AB24/sum($Z24:$AP24) -> 0.075218098 | AT24: =AC24/sum($Z24:$AP24) -> 0.0043184576 | AU24: =AD24/sum($Z24:$AP24) -> 0.0053425457 | AV24: =AE24/sum($Z24:$AP24) -> 0.060331898 | AW24: =AF24/sum($Z24:$AP24) -> 0.2005982 | AX24: =AG24/sum($Z24:$AP24) -> 0.059731985 | AY24: =AH24/sum($Z24:$AP24) -> 0.076018364 | ... BG24: =AP24/sum($Z24:$AP24) -> 0.043049481 | BH24: 45 | BI24: 3310.723 | BJ24: 0 | BK24: 3963732 | BL24: =BI24*1000/BK24 -> 0.835254 | BM24: 36.54 | BN24: 44.26 | BO24: 13617 | BP24: 1784 | BQ24: 1661 | BR24: 556716 | BS24: 169532 | BT24: 7686 | BU24: 12271 | DA24: 146 | DB24: 136 | DC24: 282 | DD24: 6365 | DE24: 47798 | DF24: 44213 | DG24: 9950 | DH24: 54163 | DI24: 2631810910 | DJ24: 235162571 | DK24: 2866973481 | DL24: 751637142 | DM24: 132246916 | DN24: 883884058 | DO24: 3750857539 | DP24: 126713253928 | DQ24: 198219772570 | DR24: =DQ24-DP24 -> 71506518642 | DS24: 66550701901 | DT24: 249 | DU24: 33 | DV24: =DH24/DC24 -> 192.06738 | DW24: =DF24/DH24 -> 0.81629526 | DX24: =DH24/DP24 -> 4.2744542e-07 | DY24: =DH24/DQ24 -> 2.7324721e-07 | DZ24: =DH24/DR24 -> 7.5745542e-07 | EA24: =DH24/DS24 -> 8.1386069e-07 | EB24: =DO24/DP24 -> 0.029601146 | EC24: =DO24/DQ24 -> 0.018922721 | ED24: =DO24/DR24 -> 0.052454764 | EE24: =DO24/DS24 -> 0.056360901 | EF24: =DO24/DH24 -> 69251.288 | EG24: =DQ24/DH24 -> 3659689.7 | EH24: =DR24/DH24 -> 1320209.7 | EI24: =DS24/DH24 -> 1228711.5 | EJ24: =DP24/DQ24 -> 0.63925638 | EK24: =DR24/DQ24 -> 0.36074362 | EL24: =DS24/DQ24 -> 0.335742 | EM24: =DK24/DO24 -> 0.76435147 | EN24: =DN24/DO24 -> 0.23564853 | EO24: =DI24/DF24 -> 59525.726 | EP24: =DL24/DG24 -> 75541.421 | EQ24: =DT24/DC24 -> 0.88297872 | ER24: =DU24/DC24 -> 0.11702128 | FD24: 506158.9 | FE24: 506158900 | FF24: 99658390 | FG24: =(FF24/FE24)*100 -> 19.689151 | FH24: 3.57 | FI24: 51.8 | FJ24: 1266.2 | FK24: =FD24/L24 -> 0.28974361 | FL24: 2.9 | FM24: 6.02 | FN24: 4.44 | FO24: 3.29 | FP24: 130.8 | FQ24: 163.1 | FR24: 10 | FS24: 4.2 | FT24: 36464.9 | FU24: 33601.2 | FV24: 8272.4 | FW24: =FU24-FV24 -> 25328.8 | FX24: 3248.7 | FY24: 4 | FZ24: 14875.93 | GA24: 119.9
A25: Kalimantan Utara | B25: 2022 | C25: 238 | D25: 51 | E25: 0.34168402 | F25: =D25-E25 -> 50.658316 | G25: 113248 | H25: =D25*L25/100 -> 180531.84 | I25: 0.67678222 | J25: 0.58726605 | K25: =I25-J25 -> 0.089516174 | L25: 353984 | M25: 4.33 | N25: 4.79 | O25: 3.44 | P25: 67.62 | Q25: 83.67 | R25: 49.3 | S25: 76378 | T25: 167333 | U25: 41101 | V25: 21907 | W25: =100-X25-Y25 -> 69.46 | X25: 24.35 | Y25: 6.19 | Z25: 118121 | AA25: 12723 | AB25: 26732 | AC25: 1168 | AD25: 704 | AE25: 17930 | AF25: 52020 | AG25: 14146 | AH25: 22676 | AI25: 5947 | AJ25: 4069 | AK25: 312 | AL25: 4091 | AM25: 31062 | AN25: 22126 | AO25: 12054 | AP25: 8103 | AQ25: =Z25/sum(Z25:AP25) -> 0.33369022 | AR25: =AA25/sum($Z25:$AP25) -> 0.035942302 | AS25: =AB25/sum($Z25:$AP25) -> 0.075517538 | AT25: =AC25/sum($Z25:$AP25) -> 0.0032995842 | AU25: =AD25/sum($Z25:$AP25) -> 0.0019887905 | AV25: =AE25/sum($Z25:$AP25) -> 0.050652007 | AW25: =AF25/sum($Z25:$AP25) -> 0.14695579 | AX25: =AG25/sum($Z25:$AP25) -> 0.039962258 | AY25: =AH25/sum($Z25:$AP25) -> 0.064059393 | ... BG25: =AP25/sum($Z25:$AP25) -> 0.022890865 | BH25: 42 | BI25: 2390.739 | BJ25: 3.7777308 | BK25: 3427759 | BL25: =BI25*1000/BK25 -> 0.69746414 | BM25: 33.73 | BN25: 49 | BO25: 2370 | BP25: 404 | BQ25: 394 | BR25: 79825 | BS25: 41331 | BT25: 989 | BU25: 660 | DA25: 17 | DB25: 21 | DC25: 38 | DD25: 717 | DE25: 16130 | DF25: 12963 | DG25: 3884 | DH25: 16847 | DI25: 642119452 | DJ25: 6826698 | DK25: 648946150 | DL25: 214014265 | DM25: 6740820 | DN25: 220755085 | DO25: 869701235 | DP25: 6459824565 | DQ25: 9726954415 | DR25: =DQ25-DP25 -> 3267129850 | DS25: 3241844864 | DT25: 31 | DU25: 7 | DV25: =DH25/DC25 -> 443.34211 | DW25: =DF25/DH25 -> 0.7694545 | DX25: =DH25/DP25 -> 2.6079656e-06 | DY25: =DH25/DQ25 -> 1.7319913e-06 | DZ25: =DH25/DR25 -> 5.1565138e-06 | EA25: =DH25/DS25 -> 5.1967323e-06 | EB25: =DO25/DP25 -> 0.13463233 | EC25: =DO25/DQ25 -> 0.089411464 | ED25: =DO25/DR25 -> 0.26619733 | EE25: =DO25/DS25 -> 0.26827355 | EF25: =DO25/DH25 -> 51623.508 | EG25: =DQ25/DH25 -> 577370.12 | EH25: =DR25/DH25 -> 193929.47 | EI25: =DS25/DH25 -> 192428.61 | EJ25: =DP25/DQ25 -> 0.66411585 | EK25: =DR25/DQ25 -> 0.33588415 | EL25: =DS25/DQ25 -> 0.33328468 | EM25: =DK25/DO25 -> 0.74617136 | EN25: =DN25/DO25 -> 0.25382864 | EO25: =DI25/DF25 -> 49534.788 | EP25: =DL25/DG25 -> 55101.51 | EQ25: =DT25/DC25 -> 0.81578947 | ER25: =DU25/DC25 -> 0.18421053 | FD25: 66528.4 | FE25: 66528400 | FF25: 5768312.1 | FG25: =(FF25/FE25)*100 -> 8.6704507 | FH25: 3.83 | FI25: 51.8 | FJ25: 430.5 | FK25: =FD25/L25 -> 0.18794183 | FL25: 0.63 | FM25: 6.02 | FN25: 4.87 | FO25: 3.65 | FP25: 130.8 | FQ25: 163.1 | FR25: 10 | FS25: 4.2 | FT25: 2569.9 | FU25: 2288.7 | FV25: 447.1 | FW25: =FU25-FV25 -> 1841.6 | FY25: 4 | FZ25: 14875.93 | GA25: 119.9
A26: Sulawesi Utara | B26: 2022 | C26: 558 | D26: 40.85 | E26: 0.27420452 | F26: =D26-E26 -> 40.575795 | G26: 263305 | H26: =D26*L26/100 -> 473845.7 | I26: 0.59904128 | J26: 0.52280424 | K26: =I26-J26 -> 0.076237038 | L26: 1159965 | M26: 6.61 | N26: 6.08 | O26: 7.6 | P26: 63.08 | Q26: 80.77 | R26: 44.79 | S26: 360403 | T26: 439544 | U26: 93486 | V26: 72754 | W26: =100-X26-Y26 -> 71.87 | X26: 21.86 | Y26: 6.27 | Z26: 281769 | AA26: 38989 | AB26: 125474 | AC26: 3931 | AD26: 3608 | AE26: 84651 | AF26: 205681 | AG26: 76287 | AH26: 66853 | AI26: 5129 | AJ26: 15742 | AK26: 585 | AL26: 14951 | AM26: 106127 | AN26: 58923 | AO26: 23035 | AP26: 48230 | AQ26: =Z26/sum(Z26:AP26) -> 0.24291164 | AR26: =AA26/sum($Z26:$AP26) -> 0.033612221 | AS26: =AB26/sum($Z26:$AP26) -> 0.10817051 | AT26: =AC26/sum($Z26:$AP26) -> 0.0033888954 | AU26: =AD26/sum($Z26:$AP26) -> 0.0031104387 | AV26: =AE26/sum($Z26:$AP26) -> 0.072977202 | AW26: =AF26/sum($Z26:$AP26) -> 0.17731656 | AX26: =AG26/sum($Z26:$AP26) -> 0.06576664 | AY26: =AH26/sum($Z26:$AP26) -> 0.057633636 | ... BG26: =AP26/sum($Z26:$AP26) -> 0.041578841 | BH26: 41 | BI26: 3165.876 | BJ26: 0 | BK26: 3240217 | BL26: =BI26*1000/BK26 -> 0.97705678 | BM26: 49.43 | BN26: 59.15 | BO26: 5730 | BP26: 306 | BQ26: 237 | BR26: 359195 | BS26: 270998 | BT26: 2520 | BU26: 4941 | DA26: 80 | DB26: 28 | DC26: 108 | DD26: 2969 | DE26: 10214 | DF26: 11132 | DG26: 2051 | DH26: 13183 | DI26: 536578398 | DJ26: 49802192 | DK26: 586380590 | DL26: 119531784 | DM26: 34925863 | DN26: 154457647 | DO26: 740838237 | DP26: 15650072989 | DQ26: 21623211407 | DR26: =DQ26-DP26 -> 5973138418 | DS26: 5854550027 | DT26: 98 | DU26: 10 | DV26: =DH26/DC26 -> 122.06481 | DW26: =DF26/DH26 -> 0.84442085 | DX26: =DH26/DP26 -> 8.4236029e-07 | DY26: =DH26/DQ26 -> 6.0966892e-07 | DZ26: =DH26/DR26 -> 2.2070475e-06 | EA26: =DH26/DS26 -> 2.2517529e-06 | EB26: =DO26/DP26 -> 0.047337686 | EC26: =DO26/DQ26 -> 0.034261249 | ED26: =DO26/DR26 -> 0.12402831 | EE26: =DO26/DS26 -> 0.12654059 | EF26: =DO26/DH26 -> 56196.483 | EG26: =DQ26/DH26 -> 1640234.5 | EH26: =DR26/DH26 -> 453094.02 | EI26: =DS26/DH26 -> 444098.46 | EJ26: =DP26/DQ26 -> 0.72376266 | EK26: =DR26/DQ26 -> 0.27623734 | EL26: =DS26/DQ26 -> 0.27075303 | EM26: =DK26/DO26 -> 0.79150962 | EN26: =DN26/DO26 -> 0.20849038 | EO26: =DI26/DF26 -> 48201.437 | EP26: =DL26/DG26 -> 58279.758 | EQ26: =DT26/DC26 -> 0.90740741 | ER26: =DU26/DC26 -> 0.092592593 | FD26: 96768.2 | FE26: 96768200 | FF26: 10230489 | FG26: =(FF26/FE26)*100 -> 10.57216 | FH26: 7.31 | FI26: 51.8 | FJ26: 105.1 | FK26: =FD26/L26 -> 0.083423379 | FL26: 2.41 | FM26: 6.02 | FN26: 5.6 | FO26: 4.1 | FP26: 130.8 | FQ26: 163.1 | FR26: 10 | FS26: 4.2 | FT26: 1119.8 | FU26: 1000.1 | FV26: 274.3 | FW26: =FU26-FV26 -> 725.8 | FX26: 1399.5 | FY26: 4 | FZ26: 14875.93 | GA26: 119.9
A27: Sulawesi Tengah | B27: 2022 | C27: 35 | D27: 32.13 | E27: 0.24356187 | F27: =D27-E27 -> 31.886438 | G27: 279988 | H27: =D27*L27/100 -> 509684.62 | I27: 0.60005229 | J27: 0.55136185 | K27: =I27-J27 -> 0.048690447 | L27: 1586320 | M27: 3 | N27: 2.81 | O27: 3.32 | P27: 69.99 | Q27: 85.83 | R27: 53.71 | S27: 397661 | T27: 466606 | U27: 263874 | V27: 120813 | W27: =100-X27-Y27 -> 65.46 | X27: 26.92 | Y27: 7.62 | Z27: 689616 | AA27: 27779 | AB27: 133238 | AC27: 5295 | AD27: 2529 | AE27: 70991 | AF27: 246081 | AG27: 42346 | AH27: 63021 | AI27: 6536 | AJ27: 10769 | AK27: 592 | AL27: 12605 | AM27: 119392 | AN27: 81237 | AO27: 31367 | AP27: 42926 | AQ27: =Z27/sum(Z27:AP27) -> 0.43472692 | AR27: =AA27/sum($Z27:$AP27) -> 0.017511599 | AS27: =AB27/sum($Z27:$AP27) -> 0.083991881 | AT27: =AC27/sum($Z27:$AP27) -> 0.0033379142 | AU27: =AD27/sum($Z27:$AP27) -> 0.0015942559 | AV27: =AE27/sum($Z27:$AP27) -> 0.044752005 | AW27: =AF27/sum($Z27:$AP27) -> 0.15512696 | AX27: =AG27/sum($Z27:$AP27) -> 0.026694488 | AY27: =AH27/sum($Z27:$AP27) -> 0.039727798 | ... BG27: =AP27/sum($Z27:$AP27) -> 0.027060114 | BH27: 39 | BI27: 2710.5959 | BJ27: 6.2139693 | BK27: 2605724 | BL27: =BI27*1000/BK27 -> 1.0402467 | BM27: 49.37 | BN27: 67.87 | BO27: 14100 | BP27: 968 | BQ27: 864 | BR27: 229939 | BS27: 103164 | BT27: 1675 | BU27: 2568 | DA27: 66 | DB27: 28 | DC27: 94 | DD27: 2505 | DE27: 52480 | DF27: 46478 | DG27: 8707 | DH27: 55185 | DI27: 7013824368 | DJ27: 94899557 | DK27: 7108723925 | DL27: 631616905 | DM27: 11408970 | DN27: 643025875 | DO27: 7751749800 | DP27: 244052217771 | DQ27: 323290535349 | DR27: =DQ27-DP27 -> 79238317578 | DS27: 70975041726 | DT27: 64 | DU27: 30 | DV27: =DH27/DC27 -> 587.07447 | DW27: =DF27/DH27 -> 0.84222162 | DX27: =DH27/DP27 -> 2.2611964e-07 | DY27: =DH27/DQ27 -> 1.7069785e-07 | DZ27: =DH27/DR27 -> 6.9644336e-07 | EA27: =DH27/DS27 -> 7.7752684e-07 | EB27: =DO27/DP27 -> 0.031762669 | EC27: =DO27/DQ27 -> 0.023977658 | ED27: =DO27/DR27 -> 0.097828299 | EE27: =DO27/DS27 -> 0.10921797 | EF27: =DO27/DH27 -> 140468.42 | EG27: =DQ27/DH27 -> 5858304.5 | EH27: =DR27/DH27 -> 1435866.9 | EI27: =DS27/DH27 -> 1286129.2 | EJ27: =DP27/DQ27 -> 0.7549006 | EK27: =DR27/DQ27 -> 0.2450994 | EL27: =DS27/DQ27 -> 0.2195395 | EM27: =DK27/DO27 -> 0.91704765 | EN27: =DN27/DO27 -> 0.082952352 | EO27: =DI27/DF27 -> 150906.33 | EP27: =DL27/DG27 -> 72541.278 | EQ27: =DT27/DC27 -> 0.68085106 | ER27: =DU27/DC27 -> 0.31914894 | FD27: 172624.8 | FE27: 172624800 | FF27: 56659016 | FG27: =(FF27/FE27)*100 -> 32.82206 | FH27: 29.9 | FI27: 51.8 | FJ27: 7486 | FK27: =FD27/L27 -> 0.10882092 | FL27: 10.7 | FM27: 6.02 | FN27: 5.35 | FO27: 3.92 | FP27: 130.8 | FQ27: 163.1 | FR27: 10 | FS27: 4.2 | FT27: 18956.3 | FU27: 17471.8 | FV27: 3549.4 | FW27: =FU27-FV27 -> 13922.4 | FX27: 825.8 | FY27: 4 | FZ27: 14875.93 | GA27: 119.9
A28: Sulawesi Selatan | B28: 2022 | C28: 191 | D28: 36.45 | E28: 0.23906132 | F28: =D28-E28 -> 36.210939 | G28: 753208 | H28: =D28*L28/100 -> 1586905.4 | I28: 0.52181022 | J28: 0.50079387 | K28: =I28-J28 -> 0.021016345 | L28: 4353650 | M28: 4.51 | N28: 4.91 | O28: 3.9 | P28: 66.18 | Q28: 82.91 | R28: 50.46 | S28: 994371 | T28: 1443452 | U28: 738968 | V28: 271017 | W28: =100-X28-Y28 -> 63.99 | X28: 29.78 | Y28: 6.23 | Z28: 1677393 | AA28: 28437 | AB28: 356510 | AC28: 13680 | AD28: 12047 | AE28: 262156 | AF28: 780174 | AG28: 196263 | AH28: 182275 | AI28: 30665 | AJ28: 44251 | AK28: 6495 | AL28: 55342 | AM28: 233622 | AN28: 255670 | AO28: 95820 | AP28: 122850 | AQ28: =Z28/sum(Z28:AP28) -> 0.3852843 | AR28: =AA28/sum($Z28:$AP28) -> 0.0065317607 | AS28: =AB28/sum($Z28:$AP28) -> 0.081887612 | AT28: =AC28/sum($Z28:$AP28) -> 0.003142191 | AU28: =AD28/sum($Z28:$AP28) -> 0.0027671035 | AV28: =AE28/sum($Z28:$AP28) -> 0.060215222 | AW28: =AF28/sum($Z28:$AP28) -> 0.17919998 | AX28: =AG28/sum($Z28:$AP28) -> 0.045080105 | AY28: =AH28/sum($Z28:$AP28) -> 0.041867169 | ... BG28: =AP28/sum($Z28:$AP28) -> 0.028217702 | BH28: 41 | BI28: 2800.58 | BJ28: 0.42146767 | BK28: 2876952 | BL28: =BI28*1000/BK28 -> 0.97345385 | BM28: 44.89 | BN28: 63.55 | BO28: 44397 | BP28: 2762 | BQ28: 2649 | BR28: 729690 | BS28: 208050 | BT28: 4960 | BU28: 9249 | DA28: 384 | DB28: 82 | DC28: 466 | DD28: 12721 | DE28: 29330 | DF28: 34855 | DG28: 7196 | DH28: 42051 | DI28: 1686859556 | DJ28: 50945897 | DK28: 1737805453 | DL28: 527889386 | DM28: 10634491 | DN28: 538523877 | DO28: 2276329330 | DP28: 36524401561 | DQ28: 76140726128 | DR28: =DQ28-DP28 -> 39616324567 | DS28: 39110405196 | DT28: 441 | DU28: 25 | DV28: =DH28/DC28 -> 90.238197 | DW28: =DF28/DH28 -> 0.82887446 | DX28: =DH28/DP28 -> 1.1513125e-06 | DY28: =DH28/DQ28 -> 5.5228e-07 | DZ28: =DH28/DR28 -> 1.0614564e-06 | EA28: =DH28/DS28 -> 1.075187e-06 | EB28: =DO28/DP28 -> 0.062323522 | EC28: =DO28/DQ28 -> 0.029896344 | ED28: =DO28/DR28 -> 0.057459377 | EE28: =DO28/DS28 -> 0.058202653 | EF28: =DO28/DH28 -> 54132.585 | EG28: =DQ28/DH28 -> 1810675.8 | EH28: =DR28/DH28 -> 942101.84 | EI28: =DS28/DH28 -> 930070.75 | EJ28: =DP28/DQ28 -> 0.479696 | EK28: =DR28/DQ28 -> 0.520304 | EL28: =DS28/DQ28 -> 0.51365947 | EM28: =DK28/DO28 -> 0.76342444 | EN28: =DN28/DO28 -> 0.23657556 | EO28: =DI28/DF28 -> 48396.487 | EP28: =DL28/DG28 -> 73358.725 | EQ28: =DT28/DC28 -> 0.94635193 | ER28: =DU28/DC28 -> 0.053648069 | FD28: 360912.82 | FE28: 360912820 | FF28: 48363156 | FG28: =(FF28/FE28)*100 -> 13.400232 | FH28: 9.73 | FI28: 51.8 | FJ28: 469 | FK28: =FD28/L28 -> 0.082898906 | FL28: 0.43 | FM28: 6.02 | FN28: 5.55 | FO28: 4.09 | FP28: 130.8 | FQ28: 163.1 | FR28: 10 | FS28: 4.2 | FT28: 2559.7 | FU28: 2469.9 | FV28: 1243.3 | FW28: =FU28-FV28 -> 1226.6 | FX28: 4265 | FY28: 4 | FZ28: 14875.93 | GA28: 119.9
A29: Sulawesi Tenggara | B29: 2022 | C29: 74 | D29: 37.61 | E29: 0.24911257 | F29: =D29-E29 -> 37.360887 | G29: 352621 | H29: =D29*L29/100 -> 502439.89 | I29: 0.76496927 | J29: 0.5868441 | K29: =I29-J29 -> 0.17812517 | L29: 1335921 | M29: 3.36 | N29: 3.36 | O29: 3.36 | P29: 68.82 | Q29: 82.91 | R29: 54.94 | S29: 336223 | T29: 460961 | U29: 216756 | V29: 108742 | W29: =100-X29-Y29 -> 63.52 | X29: 28.34 | Y29: 8.14 | Z29: 438501 | AA29: 33974 | AB29: 119588 | AC29: 4737 | AD29: 2869 | AE29: 88796 | AF29: 247446 | AG29: 55477 | AH29: 61089 | AI29: 6414 | AJ29: 10922 | AK29: 1307 | AL29: 8885 | AM29: 106493 | AN29: 82681 | AO29: 37496 | AP29: 29246 | AQ29: =Z29/sum(Z29:AP29) -> 0.32823872 | AR29: =AA29/sum($Z29:$AP29) -> 0.025431145 | AS29: =AB29/sum($Z29:$AP29) -> 0.089517269 | AT29: =AC29/sum($Z29:$AP29) -> 0.0035458684 | AU29: =AD29/sum($Z29:$AP29) -> 0.0021475821 | AV29: =AE29/sum($Z29:$AP29) -> 0.066468002 | AW29: =AF29/sum($Z29:$AP29) -> 0.18522502 | AX29: =AG29/sum($Z29:$AP29) -> 0.041527156 | AY29: =AH29/sum($Z29:$AP29) -> 0.045728003 | ... BG29: =AP29/sum($Z29:$AP29) -> 0.021892013 | BH29: 40 | BI29: 2678.8631 | BJ29: 0 | BK29: 2831991 | BL29: =BI29*1000/BK29 -> 0.94592924 | BM29: 45.98 | BN29: 62.39 | BO29: 9505 | BP29: 1658 | BQ29: 1550 | BR29: 170454 | BS29: 57273 | BT29: 1571 | BU29: 1991 | DA29: 122 | DB29: 12 | DC29: 134 | DD29: 3449 | DE29: 23830 | DF29: 25819 | DG29: 1460 | DH29: 27279 | DI29: 890695265 | DJ29: 21472164 | DK29: 912167429 | DL29: 398345606 | DM29: 42805471 | DN29: 441151077 | DO29: 1353318506 | DP29: 20061482100 | DQ29: 51939586825 | DR29: =DQ29-DP29 -> 31878104725 | DS29: 30084502525 | DT29: 130 | DU29: 4 | DV29: =DH29/DC29 -> 203.57463 | DW29: =DF29/DH29 -> 0.94647898 | DX29: =DH29/DP29 -> 1.3597699e-06 | DY29: =DH29/DQ29 -> 5.2520633e-07 | DZ29: =DH29/DR29 -> 8.5572841e-07 | EA29: =DH29/DS29 -> 9.0674592e-07 | EB29: =DO29/DP29 -> 0.067458551 | EC29: =DO29/DQ29 -> 0.026055627 | ED29: =DO29/DR29 -> 0.042452916 | EE29: =DO29/DS29 -> 0.044983908 | EF29: =DO29/DH29 -> 49610.268 | EG29: =DQ29/DH29 -> 1904013.6 | EH29: =DR29/DH29 -> 1168595.1 | EI29: =DS29/DH29 -> 1102844.8 | EJ29: =DP29/DQ29 -> 0.38624647 | EK29: =DR29/DQ29 -> 0.61375353 | EL29: =DS29/DQ29 -> 0.57922106 | EM29: =DK29/DO29 -> 0.67402273 | EN29: =DN29/DO29 -> 0.32597727 | EO29: =DI29/DF29 -> 34497.667 | EP29: =DL29/DG29 -> 272839.46 | EQ29: =DT29/DC29 -> 0.97014925 | ER29: =DU29/DC29 -> 0.029850746 | FD29: 102656.4 | FE29: 102656400 | FF29: 8336672 | FG29: =(FF29/FE29)*100 -> 8.1209472 | FH29: 16.83 | FI29: 51.8 | FJ29: 877.9 | FK29: =FD29/L29 -> 0.076843167 | FL29: 4.83 | FM29: 6.02 | FN29: 7.39 | FO29: 5.43 | FP29: 130.8 | FQ29: 163.1 | FR29: 10 | FS29: 4.2 | FT29: 5831.7 | FU29: 5668.3 | FV29: 2710.7 | FW29: =FU29-FV29 -> 2957.6 | FX29: 592 | FY29: 4 | FZ29: 14875.93 | GA29: 119.9
A30: Gorontalo | B30: 2022 | C30: 171 | D30: 35.03 | E30: 0.26919879 | F30: =D30-E30 -> 34.760801 | G30: 120089 | H30: =D30*L30/100 -> 215171.77 | I30: 0.61214305 | J30: 0.51790133 | K30: =I30-J30 -> 0.094241725 | L30: 614250 | M30: 2.58 | N30: 2.28 | O30: 3.07 | P30: 68.91 | Q30: 85.3 | R30: 52.64 | S30: 151566 | T30: 196178 | U30: 78170 | V30: 37481 | W30: =100-X30-Y30 -> 70.8 | X30: 23.1 | Y30: 6.1 | Z30: 204305 | AA30: 15810 | AB30: 56602 | AC30: 2036 | AD30: 551 | AE30: 30493 | AF30: 114273 | AG30: 28065 | AH30: 28813 | AI30: 4956 | AJ30: 6123 | AK30: 257 | AL30: 4823 | AM30: 49236 | AN30: 33009 | AO30: 13284 | AP30: 21614 | AQ30: =Z30/sum(Z30:AP30) -> 0.33260887 | AR30: =AA30/sum($Z30:$AP30) -> 0.025738706 | AS30: =AB30/sum($Z30:$AP30) -> 0.092148148 | AT30: =AC30/sum($Z30:$AP30) -> 0.0033146113 | AU30: =AD30/sum($Z30:$AP30) -> 0.0008970289 | AV30: =AE30/sum($Z30:$AP30) -> 0.049642654 | AW30: =AF30/sum($Z30:$AP30) -> 0.18603663 | AX30: =AG30/sum($Z30:$AP30) -> 0.045689866 | AY30: =AH30/sum($Z30:$AP30) -> 0.046907611 | ... BG30: =AP30/sum($Z30:$AP30) -> 0.035187627 | BH30: 41 | BI30: 2207.212 | BJ30: 1.0682349 | BK30: 2551301 | BL30: =BI30*1000/BK30 -> 0.86513195 | BM30: 52.03 | BN30: 64.97 | BO30: 2283 | BP30: 523 | BQ30: 513 | BR30: 89438 | BS30: 64828 | BT30: 741 | BU30: 1704 | DA30: 22 | DB30: 7 | DC30: 29 | DD30: 889 | DE30: 4228 | DF30: 4465 | DG30: 652 | DH30: 5117 | DI30: 97603980 | DJ30: 6012114 | DK30: 103616094 | DL30: 24353234 | DM30: 2131727 | DN30: 26484961 | DO30: 130101055 | DP30: 1108921915 | DQ30: 2728975105 | DR30: =DQ30-DP30 -> 1620053190 | DS30: 1618465450 | DT30: 27 | DU30: 2 | DV30: =DH30/DC30 -> 176.44828 | DW30: =DF30/DH30 -> 0.87258159 | DX30: =DH30/DP30 -> 4.6143916e-06 | DY30: =DH30/DQ30 -> 1.8750629e-06 | DZ30: =DH30/DR30 -> 3.1585383e-06 | EA30: =DH30/DS30 -> 3.1616368e-06 | EB30: =DO30/DP30 -> 0.11732211 | EC30: =DO30/DQ30 -> 0.047673962 | ED30: =DO30/DR30 -> 0.080306656 | EE30: =DO30/DS30 -> 0.080385439 | EF30: =DO30/DH30 -> 25425.26 | EG30: =DQ30/DH30 -> 533315.44 | EH30: =DR30/DH30 -> 316602.15 | EI30: =DS30/DH30 -> 316291.86 | EJ30: =DP30/DQ30 -> 0.40635106 | EK30: =DR30/DQ30 -> 0.59364894 | EL30: =DS30/DQ30 -> 0.59306714 | EM30: =DK30/DO30 -> 0.79642778 | EN30: =DN30/DO30 -> 0.20357222 | EO30: =DI30/DF30 -> 21859.794 | EP30: =DL30/DG30 -> 37351.586 | EQ30: =DT30/DC30 -> 0.93103448 | ER30: =DU30/DC30 -> 0.068965517 | FD30: 30282.2 | FE30: 30282200 | FF30: 1332268.4 | FG30: =(FF30/FE30)*100 -> 4.3995099 | FH30: 7.79 | FI30: 51.8 | FJ30: 102.9 | FK30: =FD30/L30 -> 0.049299471 | FL30: -1.93 | FM30: 6.02 | FN30: 5.74 | FO30: 4.22 | FP30: 130.8 | FQ30: 163.1 | FR30: 10 | FS30: 4.2 | FT30: 52 | FU30: 52 | FV30: 32.6 | FW30: =FU30-FV30 -> 19.4 | FX30: 641.7 | FY30: 4 | FZ30: 14875.93 | GA30: 119.9
A31: Sulawesi Barat | B31: 2022 | C31: 34 | D31: 22.75 | E31: 0.19107675 | F31: =D31-E31 -> 22.558923 | G31: 103671 | H31: =D31*L31/100 -> 166507.7 | I31: 0.65546107 | J31: 0.5286198 | K31: =I31-J31 -> 0.12684126 | L31: 731902 | M31: 2.34 | N31: 2.55 | O31: 2.03 | P31: 73 | Q31: 87.71 | R31: 58.22 | S31: 151389 | T31: 158165 | U31: 163350 | V31: 95410 | W31: =100-X31-Y31 -> 50.85 | X31: 36.11 | Y31: 13.04 | Z31: 367695 | AA31: 4120 | AB31: 54269 | AC31: 907 | AD31: 606 | AE31: 35242 | AF31: 114746 | AG31: 23035 | AH31: 16384 | AI31: 3633 | AJ31: 4621 | AK31: 132 | AL31: 2765 | AM31: 37801 | AN31: 38849 | AO31: 14679 | AP31: 12418 | AQ31: =Z31/sum(Z31:AP31) -> 0.50238283 | AR31: =AA31/sum($Z31:$AP31) -> 0.0056291689 | AS31: =AB31/sum($Z31:$AP31) -> 0.074147905 | AT31: =AC31/sum($Z31:$AP31) -> 0.0012392369 | AU31: =AD31/sum($Z31:$AP31) -> 0.0008279797 | AV31: =AE31/sum($Z31:$AP31) -> 0.048151255 | AW31: =AF31/sum($Z31:$AP31) -> 0.15677782 | AX31: =AG31/sum($Z31:$AP31) -> 0.031472793 | AY31: =AH31/sum($Z31:$AP31) -> 0.022385511 | ... BG31: =AP31/sum($Z31:$AP31) -> 0.016966752 | BH31: 36 | BI31: 1975 | BJ31: 1.2820513 | BK31: 2340502 | BL31: =BI31*1000/BK31 -> 0.84383607 | BM31: 57.15 | BN31: 77.25 | BO31: 3762 | BP31: 306 | BQ31: 286 | BR31: 84461 | BS31: 47063 | BT31: 278 | BU31: 507 | DA31: 17 | DB31: 10 | DC31: 27 | DD31: 847 | DE31: 1889 | DF31: 2490 | DG31: 246 | DH31: 2736 | DI31: 108852019 | DJ31: 336766 | DK31: 109188785 | DL31: 12263879 | DM31: 102868 | DN31: 12366747 | DO31: 121555532 | DP31: 12675309015 | DQ31: 14422098600 | DR31: =DQ31-DP31 -> 1746789585 | DS31: 1746186971 | DT31: 24 | DU31: 3 | DV31: =DH31/DC31 -> 101.33333 | DW31: =DF31/DH31 -> 0.91008772 | DX31: =DH31/DP31 -> 2.1585273e-07 | DY31: =DH31/DQ31 -> 1.8970887e-07 | DZ31: =DH31/DR31 -> 1.566302e-06 | EA31: =DH31/DS31 -> 1.5668425e-06 | EB31: =DO31/DP31 -> 0.0095899462 | EC31: =DO31/DQ31 -> 0.0084284219 | ED31: =DO31/DR31 -> 0.069587965 | EE31: =DO31/DS31 -> 0.06961198 | EF31: =DO31/DH31 -> 44428.192 | EG31: =DQ31/DH31 -> 5271234.9 | EH31: =DR31/DH31 -> 638446.49 | EI31: =DS31/DH31 -> 638226.23 | EJ31: =DP31/DQ31 -> 0.87888104 | EK31: =DR31/DQ31 -> 0.12111896 | EL31: =DS31/DQ31 -> 0.12107718 | EM31: =DK31/DO31 -> 0.89826257 | EN31: =DN31/DO31 -> 0.10173743 | EO31: =DI31/DF31 -> 43715.67 | EP31: =DL31/DG31 -> 49853.167 | EQ31: =DT31/DC31 -> 0.88888889 | ER31: =DU31/DC31 -> 0.11111111 | FD31: 33643 | FE31: 33643000 | FF31: 3580179.5 | FG31: =(FF31/FE31)*100 -> 10.641677 | FH31: -0.64 | FI31: 51.8 | FJ31: 28.3 | FK31: =FD31/L31 -> 0.045966537 | FL31: -4.04 | FM31: 6.02 | FN31: 6.78 | FO31: 4.97 | FP31: 130.8 | FQ31: 163.1 | FR31: 10 | FS31: 4.2 | FT31: 472.2 | FU31: 411.2 | FV31: 67.4 | FW31: =FU31-FV31 -> 343.8 | FX31: 191.1 | FY31: 4 | FZ31: 14875.93 | GA31: 119.9
A32: Maluku | B32: 2022 | C32: 195 | D32: 36.7 | E32: 0.22521913 | F32: =D32-E32 -> 36.474781 | G32: 165158 | H32: =D32*L32/100 -> 296845.75 | I32: 0.58913462 | J32: 0.64336635 | K32: =I32-J32 -> -0.054231727 | L32: 808844 | M32: 6.88 | N32: 5.03 | O32: 9.65 | P32: 65.46 | Q32: 78.33 | R32: 52.47 | S32: 264482 | T32: 280340 | U32: 116614 | V32: 95439 | W32: =100-X32-Y32 -> 58.46 | X32: 29.74 | Y32: 11.8 | Z32: 271247 | AA32: 15856 | AB32: 86975 | AC32: 1450 | AD32: 1828 | AE32: 34808 | AF32: 110583 | AG32: 60191 | AH32: 29997 | AI32: 3044 | AJ32: 7038 | AK32: 380 | AL32: 5776 | AM32: 79210 | AN32: 60513 | AO32: 17078 | AP32: 22870 | AQ32: =Z32/sum(Z32:AP32) -> 0.33535144 | AR32: =AA32/sum($Z32:$AP32) -> 0.019603286 | AS32: =AB32/sum($Z32:$AP32) -> 0.10753001 | AT32: =AC32/sum($Z32:$AP32) -> 0.0017926819 | AU32: =AD32/sum($Z32:$AP32) -> 0.0022600155 | AV32: =AE32/sum($Z32:$AP32) -> 0.043034256 | AW32: =AF32/sum($Z32:$AP32) -> 0.13671734 | AX32: =AG32/sum($Z32:$AP32) -> 0.07441608 | AY32: =AH32/sum($Z32:$AP32) -> 0.037086261 | ... BG32: =AP32/sum($Z32:$AP32) -> 0.028274921 | BH32: 41 | BI32: 2619.3128 | BJ32: 0.55094222 | BK32: 2719294 | BL32: =BI32*1000/BK32 -> 0.96323267 | BM32: 48.04 | BN32: 63.3 | BO32: 7493 | BP32: 1045 | BQ32: 1039 | BR32: 116024 | BS32: 66863 | BT32: 1758 | BU32: 1354 | DA32: 31 | DB32: 7 | DC32: 38 | DD32: 1159 | DE32: 3058 | DF32: 2516 | DG32: 1701 | DH32: 4217 | DI32: 189319132 | DJ32: 1004400 | DK32: 190323532 | DL32: 206906332 | DM32: 264692 | DN32: 207171024 | DO32: 397494556 | DP32: 2271623633 | DQ32: 5263056064 | DR32: =DQ32-DP32 -> 2991432431 | DS32: 2979949035 | DT32: 37 | DU32: 1 | DV32: =DH32/DC32 -> 110.97368 | DW32: =DF32/DH32 -> 0.59663268 | DX32: =DH32/DP32 -> 1.8563815e-06 | DY32: =DH32/DQ32 -> 8.012455e-07 | DZ32: =DH32/DR32 -> 1.4096925e-06 | EA32: =DH32/DS32 -> 1.4151249e-06 | EB32: =DO32/DP32 -> 0.17498258 | EC32: =DO32/DQ32 -> 0.075525427 | ED32: =DO32/DR32 -> 0.13287766 | EE32: =DO32/DS32 -> 0.13338972 | EF32: =DO32/DH32 -> 94260.032 | EG32: =DQ32/DH32 -> 1248056.9 | EH32: =DR32/DH32 -> 709374.54 | EI32: =DS32/DH32 -> 706651.42 | EJ32: =DP32/DQ32 -> 0.43161684 | EK32: =DR32/DQ32 -> 0.56838316 | EL32: =DS32/DQ32 -> 0.56620127 | EM32: =DK32/DO32 -> 0.4788079 | EN32: =DN32/DO32 -> 0.5211921 | EO32: =DI32/DF32 -> 75246.078 | EP32: =DL32/DG32 -> 121638.06 | EQ32: =DT32/DC32 -> 0.97368421 | ER32: =DU32/DC32 -> 0.026315789 | FD32: 33575.1 | FE32: 33575100 | FF32: 2019621.7 | FG32: =(FF32/FE32)*100 -> 6.0152366 | FH32: 12.29 | FI32: 51.8 | FJ32: 73.4 | FK32: =FD32/L32 -> 0.041509982 | FL32: 4.06 | FM32: 6.02 | FN32: 6.54 | FO32: 4.81 | FP32: 130.8 | FQ32: 163.1 | FR32: 10 | FS32: 4.2 | FT32: 129.4 | FU32: 133.5 | FV32: 185.7 | FW32: =FU32-FV32 -> -52.2 | FX32: 288.8 | FY32: 4 | FZ32: 14875.93 | GA32: 119.9
A33: Maluku Utara | B33: 2022 | C33: 8 | D33: 34.37 | E33: 0.23737246 | F33: =D33-E33 -> 34.132628 | G33: 120834 | H33: =D33*L33/100 -> 201053.5 | I33: 0.65401582 | J33: 0.62211064 | K33: =I33-J33 -> 0.031905178 | L33: 584968 | M33: 3.98 | N33: 3.8 | O33: 4.31 | P33: 64.88 | Q33: 82.29 | R33: 46.87 | S33: 168100 | T33: 184757 | U33: 82405 | V33: 54281 | W33: =100-X33-Y33 -> 60.78 | X33: 29.94 | Y33: 9.28 | Z33: 166716 | AA33: 19597 | AB33: 116038 | AC33: 1257 | AD33: 1195 | AE33: 30214 | AF33: 70357 | AG33: 37177 | AH33: 15499 | AI33: 955 | AJ33: 3692 | AK33: - | AL33: 3717 | AM33: 57378 | AN33: 37071 | AO33: 11223 | AP33: 12882 | AQ33: =Z33/sum(Z33:AP33) -> 0.28500021 | AR33: =AA33/sum($Z33:$AP33) -> 0.033500978 | AS33: =AB33/sum($Z33:$AP33) -> 0.19836641 | AT33: =AC33/sum($Z33:$AP33) -> 0.0021488355 | AU33: =AD33/sum($Z33:$AP33) -> 0.0020428468 | AV33: =AE33/sum($Z33:$AP33) -> 0.051650689 | AW33: =AF33/sum($Z33:$AP33) -> 0.12027496 | AX33: =AG33/sum($Z33:$AP33) -> 0.063553904 | AY33: =AH33/sum($Z33:$AP33) -> 0.026495466 | ... BG33: =AP33/sum($Z33:$AP33) -> 0.022021717 | BH33: 39 | BI33: 2862.231 | BJ33: 5.1699228 | BK33: 2938081 | BL33: =BI33*1000/BK33 -> 0.97418383 | BM33: 54.29 | BN33: 65.63 | BO33: 9719 | BP33: 488 | BQ33: 418 | BR33: 86515 | BS33: 18548 | BT33: 2574 | BU33: 1021 | DA33: 14 | DB33: 15 | DC33: 29 | DD33: 505 | DE33: 32134 | DF33: 18865 | DG33: 13774 | DH33: 32639 | DI33: 2711669381 | DJ33: 142145671 | DK33: 2853815052 | DL33: 1242308260 | DM33: 41346478 | DN33: 1283654738 | DO33: 4137469790 | DP33: 31119974932 | DQ33: 77750629451 | DR33: =DQ33-DP33 -> 46630654519 | DS33: 46626094115 | DT33: 13 | DU33: 16 | DV33: =DH33/DC33 -> 1125.4828 | DW33: =DF33/DH33 -> 0.57798952 | DX33: =DH33/DP33 -> 1.0488119e-06 | DY33: =DH33/DQ33 -> 4.1979081e-07 | DZ33: =DH33/DR33 -> 6.9994728e-07 | EA33: =DH33/DS33 -> 7.0001574e-07 | EB33: =DO33/DP33 -> 0.13295222 | EC33: =DO33/DQ33 -> 0.053214615 | ED33: =DO33/DR33 -> 0.088728538 | EE33: =DO33/DS33 -> 0.088737216 | EF33: =DO33/DH33 -> 126764.6 | EG33: =DQ33/DH33 -> 2382138.8 | EH33: =DR33/DH33 -> 1428679 | EI33: =DS33/DH33 -> 1428539.3 | EJ33: =DP33/DQ33 -> 0.40025367 | EK33: =DR33/DQ33 -> 0.59974633 | EL33: =DS33/DQ33 -> 0.59968767 | EM33: =DK33/DO33 -> 0.68974886 | EN33: =DN33/DO33 -> 0.31025114 | EO33: =DI33/DF33 -> 143740.76 | EP33: =DL33/DG33 -> 90192.265 | EQ33: =DT33/DC33 -> 0.44827586 | ER33: =DU33/DC33 -> 0.55172414 | FD33: 40248.4 | FE33: 40248400 | FF33: 10326442 | FG33: =(FF33/FE33)*100 -> 25.656776 | FH33: 76.74 | FI33: 51.8 | FJ33: 4487.5 | FK33: =FD33/L33 -> 0.068804447 | FL33: 19.52 | FM33: 6.02 | FN33: 5.21 | FO33: 3.84 | FP33: 130.8 | FQ33: 163.1 | FR33: 10 | FS33: 4.2 | FT33: 8200.2 | FU33: 7947.8 | FV33: 4243 | FW33: =FU33-FV33 -> 3704.8 | FX33: 168.8 | FY33: 4 | FZ33: 14875.93 | GA33: 119.9
A34: Papua Barat | B34: 2022 | C34: 124 | D34: 39.72 | E34: 0.30857719 | F34: =D34-E34 -> 39.411423 | G34: 115944 | H34: =D34*L34/100 -> 193716.43 | I34: 0.62087135 | J34: 0.62713162 | K34: =I34-J34 -> -0.0062602701 | L34: 487705 | M34: 5.37 | N34: 5.94 | O34: 4.41 | P34: 68.55 | Q34: 80.88 | R34: 54.63 | S34: 118867 | T34: 186744 | U34: 83932 | V34: 59963 | W34: =100-X34-Y34 -> 58.46 | X34: 29.25 | Y34: 12.29 | Z34: 188481 | AA34: 8859 | AB34: 20375 | AC34: 1336 | AD34: 523 | AE34: 29170 | AF34: 69746 | AG34: 28440 | AH34: 15477 | AI34: 2907 | AJ34: 4051 | AK34: - | AL34: 5075 | AM34: 59758 | AN34: 25092 | AO34: 12136 | AP34: 16245 | AQ34: =Z34/sum(Z34:AP34) -> 0.38649212 | AR34: =AA34/sum($Z34:$AP34) -> 0.018165936 | AS34: =AB34/sum($Z34:$AP34) -> 0.041780217 | AT34: =AC34/sum($Z34:$AP34) -> 0.0027395519 | AU34: =AD34/sum($Z34:$AP34) -> 0.0010724443 | AV34: =AE34/sum($Z34:$AP34) -> 0.059814916 | AW34: =AF34/sum($Z34:$AP34) -> 0.14301855 | AX34: =AG34/sum($Z34:$AP34) -> 0.058318005 | AY34: =AH34/sum($Z34:$AP34) -> 0.03173656 | ... BG34: =AP34/sum($Z34:$AP34) -> 0.033311392 | BH34: 38 | BI34: 3200 | BJ34: 2.0863906 | BK34: 3283235 | BL34: =BI34*1000/BK34 -> 0.97464848 | BM34: 38.02 | BN34: 60.28 | BO34: 2095 | BP34: 581 | BQ34: 575 | BR34: 100883 | BS34: 253377 | BT34: 755 | BU34: 830 | DA34: 30 | DB34: 13 | DC34: 43 | DD34: 1180 | DE34: 14705 | DF34: 10835 | DG34: 5050 | DH34: 15885 | DI34: 526746960 | DJ34: 11078390 | DK34: 537825350 | DL34: 282100906 | DM34: 14561041 | DN34: 296661947 | DO34: 834487297 | DP34: 5623106758 | DQ34: 15184433578 | DR34: =DQ34-DP34 -> 9561326820 | DS34: 9194598584 | DT34: 39 | DU34: 4 | DV34: =DH34/DC34 -> 369.4186 | DW34: =DF34/DH34 -> 0.68209002 | DX34: =DH34/DP34 -> 2.8249508e-06 | DY34: =DH34/DQ34 -> 1.0461371e-06 | DZ34: =DH34/DR34 -> 1.6613803e-06 | EA34: =DH34/DS34 -> 1.7276448e-06 | EB34: =DO34/DP34 -> 0.14840325 | EC34: =DO34/DQ34 -> 0.054956762 | ED34: =DO34/DR34 -> 0.087277353 | EE34: =DO34/DS34 -> 0.090758426 | EF34: =DO34/DH34 -> 52533.037 | EG34: =DQ34/DH34 -> 955897.61 | EH34: =DR34/DH34 -> 601909.15 | EI34: =DS34/DH34 -> 578822.7 | EJ34: =DP34/DQ34 -> 0.37032048 | EK34: =DR34/DQ34 -> 0.62967952 | EL34: =DS34/DQ34 -> 0.60552793 | EM34: =DK34/DO34 -> 0.64449795 | EN34: =DN34/DO34 -> 0.35550205 | EO34: =DI34/DF34 -> 48615.317 | EP34: =DL34/DG34 -> 55861.566 | EQ34: =DT34/DC34 -> 0.90697674 | ER34: =DU34/DC34 -> 0.093023256 | FD34: 62530.5 | FE34: 62530500 | FF34: 19299248 | FG34: =(FF34/FE34)*100 -> 30.863736 | FH34: 2.92 | FI34: 51.8 | FJ34: 71.8 | FK34: =FD34/L34 -> 0.12821378 | FL34: 1.16 | FM34: 6.02 | FN34: 6.12 | FO34: 4.49 | FP34: 130.8 | FQ34: 163.1 | FR34: 10 | FS34: 4.2 | FT34: 2730.1 | FU34: 2463 | FV34: 297.2 | FW34: =FU34-FV34 -> 2165.8 | FX34: 585.2 | FY34: 4 | FZ34: 14875.93 | GA34: 119.9
A35: Papua Barat Daya | B35: 2022 | H35: =D35*L35/100 -> 0
A36: Papua | B36: 2022 | C36: 76 | D36: 15.89 | E36: 0.15880958 | F36: =D36-E36 -> 15.73119 | G36: 210754 | H36: =D36*L36/100 -> 307434.48 | I36: 0.71072457 | J36: 0.70012699 | K36: =I36-J36 -> 0.010597577 | L36: 1934767 | M36: 2.83 | N36: 3.34 | O36: 2.12 | P36: 77.75 | Q36: 85.49 | R36: 69.09 | S36: 408941 | T36: 296534 | U36: 622882 | V36: 113204 | W36: =100-X36-Y36 -> 54.69 | X36: 39.46 | Y36: 5.85 | Z36: 1383238 | AA36: 13771 | AB36: 30598 | AC36: 3226 | AD36: 1572 | AE36: 42372 | AF36: 131153 | AG36: 66707 | AH36: 37869 | AI36: 2649 | AJ36: 5457 | AK36: 3063 | AL36: 12844 | AM36: 109928 | AN36: 50303 | AO36: 22990 | AP36: 17027 | AQ36: =Z36/sum(Z36:AP36) -> 0.71493777 | AR36: =AA36/sum($Z36:$AP36) -> 0.0071176529 | AS36: =AB36/sum($Z36:$AP36) -> 0.015814824 | AT36: =AC36/sum($Z36:$AP36) -> 0.0016673842 | AU36: =AD36/sum($Z36:$AP36) -> 0.00081250094 | AV36: =AE36/sum($Z36:$AP36) -> 0.021900312 | AW36: =AF36/sum($Z36:$AP36) -> 0.067787491 | AX36: =AG36/sum($Z36:$AP36) -> 0.034478053 | AY36: =AH36/sum($Z36:$AP36) -> 0.019572899 | ... BG36: =AP36/sum($Z36:$AP36) -> 0.0088005429 | BH36: 43 | BI36: 3561.932 | BJ36: 1.2862058 | BK36: 3954382 | BL36: =BI36*1000/BK36 -> 0.90075567 | BM36: 45.83 | BN36: 84.11 | BO36: 1783 | BP36: 255 | BQ36: 213 | BR36: 138863 | BS36: 83197 | BT36: 887 | BU36: 1107 | DA36: 29 | DB36: 11 | DC36: 40 | DD36: 1176 | DE36: 3420 | DF36: 3927 | DG36: 669 | DH36: 4596 | DI36: 201196455 | DJ36: 6833369 | DK36: 208029824 | DL36: 40376904 | DM36: 2389874 | DN36: 42766778 | DO36: 250796602 | DP36: 2040177007 | DQ36: 3809770506 | DR36: =DQ36-DP36 -> 1769593499 | DS36: 1216074564 | DT36: 38 | DU36: 2 | DV36: =DH36/DC36 -> 114.9 | DW36: =DF36/DH36 -> 0.85443864 | DX36: =DH36/DP36 -> 2.2527457e-06 | DY36: =DH36/DQ36 -> 1.2063719e-06 | DZ36: =DH36/DR36 -> 2.5972066e-06 | EA36: =DH36/DS36 -> 3.7793735e-06 | EB36: =DO36/DP36 -> 0.12292884 | EC36: =DO36/DQ36 -> 0.065829845 | ED36: =DO36/DR36 -> 0.14172554 | EE36: =DO36/DS36 -> 0.20623456 | EF36: =DO36/DH36 -> 54568.451 | EG36: =DQ36/DH36 -> 828931.79 | EH36: =DR36/DH36 -> 385029.05 | EI36: =DS36/DH36 -> 264594.12 | EJ36: =DP36/DQ36 -> 0.53551179 | EK36: =DR36/DQ36 -> 0.46448821 | EL36: =DS36/DQ36 -> 0.3191989 | EM36: =DK36/DO36 -> 0.82947625 | EN36: =DN36/DO36 -> 0.17052375 | EO36: =DI36/DF36 -> 51234.137 | EP36: =DL36/DG36 -> 60354.117 | EQ36: =DT36/DC36 -> 0.95 | ER36: =DU36/DC36 -> 0.05 | FF36: 2855820 | FH36: 0.08 | FI36: 51.8 | FJ36: 1260.5 | FK36: =FD36/L36 -> 0 | FL36: 6.32 | FM36: 6.02 | FN36: 5.53 | FO36: 4.1 | FP36: 130.8 | FQ36: 163.1 | FR36: 10 | FS36: 4.2 | FT36: 6323.5 | FU36: 5959.4 | FV36: 843.1 | FW36: =FU36-FV36 -> 5116.3 | FX36: 951.6 | FY36: 4 | FZ36: 14875.93 | GA36: 119.9
A37: Papua Selatan | B37: 2022 | H37: =D37*L37/100 -> 0
A38: Papua Tengah | B38: 2022 | H38: =D38*L38/100 -> 0
A39: Papua Pegunungan | B39: 2022 | H39: =D39*L39/100 -> 0
A40: Aceh | B40: 2023 | C40: 195 | D40: 40.14 | F40: =D40-E2 -> 39.882968 | G40: 405796 | H40: =D40*L40/100 -> 982364.28 | I40: 0.46163332 | K40: =I40-J2 -> -0.030738401 | L40: 2447345 | M40: 6.03 | N40: 4.64 | O40: 8.31 | P40: 64.77 | Q40: 80.57 | R40: 49.05 | S40: 626676 | T40: 879044 | U40: 283389 | V40: 256697 | W40: =100-X40-Y40 -> 60.6 | X40: 28.91 | Y40: 10.49 | Z40: 946649 | AA40: 23448 | AB40: 176000 | AC40: 4998 | AD40: 5435 | AE40: 178702 | AF40: 358557 | AG40: 84418 | AH40: 136548 | AI40: 9379 | AJ40: 12515 | AK40: 1495 | AL40: 24597 | AM40: 160113 | AN40: 174250 | AO40: 63201 | AP40: 87040 | AQ40: =Z40/sum(Z40:AP40) -> 0.38680652 | AR40: =AA40/sum($Z40:$AP40) -> 0.0095809949 | AS40: =AB40/sum($Z40:$AP40) -> 0.071914667 | AT40: =AC40/sum($Z40:$AP40) -> 0.0020422131 | AU40: =AD40/sum($Z40:$AP40) -> 0.0022207739 | AV40: =AE40/sum($Z40:$AP40) -> 0.07301872 | AW40: =AF40/sum($Z40:$AP40) -> 0.14650856 | AX40: =AG40/sum($Z40:$AP40) -> 0.034493706 | AY40: =AH40/sum($Z40:$AP40) -> 0.05579434 | ... BG40: =AP40/sum($Z40:$AP40) -> 0.035565072 | BH40: 38 | BI40: 3413.666 | BJ40: =BI40/BI2*100-100 -> 7.8070148 | BK40: 2594530 | BL40: =BI40*1000/BK40 -> 1.3157165 | BM40: 44.52 | BN40: 59.86 | BO40: 13977 | BP40: 1147 | BQ40: 1446 | BR40: 363301 | BS40: 96820 | BT40: 1892 | BU40: 2019 | BV40: 739 | BW40: =L40/L2*100-100 -> 2.185851 | BX40: =T40/T2*100-100 -> 4.2813724 | BY40: =U40/U2*100-100 -> -5.5886116 | BZ40: =D40-D2 -> 1.59 | CB40: =W40-W2 -> -0.9 | CC40: =X40-X2 -> 0.87 | CD40: =Y40-Y2 -> 0.03 | CE40: =BH40-BH2 -> 0 | CF40: =M40-M2 -> -0.14 | CG40: =N40-N2 -> -1.04 | CH40: =O40-O2 -> 1.29 | CI40: =P40-P2 -> 1.27 | CJ40: =Q40-Q2 -> -0.49 | CK40: =R40-R2 -> 2.9 | CL40: =BK40/BK2*100-100 -> 11.449362 | CM40: =BR40/BR2*100-100 -> 14.992324 | CN40: =BS40/BS2*100-100 -> 70.194066 | CO40: =BT40/BT2*100-100 -> 30.662983 | CP40: =BU40/BU2*100-100 -> -48.743336 | CR40: =C2 -> 84 | CS40: =D2 -> 38.55 | CU40: =BJ2 -> 0.045149637 | CV40: =BR2 -> 315935 | CW40: =BS2 -> 56888 | CX40: =BT2 -> 1448 | CY40: =BU2 -> 3939 | CZ40: =BV2 | DC40: 101 | DF40: 6555 | DG40: 2690 | DH40: 9245 | DI40: 396453063 | DJ40: 22376745 | DK40: =DI40+DJ40 -> 418829808 | DL40: 166967045 | DM40: 5750172 | DN40: 172717217 | DO40: =DN40+DK40 -> 591547025 | DP40: 13502673148 | DQ40: 24136750980 | DR40: =DQ40-DP40 -> 10634077832 | DS40: 10351005530 | DT40: 92 | DU40: 9 | DV40: =DH40/DC40 -> 91.534653 | DW40: =DF40/DH40 -> 0.70903191 | DX40: =DH40/DP40 -> 6.8467924e-07 | DY40: =DH40/DQ40 -> 3.8302587e-07 | DZ40: =DH40/DR40 -> 8.6937487e-07 | EA40: =DH40/DS40 -> 8.9314994e-07 | EB40: =DO40/DP40 -> 0.043809623 | EC40: =DO40/DQ40 -> 0.024508146 | ED40: =DO40/DR40 -> 0.055627487 | EE40: =DO40/DS40 -> 0.05714875 | EF40: =DO40/DH40 -> 63985.617 | EG40: =DQ40/DH40 -> 2610789.7 | EH40: =DR40/DH40 -> 1150251.8 | EI40: =DS40/DH40 -> 1119632.8 | EJ40: =DP40/DQ40 -> 0.55942381 | EK40: =DR40/DQ40 -> 0.44057619 | EL40: =DS40/DQ40 -> 0.42884834 | EM40: =DK40/DO40 -> 0.70802454 | EN40: =DN40/DO40 -> 0.29197546 | EO40: =DI40/DF40 -> 60481.016 | EP40: =DL40/DG40 -> 62069.533 | EQ40: =DT40/DC40 -> 0.91089109 | ER40: =DU40/DC40 -> 0.089108911 | ES40: =DQ40/DQ2*100-100 -> 13.457182 | ET40: =DP40/DP2*100-100 -> 26.753992 | EU40: =DR40/DR2*100-100 -> 0.12101559 | EV40: =DS40/DS2*100-100 -> -0.27760724 | EW40: =DH40/DH2*100-100 -> -12.815919 | EX40: =DC40/DC2*100-100 -> 16.091954 | EY40: =DO40/DO2*100-100 -> -7.1692105 | EZ40: =EH40/EH2*100-100 -> 14.838642 | FA40: =EI40/EI2*100-100 -> 14.381423 | FB40: =ET40-ES40 -> 13.29681 | FC40: =EY40-ES40 -> -20.626392 | FD40: 146932.5 | FE40: 146932500 | FF40: 6371290 | FG40: =(FF40/FE40)*100 -> 4.336202 | FH40: -1.56 | FI40: 51.3 | FJ40: 248.6 | FK40: =FD40/L40 -> 0.06003751 | FL40: 2 | FM40: 6.33 | FN40: 3.13 | FO40: 3.67 | FP40: 132.15 | FQ40: 169.1 | FR40: =(FP40-FP2)/FP2*100 -> 1.0321101 | FS40: =(FQ40-FQ2)/FQ2*100 -> 3.6787247 | FT40: 609.2 | FU40: 609.2 | FV40: 148 | FW40: =FU40-FV40 -> 461.2 | FX40: 655.5 | FY40: 5.81 | FZ40: 14875.93 | GA40: 124.4
A41: Sumatera Utara | B41: 2023 | C41: 1247 | D41: 41.48 | F41: =D41-E3 -> 41.181774 | G41: 1096942 | H41: =D41*L41/100 -> 3131547.9 | I41: 0.38572876 | K41: =I41-J3 -> -0.019656485 | L41: 7549537 | M41: 5.89 | N41: 5.58 | O41: 6.33 | P41: 71.06 | Q41: 84.4 | R41: 57.81 | S41: 1678211 | T41: 2843817 | U41: 1152216 | V41: 507793 | W41: =100-X41-Y41 -> 67.09 | X41: 26.18 | Y41: 6.73 | Z41: 2559037 | AA41: 51392 | AB41: 677302 | AC41: 17980 | AD41: 17150 | AE41: 447205 | AF41: 1442126 | AG41: 361377 | AH41: 605080 | AI41: 34228 | AJ41: 62854 | AK41: 15176 | AL41: 106069 | AM41: 285562 | AN41: 388171 | AO41: 117837 | AP41: 360991 | AQ41: =Z41/sum(Z41:AP41) -> 0.33896608 | AR41: =AA41/sum($Z41:$AP41) -> 0.0068073049 | AS41: =AB41/sum($Z41:$AP41) -> 0.089714376 | AT41: =AC41/sum($Z41:$AP41) -> 0.002381603 | AU41: =AD41/sum($Z41:$AP41) -> 0.0022716625 | AV41: =AE41/sum($Z41:$AP41) -> 0.059236083 | AW41: =AF41/sum($Z41:$AP41) -> 0.19102178 | AX41: =AG41/sum($Z41:$AP41) -> 0.047867439 | AY41: =AH41/sum($Z41:$AP41) -> 0.080147961 | ... BG41: =AP41/sum($Z41:$AP41) -> 0.04781631 | BH41: 41 | BI41: 2710.4939 | BJ41: =BI41/BI3*100-100 -> 7.4480001 | BK41: 2610584 | BL41: =BI41*1000/BK41 -> 1.0382711 | BM41: 47.19 | BN41: 58.52 | BO41: 52542 | BP41: 5896 | BQ41: 7473 | BR41: 1384255 | BS41: 579853 | BT41: 16345 | BU41: 15945 | BV41: 10388 | BW41: =L41/L3*100-100 -> 4.8929373 | BX41: =T41/T3*100-100 -> 6.0372802 | BY41: =U41/U3*100-100 -> 2.9295476 | BZ41: =D41-D3 -> 0.55 | CB41: =W41-W3 -> -1.84 | CC41: =X41-X3 -> 1.94 | CD41: =Y41-Y3 -> -0.1 | CE41: =BH41-BH3 -> -1 | CF41: =M41-M3 -> -0.27 | CG41: =N41-N3 -> -0.32 | CH41: =O41-O3 -> -0.22 | CI41: =P41-P3 -> 1.53 | CJ41: =Q41-Q3 -> 0.51 | CK41: =R41-R3 -> 2.44 | CL41: =BK41/BK3*100-100 -> 1.3251608 | CM41: =BR41/BR3*100-100 -> 15.164849 | CN41: =BS41/BS3*100-100 -> 105.21775 | CO41: =BT41/BT3*100-100 -> 52.188082 | CP41: =BU41/BU3*100-100 -> -38.214438 | CR41: =C3 -> 70 | CS41: =D3 -> 40.93 | CU41: =BJ3 -> 0.92769171 | CV41: =BR3 -> 1201977 | CW41: =BS3 -> 282555 | CX41: =BT3 -> 10740 | CY41: =BU3 -> 25807 | CZ41: =BV3 | DC41: 1246 | DF41: 174782 | DG41: 49236 | DH41: 224018 | DI41: 9617862948 | DJ41: 780795464 | DK41: =DI41+DJ41 -> 10398658412 | DL41: 3740814858 | DM41: 519717760 | DN41: 4260532617 | DO41: =DN41+DK41 -> 14659191029 | DP41: 239692596346 | DQ41: 336357971287 | DR41: =DQ41-DP41 -> 96665374941 | DS41: 90494181761 | DT41: 1199 | DU41: 47 | DV41: =DH41/DC41 -> 179.78973 | DW41: =DF41/DH41 -> 0.78021409 | DX41: =DH41/DP41 -> 9.3460542e-07 | DY41: =DH41/DQ41 -> 6.6601068e-07 | DZ41: =DH41/DR41 -> 2.3174586e-06 | EA41: =DH41/DS41 -> 2.4754962e-06 | EB41: =DO41/DP41 -> 0.061158297 | EC41: =DO41/DQ41 -> 0.043582113 | ED41: =DO41/DR41 -> 0.15164883 | EE41: =DO41/DS41 -> 0.16199043 | EF41: =DO41/DH41 -> 65437.559 | EG41: =DQ41/DH41 -> 1501477.4 | EH41: =DR41/DH41 -> 431507.18 | EI41: =DS41/DH41 -> 403959.42 | EJ41: =DP41/DQ41 -> 0.71261161 | EK41: =DR41/DQ41 -> 0.28738839 | EL41: =DS41/DQ41 -> 0.26904129 | EM41: =DK41/DO41 -> 0.709361 | EN41: =DN41/DO41 -> 0.290639 | EO41: =DI41/DF41 -> 55027.766 | EP41: =DL41/DG41 -> 75977.229 | EQ41: =DT41/DC41 -> 0.96227929 | ER41: =DU41/DC41 -> 0.037720706 | ES41: =DQ41/DQ3*100-100 -> 16.618613 | ET41: =DP41/DP3*100-100 -> 21.751518 | EU41: =DR41/DR3*100-100 -> 5.5813885 | EV41: =DS41/DS3*100-100 -> 1.0415173 | EW41: =DH41/DH3*100-100 -> 30.893687 | EX41: =DC41/DC3*100-100 -> -1.4240506 | EY41: =DO41/DO3*100-100 -> 55.291093 | EZ41: =EH41/EH3*100-100 -> -19.338059 | FA41: =EI41/EI3*100-100 -> -22.806424 | FB41: =ET41-ES41 -> 5.1329049 | FC41: =EY41-ES41 -> 38.67248 | FD41: 602235.9 | FE41: 602235900 | FF41: 103315910 | FG41: =(FF41/FE41)*100 -> 17.155389 | FH41: 3.44 | FI41: 51.3 | FJ41: 1181.3 | FK41: =FD41/L41 -> 0.079771236 | FL41: 0.11 | FM41: 6.33 | FN41: 2.72 | FO41: 3.64 | FP41: 132.15 | FQ41: 169.1 | FR41: =(FP41-FP3)/FP3*100 -> 1.0321101 | FS41: =(FQ41-FQ3)/FQ3*100 -> 3.6787247 | FT41: 10238.9 | FU41: 10238.9 | FV41: 5820.8 | FW41: =FU41-FV41 -> 4418.1 | FX41: 5037.9 | FY41: 5.81 | FZ41: 14875.93 | GA41: 124.4
A42: Sumatera Barat | B42: 2023 | C42: 465 | D42: 35.81 | F42: =D42-E4 -> 35.570578 | G42: 442236 | H42: =D42*L42/100 -> 1018767.6 | I42: 0.49301892 | K42: =I42-J4 -> 0.029848076 | L42: 2844925 | M42: 5.94 | N42: 5.31 | O42: 6.84 | P42: 69.61 | Q42: 82.21 | R42: 56.94 | S42: 694094 | T42: 896996 | U42: 363308 | V42: 279045 | W42: =100-X42-Y42 -> 64.65 | X42: 25.54 | Y42: 9.81 | Z42: 964493 | AA42: 35487 | AB42: 245568 | AC42: 6365 | AD42: 6666 | AE42: 130223 | AF42: 529285 | AG42: 110681 | AH42: 237846 | AI42: 24953 | AJ42: 23674 | AK42: 1977 | AL42: 44776 | AM42: 140148 | AN42: 187278 | AO42: 55009 | AP42: 100496 | AQ42: =Z42/sum(Z42:AP42) -> 0.33902229 | AR42: =AA42/sum($Z42:$AP42) -> 0.012473791 | AS42: =AB42/sum($Z42:$AP42) -> 0.086317917 | AT42: =AC42/sum($Z42:$AP42) -> 0.0022373173 | AU42: =AD42/sum($Z42:$AP42) -> 0.0023431198 | AV42: =AE42/sum($Z42:$AP42) -> 0.04577379 | AW42: =AF42/sum($Z42:$AP42) -> 0.18604533 | AX42: =AG42/sum($Z42:$AP42) -> 0.038904716 | AY42: =AH42/sum($Z42:$AP42) -> 0.08360361 | ... BG42: =AP42/sum($Z42:$AP42) -> 0.035324657 | BH42: 39 | BI42: 2742.476 | BJ42: =BI42/BI4*100-100 -> 9.1515793 | BK42: 2753517 | BL42: =BI42*1000/BK42 -> 0.99599022 | BM42: 51.54 | BN42: 64.19 | BO42: 36285 | BP42: 20516 | BQ42: 5534 | BR42: 404050 | BS42: 239627 | BT42: 3582 | BU42: 3539 | BV42: 3665 | BW42: =L42/L4*100-100 -> 5.8315266 | BX42: =T42/T4*100-100 -> 6.6960707 | BY42: =U42/U4*100-100 -> -6.1951655 | BZ42: =D42-D4 -> 1.07 | CB42: =W42-W4 -> -1.09 | CC42: =X42-X4 -> -0.04 | CD42: =Y42-Y4 -> 1.13 | CE42: =BH42-BH4 -> 0 | CF42: =M42-M4 -> -0.34 | CG42: =N42-N4 -> -0.89 | CH42: =O42-O4 -> 0.45 | CI42: =P42-P4 -> 0.31 | CJ42: =Q42-Q4 -> -0.37 | CK42: =R42-R4 -> 0.66 | CL42: =BK42/BK4*100-100 -> 3.6806693 | CM42: =BR42/BR4*100-100 -> 8.0570064 | CN42: =BS42/BS4*100-100 -> 115.09344 | CO42: =BT42/BT4*100-100 -> 33.606863 | CP42: =BU42/BU4*100-100 -> -55.140068 | CR42: =C4 -> 35 | CS42: =D4 -> 34.74 | CU42: =BJ4 -> 1.1472435 | CV42: =BR4 -> 373923 | CW42: =BS4 -> 111406 | CX42: =BT4 -> 2681 | CY42: =BU4 -> 7889 | CZ42: =BV4 | DC42: 212 | DF42: 18812 | DG42: 5776 | DH42: 24588 | DI42: 955692619 | DJ42: 191998981 | DK42: =DI42+DJ42 -> 1147691600 | DL42: 413730235 | DM42: 94700868 | DN42: 508431103 | DO42: =DN42+DK42 -> 1656122703 | DP42: 42332517621 | DQ42: 68243082279 | DR42: =DQ42-DP42 -> 25910564658 | DS42: 25382838175 | DT42: 203 | DU42: 9 | DV42: =DH42/DC42 -> 115.98113 | DW42: =DF42/DH42 -> 0.76508866 | DX42: =DH42/DP42 -> 5.8083009e-07 | DY42: =DH42/DQ42 -> 3.6030026e-07 | DZ42: =DH42/DR42 -> 9.4895655e-07 | EA42: =DH42/DS42 -> 9.68686e-07 | EB42: =DO42/DP42 -> 0.039121763 | EC42: =DO42/DQ42 -> 0.024267994 | ED42: =DO42/DR42 -> 0.06391689 | EE42: =DO42/DS42 -> 0.065245765 | EF42: =DO42/DH42 -> 67354.917 | EG42: =DQ42/DH42 -> 2775462.9 | EH42: =DR42/DH42 -> 1053789 | EI42: =DS42/DH42 -> 1032326.3 | EJ42: =DP42/DQ42 -> 0.62031954 | EK42: =DR42/DQ42 -> 0.37968046 | EL42: =DS42/DQ42 -> 0.37194742 | EM42: =DK42/DO42 -> 0.69299913 | EN42: =DN42/DO42 -> 0.30700087 | EO42: =DI42/DF42 -> 50802.287 | EP42: =DL42/DG42 -> 71629.196 | EQ42: =DT42/DC42 -> 0.95754717 | ER42: =DU42/DC42 -> 0.04245283 | ES42: =DQ42/DQ4*100-100 -> 5.0729021 | ET42: =DP42/DP4*100-100 -> 4.7317018 | EU42: =DR42/DR4*100-100 -> 5.6351619 | EV42: =DS42/DS4*100-100 -> 4.8197656 | EW42: =DH42/DH4*100-100 -> 46.505392 | EX42: =DC42/DC4*100-100 -> 8.1632653 | EY42: =DO42/DO4*100-100 -> 97.333196 | EZ42: =EH42/EH4*100-100 -> -27.896741 | FA42: =EI42/EI4*100-100 -> -28.453305 | FB42: =ET42-ES42 -> -0.34120034 | FC42: =EY42-ES42 -> 92.260294 | FD42: 191069.3 | FE42: 191069300 | FF42: 17440380 | FG42: =(FF42/FE42)*100 -> 9.1277772 | FH42: 3.09 | FI42: 51.3 | FJ42: 120.7 | FK42: =FD42/L42 -> 0.067161454 | FL42: -1.14 | FM42: 6.33 | FN42: 2.68 | FO42: 3.53 | FP42: 132.15 | FQ42: 169.1 | FR42: =(FP42-FP4)/FP4*100 -> 1.0321101 | FS42: =(FQ42-FQ4)/FQ4*100 -> 3.6787247 | FT42: 2366.7 | FU42: 2366.7 | FV42: 399.6 | FW42: =FU42-FV42 -> 1967.1 | FX42: 1257.2 | FY42: 5.81 | FZ42: 15254.41 | GA42: 124.4
A43: Riau | B43: 2023 | C43: 4063 | D43: 47.87 | F43: =D43-E5 -> 47.574804 | G43: 567868 | H43: =D43*L43/100 -> 1437217.3 | I43: 0.46001664 | K43: =I43-J5 -> -0.048635042 | L43: 3002334 | M43: 4.23 | N43: 3.63 | O43: 5.4 | P43: 64.45 | Q43: 83.77 | R43: 44.27 | S43: 688343 | T43: 1234451 | U43: 308472 | V43: 241033 | W43: =100-X43-Y43 -> 65.07 | X43: 26.9 | Y43: 8.03 | Z43: 1146960 | AA43: 43021 | AB43: 236877 | AC43: 5638 | AD43: 15181 | AE43: 179126 | AF43: 523429 | AG43: 102891 | AH43: 207327 | AI43: 25171 | AJ43: 27018 | AK43: 5176 | AL43: 48681 | AM43: 117133 | AN43: 165758 | AO43: 43194 | AP43: 109753 | AQ43: =Z43/sum(Z43:AP43) -> 0.38202279 | AR43: =AA43/sum($Z43:$AP43) -> 0.014329185 | AS43: =AB43/sum($Z43:$AP43) -> 0.078897618 | AT43: =AC43/sum($Z43:$AP43) -> 0.0018778723 | AU43: =AD43/sum($Z43:$AP43) -> 0.0050563995 | AV43: =AE43/sum($Z43:$AP43) -> 0.059662249 | AW43: =AF43/sum($Z43:$AP43) -> 0.1743407 | AX43: =AG43/sum($Z43:$AP43) -> 0.034270338 | AY43: =AH43/sum($Z43:$AP43) -> 0.069055275 | ... BG43: =AP43/sum($Z43:$AP43) -> 0.036555893 | BH43: 41 | BI43: 3191.6625 | BJ43: =BI43/BI5*100-100 -> 8.6130001 | BK43: 3011040 | BL43: =BI43*1000/BK43 -> 1.0599868 | BM43: 43.08 | BN43: 52.13 | BO43: 25052 | BP43: 773 | BQ43: 2902 | BR43: 619922 | BS43: 254906 | BT43: 6901 | BU43: 6408 | BV43: 1591 | BW43: =L43/L5*100-100 -> -5.2571389 | BX43: =T43/T5*100-100 -> -3.38181 | BY43: =U43/U5*100-100 -> -7.8489362 | BZ43: =D43-D5 -> 1.89 | CB43: =W43-W5 -> 1.46 | CC43: =X43-X5 -> -2.07 | CD43: =Y43-Y5 -> 0.61 | CE43: =BH43-BH5 -> 1 | CF43: =M43-M5 -> -0.14 | CG43: =N43-N5 -> -0.09 | CH43: =O43-O5 -> -0.28 | CI43: =P43-P5 -> 0.59 | CJ43: =Q43-Q5 -> 0.18 | CK43: =R43-R5 -> 0.99 | CL43: =BK43/BK5*100-100 -> 4.1993763 | CM43: =BR43/BR5*100-100 -> 4.5396137 | CN43: =BS43/BS5*100-100 -> 46.574358 | CO43: =BT43/BT5*100-100 -> 45.253631 | CP43: =BU43/BU5*100-100 -> -38.313439 | CR43: =C5 -> 916 | CS43: =D5 -> 45.98 | CU43: =BJ5 -> 1.7309639 | CV43: =BR5 -> 593002 | CW43: =BS5 -> 173909 | CX43: =BT5 -> 4751 | CY43: =BU5 -> 10388 | CZ43: =BV5 | DC43: 388 | DF43: 67907 | DG43: 35016 | DH43: 102923 | DI43: 3806429922 | DJ43: 205486354 | DK43: =DI43+DJ43 -> 4011916276 | DL43: 2200924640 | DM43: 107833767 | DN43: 2308758407 | DO43: =DN43+DK43 -> 6320674683 | DP43: 368809110228 | DQ43: 557698133495 | DR43: =DQ43-DP43 -> 188889023267 | DS43: 186276022264 | DT43: 332 | DU43: 56 | DV43: =DH43/DC43 -> 265.26546 | DW43: =DF43/DH43 -> 0.6597845 | DX43: =DH43/DP43 -> 2.7906849e-07 | DY43: =DH43/DQ43 -> 1.8454966e-07 | DZ43: =DH43/DR43 -> 5.4488608e-07 | EA43: =DH43/DS43 -> 5.5252951e-07 | EB43: =DO43/DP43 -> 0.017138065 | EC43: =DO43/DQ43 -> 0.011333505 | ED43: =DO43/DR43 -> 0.033462372 | EE43: =DO43/DS43 -> 0.033931768 | EF43: =DO43/DH43 -> 61411.683 | EG43: =DQ43/DH43 -> 5418595.8 | EH43: =DR43/DH43 -> 1835246 | EI43: =DS43/DH43 -> 1809858.1 | EJ43: =DP43/DQ43 -> 0.66130598 | EK43: =DR43/DQ43 -> 0.33869402 | EL43: =DS43/DQ43 -> 0.33400869 | EM43: =DK43/DO43 -> 0.63472912 | EN43: =DN43/DO43 -> 0.36527088 | EO43: =DI43/DF43 -> 56053.572 | EP43: =DL43/DG43 -> 62854.828 | EQ43: =DT43/DC43 -> 0.8556701 | ER43: =DU43/DC43 -> 0.1443299 | ES43: =DQ43/DQ5*100-100 -> -5.7941029 | ET43: =DP43/DP5*100-100 -> -10.843071 | EU43: =DR43/DR5*100-100 -> 5.9173133 | EV43: =DS43/DS5*100-100 -> 5.4409611 | EW43: =DH43/DH5*100-100 -> 25.106967 | EX43: =DC43/DC5*100-100 -> 0.51813471 | EY43: =DO43/DO5*100-100 -> -5.8767691 | EZ43: =EH43/EH5*100-100 -> -15.338598 | FA43: =EI43/EI5*100-100 -> -15.719353 | FB43: =ET43-ES43 -> -5.0489682 | FC43: =EY43-ES43 -> -0.082666266 | FD43: 551828.5 | FE43: 551828500 | FF43: 176290050 | FG43: =(FF43/FE43)*100 -> 31.946529 | FH43: 3.63 | FI43: 51.3 | FJ43: 2042.3 | FK43: =FD43/L43 -> 0.18379984 | FL43: 9.99 | FM43: 6.33 | FN43: 2.84 | FO43: 3.41 | FP43: 132.15 | FQ43: 169.1 | FR43: =(FP43-FP5)/FP5*100 -> 1.0321101 | FS43: =(FQ43-FQ5)/FQ5*100 -> 3.6787247 | FT43: 18956.8 | FU43: 18956.8 | FV43: 2335.9 | FW43: =FU43-FV43 -> 16620.9 | FX43: 1987.7 | FY43: 5.81 | FZ43: 15254.41 | GA43: 124.4
A44: Jambi | B44: 2023 | C44: 331 | D44: 40.27 | F44: =D44-E6 -> 39.994068 | G44: 284600 | H44: =D44*L44/100 -> 725771.71 | I44: 0.44773208 | K44: =I44-J6 -> 0.019723148 | L44: 1802264 | M44: 4.53 | N44: 3.64 | O44: 6.05 | P44: 68.75 | Q44: 85.27 | R44: 51.68 | S44: 455085 | T44: 635648 | U44: 238950 | V44: 166946 | W44: =100-X44-Y44 -> 59.34 | X44: 31.4 | Y44: 9.26 | Z44: 814402 | AA44: 60352 | AB44: 85245 | AC44: 4622 | AD44: 7071 | AE44: 81584 | AF44: 272341 | AG44: 63408 | AH44: 97651 | AI44: 5382 | AJ44: 15964 | AK44: 1541 | AL44: 23457 | AM44: 97079 | AN44: 91432 | AO44: 30119 | AP44: 50614 | AQ44: =Z44/sum(Z44:AP44) -> 0.45187719 | AR44: =AA44/sum($Z44:$AP44) -> 0.03348677 | AS44: =AB44/sum($Z44:$AP44) -> 0.047298842 | AT44: =AC44/sum($Z44:$AP44) -> 0.0025645521 | AU44: =AD44/sum($Z44:$AP44) -> 0.0039233986 | AV44: =AE44/sum($Z44:$AP44) -> 0.045267508 | AW44: =AF44/sum($Z44:$AP44) -> 0.15111049 | AX44: =AG44/sum($Z44:$AP44) -> 0.035182415 | AY44: =AH44/sum($Z44:$AP44) -> 0.054182406 | ... BG44: =AP44/sum($Z44:$AP44) -> 0.028083566 | BH44: 38 | BI44: 2943.0331 | BJ44: =BI44/BI6*100-100 -> 11.098341 | BK44: 2668478 | BL44: =BI44*1000/BK44 -> 1.1028883 | BM44: 45.37 | BN44: 59.73 | BO44: 23224 | BP44: 4554 | BQ44: 5470 | BR44: 300622 | BS44: 214514 | BT44: 2207 | BU44: 2512 | BV44: 1794 | BW44: =L44/L6*100-100 -> 0.24724402 | BX44: =T44/T6*100-100 -> 1.0712168 | BY44: =U44/U6*100-100 -> -7.198838 | BZ44: =D44-D6 -> 0.25 | CB44: =W44-W6 -> -2.52 | CC44: =X44-X6 -> 0.72 | CD44: =Y44-Y6 -> 1.8 | CE44: =BH44-BH6 -> -1 | CF44: =M44-M6 -> -0.06 | CG44: =N44-N6 -> -0.69 | CH44: =O44-O6 -> 1 | CI44: =P44-P6 -> 0.91 | CJ44: =Q44-Q6 -> -0.9 | CK44: =R44-R6 -> 2.71 | CL44: =BK44/BK6*100-100 -> 5.8597641 | CM44: =BR44/BR6*100-100 -> 11.934319 | CN44: =BS44/BS6*100-100 -> 90.967685 | CO44: =BT44/BT6*100-100 -> 14.649351 | CP44: =BU44/BU6*100-100 -> -19.564521 | CR44: =C6 -> 92 | CS44: =D6 -> 40.02 | CU44: =BJ6 -> 0.71752649 | CV44: =BR6 -> 268570 | CW44: =BS6 -> 112330 | CX44: =BT6 -> 1925 | CY44: =BU6 -> 3123 | CZ44: =BV6 | DC44: 193 | DF44: 17155 | DG44: 6331 | DH44: 23486 | DI44: 821532146 | DJ44: 37732148 | DK44: =DI44+DJ44 -> 859264294 | DL44: 400671035 | DM44: 8002764 | DN44: 408673799 | DO44: =DN44+DK44 -> 1267938093 | DP44: 40472068541 | DQ44: 66391447353 | DR44: =DQ44-DP44 -> 25919378812 | DS44: 24452737882 | DT44: 183 | DU44: 10 | DV44: =DH44/DC44 -> 121.68912 | DW44: =DF44/DH44 -> 0.73043515 | DX44: =DH44/DP44 -> 5.8030145e-07 | DY44: =DH44/DQ44 -> 3.5375038e-07 | DZ44: =DH44/DR44 -> 9.0611739e-07 | EA44: =DH44/DS44 -> 9.6046505e-07 | EB44: =DO44/DP44 -> 0.03132872 | EC44: =DO44/DQ44 -> 0.019097913 | ED44: =DO44/DR44 -> 0.048918537 | EE44: =DO44/DS44 -> 0.051852602 | EF44: =DO44/DH44 -> 53986.975 | EG44: =DQ44/DH44 -> 2826852.1 | EH44: =DR44/DH44 -> 1103609.8 | EI44: =DS44/DH44 -> 1041162.3 | EJ44: =DP44/DQ44 -> 0.60959762 | EK44: =DR44/DQ44 -> 0.39040238 | EL44: =DS44/DQ44 -> 0.36831157 | EM44: =DK44/DO44 -> 0.67768632 | EN44: =DN44/DO44 -> 0.32231368 | EO44: =DI44/DF44 -> 47888.787 | EP44: =DL44/DG44 -> 63287.164 | EQ44: =DT44/DC44 -> 0.94818653 | ER44: =DU44/DC44 -> 0.051813471 | ES44: =DQ44/DQ6*100-100 -> 6.2991667 | ET44: =DP44/DP6*100-100 -> 6.9930243 | EU44: =DR44/DR6*100-100 -> 5.2335526 | EV44: =DS44/DS6*100-100 -> 0.11188419 | EW44: =DH44/DH6*100-100 -> -15.678742 | EX44: =DC44/DC6*100-100 -> 0 | EY44: =DO44/DO6*100-100 -> -29.648347 | EZ44: =EH44/EH6*100-100 -> 24.800738 | FA44: =EI44/EI6*100-100 -> 18.726744 | FB44: =ET44-ES44 -> 0.69385763 | FC44: =EY44-ES44 -> -35.947513 | FD44: 169259 | FE44: 169259000 | FF44: 16892880 | FG44: =(FF44/FE44)*100 -> 9.9804914 | FH44: 4.16 | FI44: 51.3 | FJ44: 45.1 | FK44: =FD44/L44 -> 0.093914654 | FL44: 4.4 | FM44: 6.33 | FN44: 2.6 | FO44: 3.22 | FP44: 132.15 | FQ44: 169.1 | FR44: =(FP44-FP6)/FP6*100 -> 1.0321101 | FS44: =(FQ44-FQ6)/FQ6*100 -> 3.6787247 | FT44: 2192.8 | FU44: 2192.8 | FV44: 78.6 | FW44: =FU44-FV44 -> 2114.2 | FX44: 957.3 | FY44: 5.81 | FZ44: 15254.41 | GA44: 124.4
A45: Sumatera Selatan | B45: 2023 | C45: 188 | D45: 37.03 | F45: =D45-E7 -> 36.773203 | G45: 627687 | H45: =D45*L45/100 -> 1629193.7 | I45: 0.42115197 | K45: =I45-J7 -> 0.019274618 | L45: 4399659 | M45: 4.11 | N45: 3.96 | O45: 4.34 | P45: 70.72 | Q45: 85.39 | R45: 55.54 | S45: 1063720 | T45: 1490405 | U45: 757671 | V45: 372104 | W45: =100-X45-Y45 -> 65.62 | X45: 25.92 | Y45: 8.46 | Z45: 1967142 | AA45: 88052 | AB45: 273151 | AC45: 14527 | AD45: 12033 | AE45: 221873 | AF45: 718902 | AG45: 196805 | AH45: 224071 | AI45: 19000 | AJ45: 27427 | AK45: 6257 | AL45: 55821 | AM45: 155351 | AN45: 205081 | AO45: 69728 | AP45: 144438 | AQ45: =Z45/sum(Z45:AP45) -> 0.44711238 | AR45: =AA45/sum($Z45:$AP45) -> 0.020013369 | AS45: =AB45/sum($Z45:$AP45) -> 0.062084584 | AT45: =AC45/sum($Z45:$AP45) -> 0.0033018468 | AU45: =AD45/sum($Z45:$AP45) -> 0.0027349847 | AV45: =AE45/sum($Z45:$AP45) -> 0.05042959 | AW45: =AF45/sum($Z45:$AP45) -> 0.16339948 | AX45: =AG45/sum($Z45:$AP45) -> 0.044731876 | AY45: =AH45/sum($Z45:$AP45) -> 0.050929174 | ... BG45: =AP45/sum($Z45:$AP45) -> 0.032829362 | BH45: 42 | BI45: 3404.1772 | BJ45: =BI45/BI7*100-100 -> 8.26 | BK45: 2767669 | BL45: =BI45*1000/BK45 -> 1.2299799 | BM45: 47.28 | BN45: 62.97 | BO45: 48174 | BP45: 4629 | BQ45: 8172 | BR45: 679919 | BS45: 197422 | BT45: 9064 | BU45: 9184 | BV45: 3636 | BW45: =L45/L7*100-100 -> 2.5632305 | BX45: =T45/T7*100-100 -> 1.3849916 | BY45: =U45/U7*100-100 -> -3.5229417 | BZ45: =D45-D7 -> 0.31 | CB45: =W45-W7 -> 1.08 | CC45: =X45-X7 -> -2.46 | CD45: =Y45-Y7 -> 1.38 | CE45: =BH45-BH7 -> 1 | CF45: =M45-M7 -> -0.52 | CG45: =N45-N7 -> -0.57 | CH45: =O45-O7 -> -0.46 | CI45: =P45-P7 -> 1.41 | CJ45: =Q45-Q7 -> 0.44 | CK45: =R45-R7 -> 2.22 | CL45: =BK45/BK7*100-100 -> 5.206761 | CM45: =BR45/BR7*100-100 -> 18.473634 | CN45: =BS45/BS7*100-100 -> 107.44142 | CO45: =BT45/BT7*100-100 -> 93.633839 | CP45: =BU45/BU7*100-100 -> -45.05534 | CR45: =C7 -> 160 | CS45: =D7 -> 36.72 | CU45: =BJ7 -> 3.3299804 | CV45: =BR7 -> 573899 | CW45: =BS7 -> 95170 | CX45: =BT7 -> 4681 | CY45: =BU7 -> 16715 | CZ45: =BV7 | DC45: 316 | DF45: 40988 | DG45: 14457 | DH45: 55445 | DI45: 2465355038 | DJ45: 349648576 | DK45: =DI45+DJ45 -> 2815003614 | DL45: 1197514512 | DM45: 150147034 | DN45: 1347661546 | DO45: =DN45+DK45 -> 4162665160 | DP45: 83866412250 | DQ45: 179216061686 | DR45: =DQ45-DP45 -> 95349649436 | DS45: 93252960804 | DT45: 295 | DU45: 21 | DV45: =DH45/DC45 -> 175.45886 | DW45: =DF45/DH45 -> 0.73925512 | DX45: =DH45/DP45 -> 6.6111091e-07 | DY45: =DH45/DQ45 -> 3.0937517e-07 | DZ45: =DH45/DR45 -> 5.8149139e-07 | EA45: =DH45/DS45 -> 5.9456557e-07 | EB45: =DO45/DP45 -> 0.049634473 | EC45: =DO45/DQ45 -> 0.023227076 | ED45: =DO45/DR45 -> 0.043656848 | EE45: =DO45/DS45 -> 0.044638424 | EF45: =DO45/DH45 -> 75077.377 | EG45: =DQ45/DH45 -> 3232321.4 | EH45: =DR45/DH45 -> 1719715.9 | EI45: =DS45/DH45 -> 1681900.3 | EJ45: =DP45/DQ45 -> 0.46796259 | EK45: =DR45/DQ45 -> 0.53203741 | EL45: =DS45/DQ45 -> 0.52033819 | EM45: =DK45/DO45 -> 0.67625031 | EN45: =DN45/DO45 -> 0.32374969 | EO45: =DI45/DF45 -> 60148.215 | EP45: =DL45/DG45 -> 82832.85 | EQ45: =DT45/DC45 -> 0.9335443 | ER45: =DU45/DC45 -> 0.066455696 | ES45: =DQ45/DQ7*100-100 -> -2.5116201 | ET45: =DP45/DP7*100-100 -> -6.5390819 | EU45: =DR45/DR7*100-100 -> 1.3290254 | EV45: =DS45/DS7*100-100 -> 0.34054314 | EW45: =DH45/DH7*100-100 -> -19.406652 | EX45: =DC45/DC7*100-100 -> 1.607717 | EY45: =DO45/DO7*100-100 -> -17.249175 | EZ45: =EH45/EH7*100-100 -> 25.72877 | FA45: =EI45/EI7*100-100 -> 24.502264 | FB45: =ET45-ES45 -> -4.0274618 | FC45: =EY45-ES45 -> -14.737555 | FD45: 360967.5 | FE45: 360967500 | FF45: 65761470 | FG45: =(FF45/FE45)*100 -> 18.218114 | FH45: 3.69 | FI45: 51.3 | FJ45: 1478.6 | FK45: =FD45/L45 -> 0.082044427 | FL45: 2.45 | FM45: 6.33 | FN45: 2.93 | FO45: 3.29 | FP45: 132.15 | FQ45: 169.1 | FR45: =(FP45-FP7)/FP7*100 -> 1.0321101 | FS45: =(FQ45-FQ7)/FQ7*100 -> 3.6787247 | FT45: 6585.5 | FU45: 6585.5 | FV45: 1164.4 | FW45: =FU45-FV45 -> 5421.1 | FX45: 3259.8 | FY45: 5.81 | FZ45: 15254.41 | GA45: 124.4
A46: Bengkulu | B46: 2023 | C46: 25 | D46: 32.23 | F46: =D46-E8 -> 31.988064 | G46: 173228 | H46: =D46*L46/100 -> 344736.91 | I46: 0.55869547 | K46: =I46-J8 -> 0.0628135 | L46: 1069615 | M46: 3.42 | N46: 3.06 | O46: 3.99 | P46: 70.91 | Q46: 84.99 | R46: 56.22 | S46: 232544 | T46: 310058 | U46: 179072 | V46: 99534 | W46: =100-X46-Y46 -> 63.41 | X46: 27.28 | Y46: 9.31 | Z46: 484033 | AA46: 15420 | AB46: 59845 | AC46: 2198 | AD46: 2015 | AE46: 48586 | AF46: 173448 | AG46: 30147 | AH46: 52419 | AI46: 5335 | AJ46: 8476 | AK46: 1610 | AL46: 10802 | AM46: 67950 | AN46: 56976 | AO46: 18287 | AP46: 32068 | AQ46: =Z46/sum(Z46:AP46) -> 0.45253012 | AR46: =AA46/sum($Z46:$AP46) -> 0.014416402 | AS46: =AB46/sum($Z46:$AP46) -> 0.055950038 | AT46: =AC46/sum($Z46:$AP46) -> 0.002054945 | AU46: =AD46/sum($Z46:$AP46) -> 0.0018838554 | AV46: =AE46/sum($Z46:$AP46) -> 0.045423821 | AW46: =AF46/sum($Z46:$AP46) -> 0.16215928 | AX46: =AG46/sum($Z46:$AP46) -> 0.028184908 | AY46: =AH46/sum($Z46:$AP46) -> 0.049007353 | ... BG46: =AP46/sum($Z46:$AP46) -> 0.029980881 | BH46: 38 | BI46: 2418.28 | BJ46: =BI46/BI8*100-100 -> 8.0508533 | BK46: 2740734 | BL46: =BI46*1000/BK46 -> 0.88234758 | BM46: 49.03 | BN46: 67.77 | BO46: 8227 | BP46: 1499 | BQ46: 1479 | BR46: 135440 | BS46: 85305 | BT46: 1157 | BU46: 1283 | BV46: 1736 | BW46: =L46/L8*100-100 -> 3.0958192 | BX46: =T46/T8*100-100 -> 4.1368169 | BY46: =U46/U8*100-100 -> -1.5027172 | BZ46: =D46-D8 -> -0.23 | CB46: =W46-W8 -> 0.35 | CC46: =X46-X8 -> -1.64 | CD46: =Y46-Y8 -> 1.29 | CE46: =BH46-BH8 -> 0 | CF46: =M46-M8 -> -0.17 | CG46: =N46-N8 -> -0.33 | CH46: =O46-O8 -> 0.08 | CI46: =P46-P8 -> 1.1 | CJ46: =Q46-Q8 -> 0.27 | CK46: =R46-R8 -> 1.86 | CL46: =BK46/BK8*100-100 -> 0.10592315 | CM46: =BR46/BR8*100-100 -> 15.718155 | CN46: =BS46/BS8*100-100 -> 243.61154 | CO46: =BT46/BT8*100-100 -> 38.729017 | CP46: =BU46/BU8*100-100 -> -34.473953 | CR46: =C8 -> 26 | CS46: =D8 -> 32.46 | CU46: =BJ8 -> 1.0426325 | CV46: =BR8 -> 117043 | CW46: =BS8 -> 24826 | CX46: =BT8 -> 834 | CY46: =BU8 -> 1958 | CZ46: =BV8 | DC46: 76 | DF46: 5826 | DG46: 1443 | DH46: 7269 | DI46: 238882229 | DJ46: 4094138 | DK46: =DI46+DJ46 -> 242976367 | DL46: 99339424 | DM46: 3643995 | DN46: 102983419 | DO46: =DN46+DK46 -> 345959786 | DP46: 13443108460 | DQ46: 18568642002 | DR46: =DQ46-DP46 -> 5125533542 | DS46: 4790941919 | DT46: 69 | DU46: 7 | DV46: =DH46/DC46 -> 95.644737 | DW46: =DF46/DH46 -> 0.80148576 | DX46: =DH46/DP46 -> 5.4072315e-07 | DY46: =DH46/DQ46 -> 3.9146643e-07 | DZ46: =DH46/DR46 -> 1.4181938e-06 | EA46: =DH46/DS46 -> 1.5172382e-06 | EB46: =DO46/DP46 -> 0.025735103 | EC46: =DO46/DQ46 -> 0.018631399 | ED46: =DO46/DR46 -> 0.067497322 | EE46: =DO46/DS46 -> 0.072211225 | EF46: =DO46/DH46 -> 47593.862 | EG46: =DQ46/DH46 -> 2554497.5 | EH46: =DR46/DH46 -> 705122.24 | EI46: =DS46/DH46 -> 659092.3 | EJ46: =DP46/DQ46 -> 0.72396831 | EK46: =DR46/DQ46 -> 0.27603169 | EL46: =DS46/DQ46 -> 0.25801251 | EM46: =DK46/DO46 -> 0.70232546 | EN46: =DN46/DO46 -> 0.29767454 | EO46: =DI46/DF46 -> 41002.786 | EP46: =DL46/DG46 -> 68842.29 | EQ46: =DT46/DC46 -> 0.90789474 | ER46: =DU46/DC46 -> 0.092105263 | ES46: =DQ46/DQ8*100-100 -> 8.4842453 | ET46: =DP46/DP8*100-100 -> 17.611394 | EU46: =DR46/DR8*100-100 -> -9.8622484 | EV46: =DS46/DS8*100-100 -> -14.212024 | EW46: =DH46/DH8*100-100 -> 13.083385 | EX46: =DC46/DC8*100-100 -> 2.7027027 | EY46: =DO46/DO8*100-100 -> 10.574655 | EZ46: =EH46/EH8*100-100 -> -20.290897 | FA46: =EI46/EI8*100-100 -> -24.137418 | FB46: =ET46-ES46 -> 9.1271488 | FC46: =EY46-ES46 -> 2.09041 | FD46: 52051.6 | FE46: 52051600 | FF46: 2915700 | FG46: =(FF46/FE46)*100 -> 5.6015569 | FH46: 1.83 | FI46: 51.3 | FJ46: 76.1 | FK46: =FD46/L46 -> 0.048663865 | FL46: 1.13 | FM46: 6.33 | FN46: 3.09 | FO46: 3.57 | FP46: 132.15 | FQ46: 169.1 | FR46: =(FP46-FP8)/FP8*100 -> 1.0321101 | FS46: =(FQ46-FQ8)/FQ8*100 -> 3.6787247 | FT46: 246.4 | FU46: 4645.8 | FW46: =FU46-FV46 -> 4645.8 | FX46: 538.6 | FY46: 5.81 | FZ46: 15254.41 | GA46: 124.4
A47: Lampung | B47: 2023 | C47: 75 | D47: 29.33 | F47: =D47-E9 -> 29.120443 | G47: 493408 | H47: =D47*L47/100 -> 1377823.1 | I47: 0.39409396 | K47: =I47-J9 -> -0.014116211 | L47: 4697658 | M47: 4.23 | N47: 3.34 | O47: 5.77 | P47: 70.04 | Q47: 87.3 | R47: 52.01 | S47: 1032382 | T47: 1252006 | U47: 801985 | V47: 399557 | W47: =100-X47-Y47 -> 62.85 | X47: 28.64 | Y47: 8.51 | Z47: 1987969 | AA47: 37008 | AB47: 409675 | AC47: 8344 | AD47: 14431 | AE47: 261032 | AF47: 890458 | AG47: 191404 | AH47: 240011 | AI47: 20324 | AJ47: 37146 | AK47: 5731 | AL47: 40190 | AM47: 144674 | AN47: 195710 | AO47: 48976 | AP47: 164575 | AQ47: =Z47/sum(Z47:AP47) -> 0.423183 | AR47: =AA47/sum($Z47:$AP47) -> 0.0078779681 | AS47: =AB47/sum($Z47:$AP47) -> 0.087208349 | AT47: =AC47/sum($Z47:$AP47) -> 0.0017762042 | AU47: =AD47/sum($Z47:$AP47) -> 0.0030719563 | AV47: =AE47/sum($Z47:$AP47) -> 0.055566412 | AW47: =AF47/sum($Z47:$AP47) -> 0.1895536 | AX47: =AG47/sum($Z47:$AP47) -> 0.040744558 | AY47: =AH47/sum($Z47:$AP47) -> 0.051091629 | ... BG47: =AP47/sum($Z47:$AP47) -> 0.035033415 | BH47: 40 | BI47: 2633.2846 | BJ47: =BI47/BI9*100-100 -> 7.9000001 | BK47: 2424538 | BL47: =BI47*1000/BK47 -> 1.0860975 | BM47: 55.57 | BN47: 70.67 | BO47: 42725 | BP47: 2850 | BQ47: 5465 | BR47: 564393 | BS47: 168497 | BT47: 4885 | BU47: 5987 | BV47: 2905 | BW47: =L47/L9*100-100 -> 7.0577575 | BX47: =T47/T9*100-100 -> 10.306177 | BY47: =U47/U9*100-100 -> -0.73017909 | BZ47: =D47-D9 -> 0.84 | CB47: =W47-W9 -> -0.53 | CC47: =X47-X9 -> -1.06 | CD47: =Y47-Y9 -> 1.59 | CE47: =BH47-BH9 -> 0 | CF47: =M47-M9 -> -0.29 | CG47: =N47-N9 -> -0.76 | CH47: =O47-O9 -> 0.53 | CI47: =P47-P9 -> -0.02 | CJ47: =Q47-Q9 -> 1.46 | CK47: =R47-R9 -> -1.53 | CL47: =BK47/BK9*100-100 -> 4.383208 | CM47: =BR47/BR9*100-100 -> 20.783131 | CN47: =BS47/BS9*100-100 -> 75.869447 | CO47: =BT47/BT9*100-100 -> 52.990918 | CP47: =BU47/BU9*100-100 -> -49.185198 | CR47: =C9 -> 30 | CS47: =D9 -> 28.49 | CU47: =BJ9 -> 0.34887354 | CV47: =BR9 -> 467278 | CW47: =BS9 -> 95808 | CX47: =BT9 -> 3193 | CY47: =BU9 -> 11782 | CZ47: =BV9 | DC47: 410 | DF47: 50650 | DG47: 13204 | DH47: 63854 | DI47: 1902524285 | DJ47: 67217397 | DK47: =DI47+DJ47 -> 1969741682 | DL47: 589697104 | DM47: 65743978 | DN47: 655441082 | DO47: =DN47+DK47 -> 2625182764 | DP47: 54474510407 | DQ47: 79119815576 | DR47: =DQ47-DP47 -> 24645305169 | DS47: 24086293945 | DT47: 397 | DU47: 13 | DV47: =DH47/DC47 -> 155.74146 | DW47: =DF47/DH47 -> 0.79321577 | DX47: =DH47/DP47 -> 1.1721813e-06 | DY47: =DH47/DQ47 -> 8.0705446e-07 | DZ47: =DH47/DR47 -> 2.5909194e-06 | EA47: =DH47/DS47 -> 2.6510513e-06 | EB47: =DO47/DP47 -> 0.04819103 | EC47: =DO47/DQ47 -> 0.033179839 | ED47: =DO47/DR47 -> 0.10651857 | EE47: =DO47/DS47 -> 0.10899073 | EF47: =DO47/DH47 -> 41112.268 | EG47: =DQ47/DH47 -> 1239073.8 | EH47: =DR47/DH47 -> 385963.37 | EI47: =DS47/DH47 -> 377208.85 | EJ47: =DP47/DQ47 -> 0.68850654 | EK47: =DR47/DQ47 -> 0.31149346 | EL47: =DS47/DQ47 -> 0.30442809 | EM47: =DK47/DO47 -> 0.75032554 | EN47: =DN47/DO47 -> 0.24967446 | EO47: =DI47/DF47 -> 37562.177 | EP47: =DL47/DG47 -> 44660.49 | EQ47: =DT47/DC47 -> 0.96829268 | ER47: =DU47/DC47 -> 0.031707317 | ES47: =DQ47/DQ9*100-100 -> -0.96643969 | ET47: =DP47/DP9*100-100 -> 4.1871802 | EU47: =DR47/DR9*100-100 -> -10.727053 | EV47: =DS47/DS9*100-100 -> -11.023614 | EW47: =DH47/DH9*100-100 -> 5.6048954 | EX47: =DC47/DC9*100-100 -> -1.4423077 | EY47: =DO47/DO9*100-100 -> 1.8150543 | EZ47: =EH47/EH9*100-100 -> -15.465143 | FA47: =EI47/EI9*100-100 -> -15.745965 | FB47: =ET47-ES47 -> 5.1536199 | FC47: =EY47-ES47 -> 2.781494 | FD47: 269240.5 | FE47: 269240500 | FF47: 47257570 | FG47: =(FF47/FE47)*100 -> 17.552177 | FH47: 1.4 | FI47: 51.3 | FJ47: 220.6 | FK47: =FD47/L47 -> 0.057313772 | FL47: -2.35 | FM47: 6.33 | FN47: 2.89 | FO47: 3.38 | FP47: 132.15 | FQ47: 169.1 | FR47: =(FP47-FP9)/FP9*100 -> 1.0321101 | FS47: =(FQ47-FQ9)/FQ9*100 -> 3.6787247 | FT47: 4645.8 | FU47: 246.4 | FV47: 2153.9 | FW47: =FU47-FV47 -> -1907.5 | FX47: 1935.4 | FY47: 5.81 | FZ47: 15254.41 | GA47: 124.4
A48: Bangka Belitung | B48: 2023 | C48: 207 | D48: 48.93 | F48: =D48-E10 -> 48.577969 | G48: 144399 | H48: =D48*L48/100 -> 366884.48 | I48: 0.43785402 | K48: =I48-J10 -> 0.069854947 | L48: 749815 | M48: 4.56 | N48: 3.25 | O48: 6.9 | P48: 68.34 | Q48: 85.38 | R48: 50.31 | S48: 218634 | T48: 329788 | U48: 65011 | V48: 40111 | W48: =100-X48-Y48 -> 72.35 | X48: 22.3 | Y48: 5.35 | Z48: 188091 | AA48: 124027 | AB48: 53823 | AC48: 4516 | AD48: 2502 | AE48: 36683 | AF48: 125487 | AG48: 16849 | AH48: 47807 | AI48: 5998 | AJ48: 5080 | AK48: 1541 | AL48: 7770 | AM48: 46431 | AN48: 40976 | AO48: 14371 | AP48: 27863 | AQ48: =Z48/sum(Z48:AP48) -> 0.25084988 | AR48: =AA48/sum($Z48:$AP48) -> 0.16541013 | AS48: =AB48/sum($Z48:$AP48) -> 0.071781706 | AT48: =AC48/sum($Z48:$AP48) -> 0.006022819 | AU48: =AD48/sum($Z48:$AP48) -> 0.0033368231 | AV48: =AE48/sum($Z48:$AP48) -> 0.048922734 | AW48: =AF48/sum($Z48:$AP48) -> 0.16735728 | AX48: =AG48/sum($Z48:$AP48) -> 0.022470876 | AY48: =AH48/sum($Z48:$AP48) -> 0.063758394 | ... BG48: =AP48/sum($Z48:$AP48) -> 0.037159833 | BH48: 41 | BI48: 3498.479 | BJ48: =BI48/BI10*100-100 -> 7.1547718 | BK48: 3221747 | BL48: =BI48*1000/BK48 -> 1.085895 | BM48: 44.77 | BN48: 51.07 | BO48: 5497 | BP48: 620 | BQ48: 930 | BR48: 118592 | BS48: 89001 | BT48: 703 | BU48: 981 | BV48: 272 | BW48: =L48/L10*100-100 -> 2.5778005 | BX48: =T48/T10*100-100 -> 1.4582462 | BY48: =U48/U10*100-100 -> 9.230976 | BZ48: =D48-D10 -> -1.44 | CB48: =W48-W10 -> -2.58 | CC48: =X48-X10 -> 0.6 | CD48: =Y48-Y10 -> 1.98 | CE48: =BH48-BH10 -> 0 | CF48: =M48-M10 -> -0.21 | CG48: =N48-N10 -> -1.08 | CH48: =O48-O10 -> 1.28 | CI48: =P48-P10 -> 0.96 | CJ48: =Q48-Q10 -> -0.64 | CK48: =R48-R10 -> 2.76 | CL48: =BK48/BK10*100-100 -> 8.5075304 | CM48: =BR48/BR10*100-100 -> 12.868441 | CN48: =BS48/BS10*100-100 -> 78.78867 | CO48: =BT48/BT10*100-100 -> -9.8717949 | CP48: =BU48/BU10*100-100 -> -37.115385 | CR48: =C10 -> 380 | CS48: =D10 -> 50.37 | CU48: =BJ10 -> 1.0792596 | CV48: =BR10 -> 105071 | CW48: =BS10 -> 49780 | CX48: =BT10 -> 780 | CY48: =BU10 -> 1560 | CZ48: =BV10 | DC48: 138 | DF48: 13364 | DG48: 4599 | DH48: 17963 | DI48: 886847682 | DJ48: 46407211 | DK48: =DI48+DJ48 -> 933254893 | DL48: 312248153 | DM48: 18447706 | DN48: 330695859 | DO48: =DN48+DK48 -> 1263950752 | DP48: 30474586241 | DQ48: 55847549225 | DR48: =DQ48-DP48 -> 25372962984 | DS48: 24784448823 | DT48: 133 | DU48: 5 | DV48: =DH48/DC48 -> 130.16667 | DW48: =DF48/DH48 -> 0.74397372 | DX48: =DH48/DP48 -> 5.8944197e-07 | DY48: =DH48/DQ48 -> 3.2164348e-07 | DZ48: =DH48/DR48 -> 7.0795831e-07 | EA48: =DH48/DS48 -> 7.2476899e-07 | EB48: =DO48/DP48 -> 0.041475567 | EC48: =DO48/DQ48 -> 0.022632161 | ED48: =DO48/DR48 -> 0.049814866 | EE48: =DO48/DS48 -> 0.050997735 | EF48: =DO48/DH48 -> 70364.124 | EG48: =DQ48/DH48 -> 3109032.4 | EH48: =DR48/DH48 -> 1412512.6 | EI48: =DS48/DH48 -> 1379750 | EJ48: =DP48/DQ48 -> 0.54567455 | EK48: =DR48/DQ48 -> 0.45432545 | EL48: =DS48/DQ48 -> 0.44378758 | EM48: =DK48/DO48 -> 0.73836334 | EN48: =DN48/DO48 -> 0.26163666 | EO48: =DI48/DF48 -> 66360.946 | EP48: =DL48/DG48 -> 67894.793 | EQ48: =DT48/DC48 -> 0.96376812 | ER48: =DU48/DC48 -> 0.036231884 | ES48: =DQ48/DQ10*100-100 -> 13.34946 | ET48: =DP48/DP10*100-100 -> 41.254985 | EU48: =DR48/DR10*100-100 -> -8.3878634 | EV48: =DS48/DS10*100-100 -> -8.6681687 | EW48: =DH48/DH10*100-100 -> 25.712086 | EX48: =DC48/DC10*100-100 -> 25.454545 | EY48: =DO48/DO10*100-100 -> 62.691957 | EZ48: =EH48/EH10*100-100 -> -27.125435 | FA48: =EI48/EI10*100-100 -> -27.348409 | FB48: =ET48-ES48 -> 27.905526 | FC48: =EY48-ES48 -> 49.342497 | FD48: 60336.3 | FE48: 60336300 | FF48: 12724000 | FG48: =(FF48/FE48)*100 -> 21.088466 | FH48: 1.92 | FI48: 51.3 | FJ48: 72.5 | FK48: =FD48/L48 -> 0.080468249 | FL48: 1.76 | FM48: 6.33 | FN48: 2.53 | FO48: 3.22 | FP48: 132.15 | FQ48: 169.1 | FR48: =(FP48-FP10)/FP10*100 -> 1.0321101 | FS48: =(FQ48-FQ10)/FQ10*100 -> 3.6787247 | FT48: 2034.7 | FU48: 2034.7 | FV48: 19.5 | FW48: =FU48-FV48 -> 2015.2 | FX48: 470.8 | FY48: 5.81 | FZ48: 15254.41 | GA48: 124.4
A49: Kepulauan Riau | B49: 2023 | C49: 683 | D49: 66.33 | F49: =D49-E11 -> 65.911741 | G49: 396909 | H49: =D49*L49/100 -> 676138.83 | I49: 0.62243735 | K49: =I49-J11 -> 0.019012042 | L49: 1019356 | N49: 5.95 | O49: 8.23 | P49: 68.68 | Q49: 84.92 | R49: 51.95 | S49: 205557 | T49: 637669 | U49: 62859 | V49: 48892 | W49: =100-X49-Y49 -> 80.98 | X49: 14.22 | Y49: 4.8 | Z49: 85171 | AA49: 11497 | AB49: 257178 | AC49: 4907 | AD49: 5076 | AE49: 78903 | AF49: 167687 | AG49: 63396 | AH49: 91889 | AI49: 9384 | AJ49: 12817 | AK49: 8117 | AL49: 28894 | AM49: 56550 | AN49: 53048 | AO49: 21257 | AP49: 63585 | AQ49: =Z49/sum(Z49:AP49) -> 0.083553734 | AR49: =AA49/sum($Z49:$AP49) -> 0.01127869 | AS49: =AB49/sum($Z49:$AP49) -> 0.25229459 | AT49: =AC49/sum($Z49:$AP49) -> 0.0048138236 | AU49: =AD49/sum($Z49:$AP49) -> 0.0049796146 | AV49: =AE49/sum($Z49:$AP49) -> 0.077404754 | AW49: =AF49/sum($Z49:$AP49) -> 0.16450288 | AX49: =AG49/sum($Z49:$AP49) -> 0.062192208 | AY49: =AH49/sum($Z49:$AP49) -> 0.090144169 | ... BG49: =AP49/sum($Z49:$AP49) -> 0.062377619 | BH49: 45 | BI49: 3279.194 | BJ49: =BI49/BI11*100-100 -> 7.5084946 | BK49: 4651057 | BL49: =BI49*1000/BK49 -> 0.70504275 | BM49: 29.45 | BN49: 33.67 | BO49: 22146 | BP49: 250 | BQ49: 3183 | BR49: 294533 | BS49: 113122 | BT49: 4031 | BU49: 3878 | BV49: 4653 | BW49: =L49/L11*100-100 -> -11.820186 | BX49: =T49/T11*100-100 -> -8.754003 | BY49: =U49/U11*100-100 -> -17.955779 | BZ49: =D49-D11 -> 2.65 | CB49: =W49-W11 -> 1.66 | CC49: =X49-X11 -> -1.51 | CD49: =Y49-Y11 -> -0.15 | CE49: =BH49-BH11 -> 1 | CF49: =M49-M11 -> 0 | CG49: =N49-N11 -> -1.83 | CH49: =O49-O11 -> -0.8 | CI49: =P49-P11 -> -0.26 | CJ49: =Q49-Q11 -> 4.9 | CK49: =R49-R11 -> 1.27 | CL49: =BK49/BK11*100-100 -> 11.924789 | CM49: =BR49/BR11*100-100 -> -5.041735 | CN49: =BS49/BS11*100-100 -> 29.944632 | CO49: =BT49/BT11*100-100 -> -0.12388503 | CP49: =BU49/BU11*100-100 -> -71.652047 | CR49: =C11 -> 863 | CS49: =D11 -> 63.68 | CU49: =BJ11 -> 1.4876924 | CV49: =BR11 -> 310171 | CW49: =BS11 -> 87054 | CX49: =BT11 -> 4036 | CY49: =BU11 -> 13680 | CZ49: =BV11 | DC49: 704 | DF49: 188273 | DG49: 16191 | DH49: 204464 | DI49: 14778850334 | DJ49: 3120278976 | DK49: =DI49+DJ49 -> 17899129310 | DL49: 1971690844 | DM49: 457059805 | DN49: 2428750649 | DO49: =DN49+DK49 -> 20327879959 | DP49: 107092234381 | DQ49: 201257572770 | DR49: =DQ49-DP49 -> 94165338389 | DS49: 91058550658 | DT49: 83 | DU49: 621 | DV49: =DH49/DC49 -> 290.43182 | DW49: =DF49/DH49 -> 0.92081247 | DX49: =DH49/DP49 -> 1.9092327e-06 | DY49: =DH49/DQ49 -> 1.015932e-06 | DZ49: =DH49/DR49 -> 2.1713297e-06 | EA49: =DH49/DS49 -> 2.2454124e-06 | EB49: =DO49/DP49 -> 0.18981656 | EC49: =DO49/DQ49 -> 0.1010043 | ED49: =DO49/DR49 -> 0.21587434 | EE49: =DO49/DS49 -> 0.22323966 | EF49: =DO49/DH49 -> 99420.338 | EG49: =DQ49/DH49 -> 984317.89 | EH49: =DR49/DH49 -> 460547.28 | EI49: =DS49/DH49 -> 445352.49 | EJ49: =DP49/DQ49 -> 0.5321153 | EK49: =DR49/DQ49 -> 0.4678847 | EL49: =DS49/DQ49 -> 0.45244782 | EM49: =DK49/DO49 -> 0.8805212 | EN49: =DN49/DO49 -> 0.1194788 | EO49: =DI49/DF49 -> 78496.918 | EP49: =DL49/DG49 -> 121776.97 | EQ49: =DT49/DC49 -> 0.11789773 | ER49: =DU49/DC49 -> 0.88210227 | ES49: =DQ49/DQ11*100-100 -> 5.1054845 | ET49: =DP49/DP11*100-100 -> 5.239975 | EU49: =DR49/DR11*100-100 -> 4.9529485 | EV49: =DS49/DS11*100-100 -> 3.1927904 | EW49: =DH49/DH11*100-100 -> 22.59283 | EX49: =DC49/DC11*100-100 -> 7.1537291 | EY49: =DO49/DO11*100-100 -> 55.26302 | EZ49: =EH49/EH11*100-100 -> -14.389 | FA49: =EI49/EI11*100-100 -> -15.824775 | FB49: =ET49-ES49 -> 0.1344905 | FC49: =EY49-ES49 -> 50.157536 | FD49: 199912.8 | FE49: 199912800 | FF49: 81302960 | FG49: =(FF49/FE49)*100 -> 40.669212 | FH49: 2.48 | FI49: 51.3 | FJ49: 764.1 | FK49: =FD49/L49 -> 0.19611676 | FL49: 19.3 | FM49: 6.33 | FN49: 2.79 | FO49: 3.38 | FP49: 132.15 | FQ49: 169.1 | FR49: =(FP49-FP11)/FP11*100 -> 1.0321101 | FS49: =(FQ49-FQ11)/FQ11*100 -> 3.6787247 | FT49: 17729 | FU49: 17789.3 | FV49: 17900.3 | FW49: =FU49-FV49 -> -111 | FX49: 1517.9 | FY49: 5.81 | FZ49: 15254.41 | GA49: 124.4
A50: DKI Jakarta | B50: 2023 | C50: 2413 | D50: 63.77 | F50: =D50-E12 -> 63.353256 | G50: 1873472 | H50: =D50*L50/100 -> 3234884.4 | I50: 0.6145487 | K50: =I50-J12 -> 0.052533947 | L50: 5072737 | M50: 6.53 | N50: 7.76 | O50: 4.55 | P50: 65.21 | Q50: 80.25 | R50: 50.12 | S50: 1162880 | T50: 3048533 | U50: 284951 | V50: 150130 | W50: =100-X50-Y50 -> 84.26 | X50: 12.78 | Y50: 2.96 | Z50: 23705 | AA50: 15157 | AB50: 562017 | AC50: 15361 | AD50: 18207 | AE50: 227719 | AF50: 1177577 | AG50: 602062 | AH50: 621697 | AI50: 130859 | AJ50: 193337 | AK50: 132359 | AL50: 236137 | AM50: 251415 | AN50: 267247 | AO50: 129393 | AP50: 468488 | AQ50: =Z50/sum(Z50:AP50) -> 0.0046730197 | AR50: =AA50/sum($Z50:$AP50) -> 0.0029879333 | AS50: =AB50/sum($Z50:$AP50) -> 0.11079167 | AT50: =AC50/sum($Z50:$AP50) -> 0.0030281483 | AU50: =AD50/sum($Z50:$AP50) -> 0.0035891867 | AV50: =AE50/sum($Z50:$AP50) -> 0.044890756 | AW50: =AF50/sum($Z50:$AP50) -> 0.23213839 | AX50: =AG50/sum($Z50:$AP50) -> 0.11868583 | AY50: =AH50/sum($Z50:$AP50) -> 0.12255652 | ... BG50: =AP50/sum($Z50:$AP50) -> 0.092354088 | BH50: 44 | BI50: 4901.7978 | BJ50: =BI50/BI12*100-100 -> 5.6 | BK50: 5532624 | BL50: =BI50*1000/BK50 -> 0.88598065 | BM50: 36.12 | BN50: 36.23 | BO50: 85385 | BP50: 12802 | BQ50: 15816 | BR50: 1684807 | BS50: 519032 | BT50: 20615 | BU50: 24989 | BV50: 15582 | BW50: =L50/L12*100-100 -> 4.0539665 | BX50: =T50/T12*100-100 -> 4.2890258 | BY50: =U50/U12*100-100 -> 17.52883 | BZ50: =D50-D12 -> 0.65 | CB50: =W50-W12 -> 2.45 | CC50: =X50-X12 -> -2.7 | CD50: =Y50-Y12 -> 0.25 | CE50: =BH50-BH12 -> 0 | CF50: =M50-M12 -> -0.65 | CG50: =N50-N12 -> 0.26 | CH50: =O50-O12 -> -2.1 | CI50: =P50-P12 -> 2.13 | CJ50: =Q50-Q12 -> 0.23 | CK50: =R50-R12 -> 3.5 | CL50: =BK50/BK12*100-100 -> 5.2665386 | CM50: =BR50/BR12*100-100 -> -2.9410782 | CN50: =BS50/BS12*100-100 -> 43.156757 | CO50: =BT50/BT12*100-100 -> 13.794436 | CP50: =BU50/BU12*100-100 -> -49.491662 | CR50: =C12 -> 1655 | CS50: =D12 -> 63.12 | CU50: =BJ12 -> 5.1100072 | CV50: =BR12 -> 1735860 | CW50: =BS12 -> 362562 | CX50: =BT12 -> 18116 | CY50: =BU12 -> 49475 | CZ50: =BV12 | DC50: 1512 | DF50: 169712 | DG50: 49593 | DH50: 219305 | DI50: 11517169936 | DJ50: 520548894 | DK50: =DI50+DJ50 -> 12037718830 | DL50: 4878498267 | DM50: 494558414 | DN50: 5373056681 | DO50: =DN50+DK50 -> 17410775511 | DP50: 223826589064 | DQ50: 448335786672 | DR50: =DQ50-DP50 -> 224509197608 | DS50: 217948279382 | DT50: 1383 | DU50: 129 | DV50: =DH50/DC50 -> 145.04299 | DW50: =DF50/DH50 -> 0.77386289 | DX50: =DH50/DP50 -> 9.797987e-07 | DY50: =DH50/DQ50 -> 4.8915346e-07 | DZ50: =DH50/DR50 -> 9.7681967e-07 | EA50: =DH50/DS50 -> 1.006225e-06 | EB50: =DO50/DP50 -> 0.077786896 | EC50: =DO50/DQ50 -> 0.038834231 | ED50: =DO50/DR50 -> 0.077550389 | EE50: =DO50/DS50 -> 0.079884895 | EF50: =DO50/DH50 -> 79390.691 | EG50: =DQ50/DH50 -> 2044348.2 | EH50: =DR50/DH50 -> 1023730.4 | EI50: =DS50/DH50 -> 993813.54 | EJ50: =DP50/DQ50 -> 0.49923873 | EK50: =DR50/DQ50 -> 0.50076127 | EL50: =DS50/DQ50 -> 0.48612733 | EM50: =DK50/DO50 -> 0.69139475 | EN50: =DN50/DO50 -> 0.30860525 | EO50: =DI50/DF50 -> 67863.026 | EP50: =DL50/DG50 -> 98370.703 | EQ50: =DT50/DC50 -> 0.91468254 | ER50: =DU50/DC50 -> 0.08531746 | ES50: =DQ50/DQ12*100-100 -> -8.7946113 | ET50: =DP50/DP12*100-100 -> -20.555203 | EU50: =DR50/DR12*100-100 -> 6.9964196 | EV50: =DS50/DS12*100-100 -> 4.4221556 | EW50: =DH50/DH12*100-100 -> -12.286421 | EX50: =DC50/DC12*100-100 -> -6.0285892 | EY50: =DO50/DO12*100-100 -> 7.3853273 | EZ50: =EH50/EH12*100-100 -> 21.983871 | FA50: =EI50/EI12*100-100 -> 19.049019 | FB50: =ET50-ES50 -> -11.760591 | FC50: =EY50-ES50 -> 16.179939 | FD50: 2050474.5 | FE50: 2050474500 | FF50: 232990980 | FG50: =(FF50/FE50)*100 -> 11.362784 | FH50: 1.86 | FI50: 51.3 | FJ50: 4830 | FK50: =FD50/L50 -> 0.40421463 | FL50: 0.87 | FM50: 6.33 | FN50: 1.83 | FO50: 2.6 | FP50: 132.15 | FQ50: 169.1 | FR50: =(FP50-FP12)/FP12*100 -> 1.0321101 | FS50: =(FQ50-FQ12)/FQ12*100 -> 3.6787247 | FT50: 11076.4 | FU50: 11076.4 | FV50: 100956.2 | FW50: =FU50-FV50 -> -89879.8 | FX50: 69457.3 | FY50: 5.81 | FZ50: 15254.41 | GA50: 124.4
A51: Jawa Barat | B51: 2023 | C51: 19217 | D51: 44.85 | F51: =D51-E13 -> 44.550836 | G51: 5161326 | H51: =D51*L51/100 -> 10541364 | I51: 0.5284035 | K51: =I51-J13 -> -0.086358356 | L51: 23503598 | M51: 7.44 | N51: 8.09 | O51: 6.25 | P51: 66.49 | Q51: 84.63 | R51: 47.98 | S51: 5465649 | T51: 9767774 | U51: 2139242 | V51: 1486113 | W51: =100-X51-Y51 -> 74.34 | X51: 19.34 | Y51: 6.32 | Z51: 3603172 | AA51: 121346 | AB51: 4439057 | AC51: 69190 | AD51: 132613 | AE51: 1785412 | AF51: 5359329 | AG51: 1187049 | AH51: 2276859 | AI51: 250391 | AJ51: 323583 | AK51: 139256 | AL51: 511159 | AM51: 539896 | AN51: 1092869 | AO51: 333422 | AP51: 1338995 | AQ51: =Z51/sum(Z51:AP51) -> 0.153303 | AR51: =AA51/sum($Z51:$AP51) -> 0.0051628691 | AS51: =AB51/sum($Z51:$AP51) -> 0.18886713 | AT51: =AC51/sum($Z51:$AP51) -> 0.0029438046 | AU51: =AD51/sum($Z51:$AP51) -> 0.0056422425 | AV51: =AE51/sum($Z51:$AP51) -> 0.075963348 | AW51: =AF51/sum($Z51:$AP51) -> 0.22802164 | AX51: =AG51/sum($Z51:$AP51) -> 0.050504991 | AY51: =AH51/sum($Z51:$AP51) -> 0.096872785 | ... BG51: =AP51/sum($Z51:$AP51) -> 0.056969788 | BH51: 42 | BI51: 1986.6702 | BJ51: =BI51/BI13*100-100 -> 7.884 | BK51: 3674236 | BL51: =BI51*1000/BK51 -> 0.54070293 | BM51: 49.23 | BN51: 55.15 | BO51: 542150 | BP51: 35546 | BQ51: 73925 | BR51: 4373889 | BS51: 1343349 | BT51: 58749 | BU51: 78987 | BV51: 78383 | BW51: =L51/L13*100-100 -> 0.21758811 | BX51: =T51/T13*100-100 -> -0.79692341 | BY51: =U51/U13*100-100 -> 2.9522142 | BZ51: =D51-D13 -> -0.54 | CB51: =W51-W13 -> 0.46 | CC51: =X51-X13 -> -1.16 | CD51: =Y51-Y13 -> 0.7 | CE51: =BH51-BH13 -> 0 | CF51: =M51-M13 -> -0.87 | CG51: =N51-N13 -> -0.46 | CH51: =O51-O13 -> -1.64 | CI51: =P51-P13 -> 0.34 | CJ51: =Q51-Q13 -> 0.7 | CK51: =R51-R13 -> -0.03 | CL51: =BK51/BK13*100-100 -> 3.9795812 | CM51: =BR51/BR13*100-100 -> 4.061623 | CN51: =BS51/BS13*100-100 -> 35.957829 | CO51: =BT51/BT13*100-100 -> 25.580351 | CP51: =BU51/BU13*100-100 -> -50.35917 | CR51: =C13 -> 4629 | CS51: =D13 -> 45.39 | CU51: =BJ13 -> 1.7198844 | CV51: =BR13 -> 4203172 | CW51: =BS13 -> 988063 | CX51: =BT13 -> 46782 | CY51: =BU13 -> 159117 | CZ51: =BV13 | DC51: 8699 | DF51: 1698768 | DG51: 372127 | DH51: 2070895 | DI51: 94682984672 | DJ51: 6292315916 | DK51: =DI51+DJ51 -> 100975300588 | DL51: 28440900934 | DM51: 3336069386 | DN51: 31776970319 | DO51: =DN51+DK51 -> 132752270907 | DP51: 975448726600 | DQ51: 1978958563180 | DR51: =DQ51-DP51 -> 1003509836580 | DS51: 988547095048 | DT51: 6736 | DU51: 1963 | DV51: =DH51/DC51 -> 238.06127 | DW51: =DF51/DH51 -> 0.8203062 | DX51: =DH51/DP51 -> 2.1230178e-06 | DY51: =DH51/DQ51 -> 1.046457e-06 | DZ51: =DH51/DR51 -> 2.0636519e-06 | EA51: =DH51/DS51 -> 2.0948875e-06 | EB51: =DO51/DP51 -> 0.13609354 | EC51: =DO51/DQ51 -> 0.067081885 | ED51: =DO51/DR51 -> 0.13228796 | EE51: =DO51/DS51 -> 0.13429028 | EF51: =DO51/DH51 -> 64103.815 | EG51: =DQ51/DH51 -> 955605.46 | EH51: =DR51/DH51 -> 484577.85 | EI51: =DS51/DH51 -> 477352.59 | EJ51: =DP51/DQ51 -> 0.49291013 | EK51: =DR51/DQ51 -> 0.50708987 | EL51: =DS51/DQ51 -> 0.49952895 | EM51: =DK51/DO51 -> 0.76062955 | EN51: =DN51/DO51 -> 0.23937045 | EO51: =DI51/DF51 -> 55736.266 | EP51: =DL51/DG51 -> 76427.942 | EQ51: =DT51/DC51 -> 0.77434188 | ER51: =DU51/DC51 -> 0.22565812 | ES51: =DQ51/DQ13*100-100 -> -1.5640049 | ET51: =DP51/DP13*100-100 -> -6.9905301 | EU51: =DR51/DR13*100-100 -> 4.3541626 | EV51: =DS51/DS13*100-100 -> 3.5778496 | EW51: =DH51/DH13*100-100 -> 9.3465119 | EX51: =DC51/DC13*100-100 -> -0.17213679 | EY51: =DO51/DO13*100-100 -> 17.14447 | EZ51: =EH51/EH13*100-100 -> -4.5656229 | FA51: =EI51/EI13*100-100 -> -5.2755796 | FB51: =ET51-ES51 -> -5.4265253 | FC51: =EY51-ES51 -> 18.708474 | FD51: 1669406.4 | FE51: 1669406400 | FF51: 715811270 | FG51: =(FF51/FE51)*100 -> 42.878191 | FH51: 4.74 | FI51: 51.3 | FJ51: 8283.7 | FK51: =FD51/L51 -> 0.071027695 | FL51: 4.77 | FM51: 6.33 | FN51: 2.48 | FO51: 3.17 | FP51: 132.15 | FQ51: 169.1 | FR51: =(FP51-FP13)/FP13*100 -> 1.0321101 | FS51: =(FQ51-FQ13)/FQ13*100 -> 3.6787247 | FT51: 36632.4 | FU51: 36632.4 | FV51: 5956.7 | FW51: =FU51-FV51 -> 30675.7 | FX51: 18276.5 | FY51: 5.81 | FZ51: 15254.41 | GA51: 124.4
A52: Jawa Tengah | B52: 2023 | C52: 9435 | D52: 39.61 | F52: =D52-E14 -> 39.335332 | G52: 3256746 | H52: =D52*L52/100 -> 7917593.4 | I52: 0.44450471 | K52: =I52-J14 -> 0.010972118 | L52: 19988875 | M52: 5.13 | N52: 5.43 | O52: 4.69 | P52: 71.72 | Q52: 84.52 | R52: 58.92 | S52: 4639252 | T52: 7326685 | U52: 2284516 | V52: 1279171 | W52: =100-X52-Y52 -> 70.49 | X52: 23.11 | Y52: 6.4 | Z52: 4883060 | AA52: 116667 | AB52: 4184724 | AC52: 37229 | AD52: 49805 | AE52: 1740953 | AF52: 3662695 | AG52: 600410 | AH52: 1708443 | AI52: 101105 | AJ52: 222871 | AK52: 16704 | AL52: 256611 | AM52: 351803 | AN52: 820862 | AO52: 267908 | AP52: 967025 | AQ52: =Z52/sum(Z52:AP52) -> 0.24428889 | AR52: =AA52/sum($Z52:$AP52) -> 0.0058365966 | AS52: =AB52/sum($Z52:$AP52) -> 0.20935265 | AT52: =AC52/sum($Z52:$AP52) -> 0.001862486 | AU52: =AD52/sum($Z52:$AP52) -> 0.002491636 | AV52: =AE52/sum($Z52:$AP52) -> 0.087096097 | AW52: =AF52/sum($Z52:$AP52) -> 0.18323668 | AX52: =AG52/sum($Z52:$AP52) -> 0.030037208 | AY52: =AH52/sum($Z52:$AP52) -> 0.085469693 | ... BG52: =AP52/sum($Z52:$AP52) -> 0.04837816 | BH52: 42 | BI52: 1958.1697 | BJ52: =BI52/BI14*100-100 -> 8.0110001 | BK52: 2321344 | BL52: =BI52*1000/BK52 -> 0.84354998 | BM52: 50.39 | BN52: 60.39 | BO52: 218013 | BP52: 35191 | BQ52: 48250 | BR52: 3598758 | BS52: 772149 | BT52: 32070 | BU52: 39009 | BV52: 24302 | BW52: =L52/L14*100-100 -> 8.6915503 | BX52: =T52/T14*100-100 -> 8.2227254 | BY52: =U52/U14*100-100 -> 1.0029932 | BZ52: =D52-D14 -> -0.23 | CB52: =W52-W14 -> -0.92 | CC52: =X52-X14 -> -0.09 | CD52: =Y52-Y14 -> 1.01 | CE52: =BH52-BH14 -> 0 | CF52: =M52-M14 -> -0.44 | CG52: =N52-N14 -> -0.32 | CH52: =O52-O14 -> -0.62 | CI52: =P52-P14 -> 0.88 | CJ52: =Q52-Q14 -> 0.78 | CK52: =R52-R14 -> 0.61 | CL52: =BK52/BK14*100-100 -> 5.481307 | CM52: =BR52/BR14*100-100 -> 15.017634 | CN52: =BS52/BS14*100-100 -> 41.852843 | CO52: =BT52/BT14*100-100 -> 66.996459 | CP52: =BU52/BU14*100-100 -> -49.591657 | CR52: =C14 -> 467 | CS52: =D14 -> 39.84 | CU52: =BJ14 -> 0.77579055 | CV52: =BR14 -> 3128875 | CW52: =BS14 -> 544331 | CX52: =BT14 -> 19204 | CY52: =BU14 -> 77386 | CZ52: =BV14 | DC52: 4465 | DF52: 1156288 | DG52: 163027 | DH52: 1319315 | DI52: 41601067935 | DJ52: 2069485521 | DK52: =DI52+DJ52 -> 43670553456 | DL52: 10201021742 | DM52: 1253057337 | DN52: 11454079079 | DO52: =DN52+DK52 -> 55124632535 | DP52: 392711015649 | DQ52: 736919391466 | DR52: =DQ52-DP52 -> 344208375817 | DS52: 335042528382 | DT52: 4182 | DU52: 283 | DV52: =DH52/DC52 -> 295.47928 | DW52: =DF52/DH52 -> 0.87643057 | DX52: =DH52/DP52 -> 3.359506e-06 | DY52: =DH52/DQ52 -> 1.7903111e-06 | DZ52: =DH52/DR52 -> 3.8328963e-06 | EA52: =DH52/DS52 -> 3.9377538e-06 | EB52: =DO52/DP52 -> 0.14036946 | EC52: =DO52/DQ52 -> 0.074804155 | ED52: =DO52/DR52 -> 0.16014902 | EE52: =DO52/DS52 -> 0.16453025 | EF52: =DO52/DH52 -> 41782.768 | EG52: =DQ52/DH52 -> 558562.13 | EH52: =DR52/DH52 -> 260899.31 | EI52: =DS52/DH52 -> 253951.88 | EJ52: =DP52/DQ52 -> 0.53290905 | EK52: =DR52/DQ52 -> 0.46709095 | EL52: =DS52/DQ52 -> 0.45465289 | EM52: =DK52/DO52 -> 0.79221487 | EN52: =DN52/DO52 -> 0.20778513 | EO52: =DI52/DF52 -> 35978.12 | EP52: =DL52/DG52 -> 62572.591 | EQ52: =DT52/DC52 -> 0.93661814 | ER52: =DU52/DC52 -> 0.063381859 | ES52: =DQ52/DQ14*100-100 -> 16.096362 | ET52: =DP52/DP14*100-100 -> 25.375607 | EU52: =DR52/DR14*100-100 -> 7.0564515 | EV52: =DS52/DS14*100-100 -> 6.7174565 | EW52: =DH52/DH14*100-100 -> 12.518464 | EX52: =DC52/DC14*100-100 -> 1.0409595 | EY52: =DO52/DO14*100-100 -> 15.485168 | EZ52: =EH52/EH14*100-100 -> -4.8543258 | FA52: =EI52/EI14*100-100 -> -5.1556052 | FB52: =ET52-ES52 -> 9.2792456 | FC52: =EY52-ES52 -> -0.61119385 | FD52: 1102437.5 | FE52: 1102437500 | FF52: 361111030 | FG52: =(FF52/FE52)*100 -> 32.755692 | FH52: 4.31 | FI52: 51.3 | FJ52: 1563.7 | FK52: =FD52/L52 -> 0.055152554 | FL52: -3.42 | FM52: 6.33 | FN52: 2.88 | FO52: 3.42 | FP52: 132.15 | FQ52: 169.1 | FR52: =(FP52-FP14)/FP14*100 -> 1.0321101 | FS52: =(FQ52-FQ14)/FQ14*100 -> 3.6787247 | FT52: 10229.2 | FU52: 10229.2 | FV52: 14497.4 | FW52: =FU52-FV52 -> -4268.2 | FX52: 16063.7 | FY52: 5.81 | FZ52: 15254.41 | GA52: 124.4
A53: DI Yogyakarta | B53: 2023 | C53: 928 | D53: 46.22 | F53: =D53-E15 -> 45.878231 | G53: 421302 | H53: =D53*L53/100 -> 988973.96 | I53: 0.45934044 | K53: =I53-J15 -> -0.0084654977 | L53: 2139710 | M53: 3.69 | N53: 4.05 | O53: 3.24 | P53: 74.08 | Q53: 83.76 | R53: 64.75 | S53: 462700 | T53: 917189 | U53: 270941 | V53: 120289 | W53: =100-X53-Y53 -> 67.2 | X53: 27.18 | Y53: 5.62 | Z53: 420457 | AA53: 6841 | AB53: 294033 | AC53: 841 | AD53: 9553 | AE53: 148904 | AF53: 445522 | AG53: 80453 | AH53: 237067 | AI53: 21136 | AJ53: 27788 | AK53: 3867 | AL53: 65827 | AM53: 66277 | AN53: 143118 | AO53: 45753 | AP53: 122273 | AQ53: =Z53/sum(Z53:AP53) -> 0.19650186 | AR53: =AA53/sum($Z53:$AP53) -> 0.0031971622 | AS53: =AB53/sum($Z53:$AP53) -> 0.13741722 | AT53: =AC53/sum($Z53:$AP53) -> 0.00039304392 | AU53: =AD53/sum($Z53:$AP53) -> 0.0044646237 | AV53: =AE53/sum($Z53:$AP53) -> 0.069590739 | AW53: =AF53/sum($Z53:$AP53) -> 0.20821607 | AX53: =AG53/sum($Z53:$AP53) -> 0.037599955 | AY53: =AH53/sum($Z53:$AP53) -> 0.11079399 | ... BG53: =AP53/sum($Z53:$AP53) -> 0.05714466 | BH53: 40 | BI53: 1981.7824 | BJ53: =BI53/BI15*100-100 -> 7.6520002 | BK53: 2705601 | BL53: =BI53*1000/BK53 -> 0.732474 | BM53: 43.2 | BN53: 53.78 | BO53: 18992 | BP53: 2047 | BQ53: 3773 | BR53: 395214 | BS53: 101920 | BT53: 3156 | BU53: 4126 | BV53: 1946 | BW53: =L53/L15*100-100 -> -4.5254383 | BX53: =T53/T15*100-100 -> -4.6760433 | BY53: =U53/U15*100-100 -> 0.5387975 | BZ53: =D53-D15 -> -0.4 | CB53: =W53-W15 -> 0.14 | CC53: =X53-X15 -> -1 | CD53: =Y53-Y15 -> 0.86 | CE53: =BH53-BH15 -> 0 | CF53: =M53-M15 -> -0.37 | CG53: =N53-N15 -> 0.15 | CH53: =O53-O15 -> -1.03 | CI53: =P53-P15 -> 1.48 | CJ53: =Q53-Q15 -> 1.54 | CK53: =R53-R15 -> 1.37 | CL53: =BK53/BK15*100-100 -> 9.8684186 | CM53: =BR53/BR15*100-100 -> 8.4781212 | CN53: =BS53/BS15*100-100 -> 60.653205 | CO53: =BT53/BT15*100-100 -> 51.294343 | CP53: =BU53/BU15*100-100 -> -50.006058 | CR53: =C15 -> 113 | CS53: =D15 -> 46.62 | CU53: =BJ15 -> 4.3011632 | CV53: =BR15 -> 364326 | CW53: =BS15 -> 63441 | CX53: =BT15 -> 2086 | CY53: =BU15 -> 8253 | CZ53: =BV15 | DC53: 568 | DF53: 69200 | DG53: 14321 | DH53: 83521 | DI53: 2166976931 | DJ53: 200247240 | DK53: =DI53+DJ53 -> 2367224171 | DL53: 814331118 | DM53: 80125722 | DN53: 894456840 | DO53: =DN53+DK53 -> 3261681011 | DP53: 9071864515 | DQ53: 22510625181 | DR53: =DQ53-DP53 -> 13438760666 | DS53: 13211584019 | DT53: 521 | DU53: 47 | DV53: =DH53/DC53 -> 147.04401 | DW53: =DF53/DH53 -> 0.82853414 | DX53: =DH53/DP53 -> 9.2065969e-06 | DY53: =DH53/DQ53 -> 3.7102923e-06 | DZ53: =DH53/DR53 -> 6.2149332e-06 | EA53: =DH53/DS53 -> 6.3218006e-06 | EB53: =DO53/DP53 -> 0.35953811 | EC53: =DO53/DQ53 -> 0.14489518 | ED53: =DO53/DR53 -> 0.24270698 | EE53: =DO53/DS53 -> 0.24688039 | EF53: =DO53/DH53 -> 39052.227 | EG53: =DQ53/DH53 -> 269520.54 | EH53: =DR53/DH53 -> 160902.77 | EI53: =DS53/DH53 -> 158182.78 | EJ53: =DP53/DQ53 -> 0.40300367 | EK53: =DR53/DQ53 -> 0.59699633 | EL53: =DS53/DQ53 -> 0.58690436 | EM53: =DK53/DO53 -> 0.72576814 | EN53: =DN53/DO53 -> 0.27423186 | EO53: =DI53/DF53 -> 31314.696 | EP53: =DL53/DG53 -> 56862.727 | EQ53: =DT53/DC53 -> 0.91725352 | ER53: =DU53/DC53 -> 0.082746479 | ES53: =DQ53/DQ15*100-100 -> -0.39816221 | ET53: =DP53/DP15*100-100 -> -2.1063674 | EU53: =DR53/DR15*100-100 -> 0.78907193 | EV53: =DS53/DS15*100-100 -> 0.33011755 | EW53: =DH53/DH15*100-100 -> 4.7075195 | EX53: =DC53/DC15*100-100 -> 1.9748653 | EY53: =DO53/DO15*100-100 -> 6.3856685 | EZ53: =EH53/EH15*100-100 -> -3.742279 | FA53: =EI53/EI15*100-100 -> -4.1805994 | FB53: =ET53-ES53 -> -1.7082052 | FC53: =EY53-ES53 -> 6.7838307 | FD53: 118625.6 | FE53: 118625600 | FF53: 13441250 | FG53: =(FF53/FE53)*100 -> 11.330817 | FH53: 4.26 | FI53: 51.3 | FJ53: 46 | FK53: =FD53/L53 -> 0.055440036 | FL53: 10.05 | FM53: 6.33 | FN53: 3.17 | FO53: 3.79 | FP53: 132.15 | FQ53: 169.1 | FR53: =(FP53-FP15)/FP15*100 -> 1.0321101 | FS53: =(FQ53-FQ15)/FQ15*100 -> 3.6787247 | FT53: 472.3 | FU53: 472.3 | FV53: 8.1 | FW53: =FU53-FV53 -> 464.2 | FX53: 1453.3 | FY53: 5.81 | FZ53: 15254.41 | GA53: 124.4
A54: Jawa Timur | B54: 2023 | C54: 2498 | D54: 36.89 | F54: =D54-E16 -> 36.626554 | G54: 3636945 | H54: =D54*L54/100 -> 8375202 | I54: 0.47585033 | K54: =I54-J16 -> 0.015936722 | L54: 22703177 | M54: 4.88 | N54: 4.94 | O54: 4.8 | P54: 72.56 | Q54: 85.9 | R54: 59.46 | S54: 4879286 | T54: 7643044 | U54: 3199941 | V54: 1302671 | W54: =100-X54-Y54 -> 67.24 | X54: 27.02 | Y54: 5.74 | Z54: 7149540 | AA54: 113629 | AB54: 3451630 | AC54: 31196 | AD54: 78581 | AE54: 1506425 | AF54: 4336018 | AG54: 734446 | AH54: 1770123 | AI54: 128194 | AJ54: 231066 | AK54: 38490 | AL54: 303491 | AM54: 451558 | AN54: 1033229 | AO54: 285499 | AP54: 1060062 | AQ54: =Z54/sum(Z54:AP54) -> 0.31491364 | AR54: =AA54/sum($Z54:$AP54) -> 0.0050049823 | AS54: =AB54/sum($Z54:$AP54) -> 0.15203291 | AT54: =AC54/sum($Z54:$AP54) -> 0.0013740808 | AU54: =AD54/sum($Z54:$AP54) -> 0.0034612336 | AV54: =AE54/sum($Z54:$AP54) -> 0.066353048 | AW54: =AF54/sum($Z54:$AP54) -> 0.19098728 | AX54: =AG54/sum($Z54:$AP54) -> 0.032349922 | AY54: =AH54/sum($Z54:$AP54) -> 0.077968075 | ... BG54: =AP54/sum($Z54:$AP54) -> 0.046692232 | BH54: 42 | BI54: 2040.2443 | BJ54: =BI54/BI16*100-100 -> 7.8600002 | BK54: 2654068 | BL54: =BI54*1000/BK54 -> 0.76872345 | BM54: 50.08 | BN54: 63.11 | BO54: 220388 | BP54: 51163 | BQ54: 56171 | BR54: 3301045 | BS54: 1036429 | BT54: 27630 | BU54: 29439 | BV54: 24239 | BW54: =L54/L16*100-100 -> 5.0426559 | BX54: =T54/T16*100-100 -> 5.9159313 | BY54: =U54/U16*100-100 -> 2.9267106 | BZ54: =D54-D16 -> 0.75 | CB54: =W54-W16 -> 1.04 | CC54: =X54-X16 -> -1.01 | CD54: =Y54-Y16 -> -0.03 | CE54: =BH54-BH16 -> 1 | CF54: =M54-M16 -> -0.61 | CG54: =N54-N16 -> -0.8 | CH54: =O54-O16 -> -0.33 | CI54: =P54-P16 -> 1.33 | CJ54: =Q54-Q16 -> 0.14 | CK54: =R54-R16 -> 2.18 | CL54: =BK54/BK16*100-100 -> 0.5804259 | CM54: =BR54/BR16*100-100 -> 13.067647 | CN54: =BS54/BS16*100-100 -> 63.533158 | CO54: =BT54/BT16*100-100 -> 3.5180398 | CP54: =BU54/BU16*100-100 -> -49.464414 | CR54: =C16 -> 3574 | CS54: =D16 -> 36.14 | CU54: =BJ16 -> 1.2195162 | CV54: =BR16 -> 2919531 | CW54: =BS16 -> 633773 | CX54: =BT16 -> 26691 | CY54: =BU16 -> 58254 | CZ54: =BV16 | DC54: 6285 | DF54: 1090043 | DG54: 247520 | DH54: 1337563 | DI54: 53450495397 | DJ54: 3423241326 | DK54: =DI54+DJ54 -> 56873736723 | DL54: 19295654069 | DM54: 1738327935 | DN54: 21033982004 | DO54: =DN54+DK54 -> 77907718727 | DP54: 729035208939 | DQ54: 1209083535078 | DR54: =DQ54-DP54 -> 480048326139 | DS54: 467200631293 | DT54: 5944 | DU54: 341 | DV54: =DH54/DC54 -> 212.8183 | DW54: =DF54/DH54 -> 0.81494703 | DX54: =DH54/DP54 -> 1.8347029e-06 | DY54: =DH54/DQ54 -> 1.1062619e-06 | DZ54: =DH54/DR54 -> 2.7863091e-06 | EA54: =DH54/DS54 -> 2.8629306e-06 | EB54: =DO54/DP54 -> 0.10686414 | EC54: =DO54/DQ54 -> 0.064435348 | ED54: =DO54/DR54 -> 0.16229141 | EE54: =DO54/DS54 -> 0.16675431 | EF54: =DO54/DH54 -> 58246.018 | EG54: =DQ54/DH54 -> 903945.11 | EH54: =DR54/DH54 -> 358897.73 | EI54: =DS54/DH54 -> 349292.43 | EJ54: =DP54/DQ54 -> 0.60296513 | EK54: =DR54/DQ54 -> 0.39703487 | EL54: =DS54/DQ54 -> 0.38640889 | EM54: =DK54/DO54 -> 0.73001415 | EN54: =DN54/DO54 -> 0.26998585 | EO54: =DI54/DF54 -> 49035.217 | EP54: =DL54/DG54 -> 77955.939 | EQ54: =DT54/DC54 -> 0.94574383 | ER54: =DU54/DC54 -> 0.054256165 | ES54: =DQ54/DQ16*100-100 -> 16.054126 | ET54: =DP54/DP16*100-100 -> 24.646999 | EU54: =DR54/DR16*100-100 -> 5.0554885 | EV54: =DS54/DS16*100-100 -> 4.4759271 | EW54: =DH54/DH16*100-100 -> 37.306638 | EX54: =DC54/DC16*100-100 -> -0.20641473 | EY54: =DO54/DO16*100-100 -> 55.436571 | EZ54: =EH54/EH16*100-100 -> -23.488412 | FA54: =EI54/EI16*100-100 -> -23.910505 | FB54: =ET54-ES54 -> 8.5928735 | FC54: =EY54-ES54 -> 39.382446 | FD54: 1844808.7 | FE54: 1844808700 | FF54: 558448650 | FG54: =(FF54/FE54)*100 -> 30.271358 | FH54: 4.08 | FI54: 51.3 | FJ54: 4741 | FK54: =FD54/L54 -> 0.081257733 | FL54: -0.09 | FM54: 6.33 | FN54: 2.99 | FO54: 3.61 | FP54: 132.15 | FQ54: 169.1 | FR54: =(FP54-FP16)/FP16*100 -> 1.0321101 | FS54: =(FQ54-FQ16)/FQ16*100 -> 3.6787247 | FT54: 22425.4 | FU54: 22425.4 | FV54: 28485.6 | FW54: =FU54-FV54 -> -6060.2 | FX54: 18124.3 | FY54: 5.81 | FZ54: 15254.41 | GA54: 124.4
A55: Banten | B55: 2023 | C55: 11140 | D55: 53.69 | F55: =D55-E17 -> 53.340693 | G55: 1686945 | H55: =D55*L55/100 -> 2961892.6 | I55: 0.59976258 | K55: =I55-J17 -> -0.1157102 | L55: 5516656 | M55: 7.52 | N55: 7.1 | O55: 8.28 | P55: 64.44 | Q55: 82.16 | R55: 46.16 | S55: 1236312 | T55: 2812688 | U55: 421898 | V55: 281657 | W55: =100-X55-Y55 -> 78.29 | X55: 16.6 | Y55: 5.11 | Z55: 662474 | AA55: 42566 | AB55: 1158479 | AC55: 10582 | AD55: 31428 | AE55: 390743 | AF55: 1186369 | AG55: 361655 | AH55: 479502 | AI55: 56224 | AJ55: 90709 | AK55: 55116 | AL55: 156921 | AM55: 132356 | AN55: 311989 | AO55: 78511 | AP55: 311032 | AQ55: =Z55/sum(Z55:AP55) -> 0.12008615 | AR55: =AA55/sum($Z55:$AP55) -> 0.0077159062 | AS55: =AB55/sum($Z55:$AP55) -> 0.2099966 | AT55: =AC55/sum($Z55:$AP55) -> 0.001918191 | AU55: =AD55/sum($Z55:$AP55) -> 0.0056969294 | AV55: =AE55/sum($Z55:$AP55) -> 0.070829684 | AW55: =AF55/sum($Z55:$AP55) -> 0.2150522 | AX55: =AG55/sum($Z55:$AP55) -> 0.065556924 | AY55: =AH55/sum($Z55:$AP55) -> 0.08691896 | ... BG55: =AP55/sum($Z55:$AP55) -> 0.056380532 | BH55: 43 | BI55: 2661.2801 | BJ55: =BI55/BI17*100-100 -> 6.4 | BK55: 4378058 | BL55: =BI55*1000/BK55 -> 0.60786771 | BM55: 40.48 | BN55: 46.31 | BO55: 125510 | BP55: 7697 | BQ55: 14729 | BR55: 1448863 | BS55: 582058 | BT55: 30187 | BU55: 29173 | BV55: 50719 | BW55: =L55/L17*100-100 -> -7.1366649 | BX55: =T55/T17*100-100 -> -5.0251105 | BY55: =U55/U17*100-100 -> -10.88576 | BZ55: =D55-D17 -> 1.65 | CB55: =W55-W17 -> 1.31 | CC55: =X55-X17 -> -1.85 | CD55: =Y55-Y17 -> 0.54 | CE55: =BH55-BH17 -> 1 | CF55: =M55-M17 -> -0.57 | CG55: =N55-N17 -> -0.29 | CH55: =O55-O17 -> -1.07 | CI55: =P55-P17 -> -0.28 | CJ55: =Q55-Q17 -> 0.47 | CK55: =R55-R17 -> -1.01 | CL55: =BK55/BK17*100-100 -> 0.17802071 | CM55: =BR55/BR17*100-100 -> 2.5656581 | CN55: =BS55/BS17*100-100 -> 64.22322 | CO55: =BT55/BT17*100-100 -> 45.767541 | CP55: =BU55/BU17*100-100 -> -41.968531 | CR55: =C17 -> 3703 | CS55: =D17 -> 52.04 | CU55: =BJ17 -> 1.6337516 | CV55: =BR17 -> 1412620 | CW55: =BS17 -> 354431 | CX55: =BT17 -> 20709 | CY55: =BU17 -> 50271 | CZ55: =BV17 | DC55: 3783 | DF55: 653281 | DG55: 166758 | DH55: 820039 | DI55: 41693104252 | DJ55: 2372244073 | DK55: =DI55+DJ55 -> 44065348325 | DL55: 16304288816 | DM55: 1283360402 | DN55: 17587649218 | DO55: =DN55+DK55 -> 61652997543 | DP55: 592929745499 | DQ55: 1025621225071 | DR55: =DQ55-DP55 -> 432691479572 | DS55: 421384349468 | DT55: 3262 | DU55: 521 | DV55: =DH55/DC55 -> 216.7695 | DW55: =DF55/DH55 -> 0.79664626 | DX55: =DH55/DP55 -> 1.3830289e-06 | DY55: =DH55/DQ55 -> 7.9955346e-07 | DZ55: =DH55/DR55 -> 1.8952049e-06 | EA55: =DH55/DS55 -> 1.9460595e-06 | EB55: =DO55/DP55 -> 0.10398027 | EC55: =DO55/DQ55 -> 0.060112833 | ED55: =DO55/DR55 -> 0.1424872 | EE55: =DO55/DS55 -> 0.1463106 | EF55: =DO55/DH55 -> 75183.007 | EG55: =DQ55/DH55 -> 1250698.1 | EH55: =DR55/DH55 -> 527647.44 | EI55: =DS55/DH55 -> 513858.91 | EJ55: =DP55/DQ55 -> 0.57811766 | EK55: =DR55/DQ55 -> 0.42188234 | EL55: =DS55/DQ55 -> 0.41085767 | EM55: =DK55/DO55 -> 0.71473164 | EN55: =DN55/DO55 -> 0.28526836 | EO55: =DI55/DF55 -> 63821.088 | EP55: =DL55/DG55 -> 97772.154 | EQ55: =DT55/DC55 -> 0.86227861 | ER55: =DU55/DC55 -> 0.13772139 | ES55: =DQ55/DQ17*100-100 -> -5.6729274 | ET55: =DP55/DP17*100-100 -> -5.2534433 | EU55: =DR55/DR17*100-100 -> -6.2417624 | EV55: =DS55/DS17*100-100 -> -8.1127067 | EW55: =DH55/DH17*100-100 -> 0.44610649 | EX55: =DC55/DC17*100-100 -> -1.1238892 | EY55: =DO55/DO17*100-100 -> 22.780771 | EZ55: =EH55/EH17*100-100 -> -6.6581664 | FA55: =EI55/EI17*100-100 -> -8.5208014 | FB55: =ET55-ES55 -> 0.41948408 | FC55: =EY55-ES55 -> 28.453698 | FD55: 507425.7 | FE55: 507425700 | FF55: 169934380 | FG55: =(FF55/FE55)*100 -> 33.48951 | FH55: 5.82 | FI55: 51.3 | FJ55: 4451.6 | FK55: =FD55/L55 -> 0.091980667 | FL55: 12.87 | FM55: 6.33 | FN55: 2.52 | FO55: 3.05 | FP55: 132.15 | FQ55: 169.1 | FR55: =(FP55-FP17)/FP17*100 -> 1.0321101 | FS55: =(FQ55-FQ17)/FQ17*100 -> 3.6787247 | FT55: 12141.9 | FU55: 12141.9 | FV55: 16493.7 | FW55: =FU55-FV55 -> -4351.8 | FX55: 3685.7 | FY55: 5.81 | FZ55: 15254.41 | GA55: 124.4
A56: Bali | B56: 2023 | C56: 145 | D56: 47.65 | F56: =D56-E18 -> 47.28455 | G56: 631495 | H56: =D56*L56/100 -> 1247389.3 | I56: 0.54186742 | K56: =I56-J18 -> 0.028096583 | L56: 2617816 | M56: 2.69 | N56: 3.15 | O56: 2.15 | P56: 77.08 | Q56: 83.55 | R56: 70.63 | S56: 478358 | T56: 1165405 | U56: 349354 | V56: 67408 | W56: =100-X56-Y56 -> 73.89 | X56: 23.54 | Y56: 2.57 | Z56: 495732 | AA56: 6093 | AB56: 384323 | AC56: 5202 | AD56: 18255 | AE56: 174496 | AF56: 559836 | AG56: 99521 | AH56: 357657 | AI56: 12649 | AJ56: 55658 | AK56: 4629 | AL56: 46330 | AM56: 114436 | AN56: 109176 | AO56: 49101 | AP56: 124722 | AQ56: =Z56/sum(Z56:AP56) -> 0.18936854 | AR56: =AA56/sum($Z56:$AP56) -> 0.0023275127 | AS56: =AB56/sum($Z56:$AP56) -> 0.14681055 | AT56: =AC56/sum($Z56:$AP56) -> 0.0019871526 | AU56: =AD56/sum($Z56:$AP56) -> 0.0069733702 | AV56: =AE56/sum($Z56:$AP56) -> 0.066657091 | AW56: =AF56/sum($Z56:$AP56) -> 0.21385613 | AX56: =AG56/sum($Z56:$AP56) -> 0.038016805 | AY56: =AH56/sum($Z56:$AP56) -> 0.13662419 | ... BG56: =AP56/sum($Z56:$AP56) -> 0.047643532 | BH56: 43 | BI56: 2713.6723 | BJ56: =BI56/BI18*100-100 -> 7.8149999 | BK56: 3380840 | BL56: =BI56*1000/BK56 -> 0.80266214 | BM56: 42.9 | BN56: 52.35 | BO56: 20047 | BP56: 1794 | BQ56: 2425 | BR56: 551350 | BS56: 267730 | BT56: 2339 | BU56: 2172 | BV56: 476 | BW56: =L56/L18*100-100 -> 0.41218686 | BX56: =T56/T18*100-100 -> 2.4041229 | BY56: =U56/U18*100-100 -> -3.5157588 | BZ56: =D56-D18 -> 1.08 | CB56: =W56-W18 -> 7.49 | CC56: =X56-X18 -> -6.13 | CD56: =Y56-Y18 -> -1.36 | CE56: =BH56-BH18 -> 1 | CF56: =M56-M18 -> -2.11 | CG56: =N56-N18 -> -2.02 | CH56: =O56-O18 -> -2.2 | CI56: =P56-P18 -> 0.22 | CJ56: =Q56-Q18 -> -0.51 | CK56: =R56-R18 -> 1.01 | CL56: =BK56/BK18*100-100 -> 12.599558 | CM56: =BR56/BR18*100-100 -> 22.644867 | CN56: =BS56/BS18*100-100 -> 65.918866 | CO56: =BT56/BT18*100-100 -> -36.21489 | CP56: =BU56/BU18*100-100 -> -74.735373 | CR56: =C18 -> 706 | CS56: =D18 -> 46.57 | CU56: =BJ18 -> 0.92105052 | CV56: =BR18 -> 449550 | CW56: =BS18 -> 161362 | CX56: =BT18 -> 3667 | CY56: =BU18 -> 8597 | CZ56: =BV18 | DC56: 446 | DF56: 28231 | DG56: 7753 | DH56: 35984 | DI56: 1021994951 | DJ56: 85810766 | DK56: =DI56+DJ56 -> 1107805717 | DL56: 505224624 | DM56: 72300279 | DN56: 577524903 | DO56: =DN56+DK56 -> 1685330620 | DP56: 6683521207 | DQ56: 13474392871 | DR56: =DQ56-DP56 -> 6790871664 | DS56: 6510109613 | DT56: 401 | DU56: 45 | DV56: =DH56/DC56 -> 80.681614 | DW56: =DF56/DH56 -> 0.78454313 | DX56: =DH56/DP56 -> 5.3839883e-06 | DY56: =DH56/DQ56 -> 2.670547e-06 | DZ56: =DH56/DR56 -> 5.2988779e-06 | EA56: =DH56/DS56 -> 5.5274031e-06 | EB56: =DO56/DP56 -> 0.25216208 | EC56: =DO56/DQ56 -> 0.12507655 | ED56: =DO56/DR56 -> 0.24817589 | EE56: =DO56/DS56 -> 0.25887899 | EF56: =DO56/DH56 -> 46835.555 | EG56: =DQ56/DH56 -> 374455.12 | EH56: =DR56/DH56 -> 188719.2 | EI56: =DS56/DH56 -> 180916.79 | EJ56: =DP56/DQ56 -> 0.4960165 | EK56: =DR56/DQ56 -> 0.5039835 | EL56: =DS56/DQ56 -> 0.48314679 | EM56: =DK56/DO56 -> 0.65732249 | EN56: =DN56/DO56 -> 0.34267751 | EO56: =DI56/DF56 -> 36201.16 | EP56: =DL56/DG56 -> 65165.049 | EQ56: =DT56/DC56 -> 0.89910314 | ER56: =DU56/DC56 -> 0.10089686 | ES56: =DQ56/DQ18*100-100 -> 18.236303 | ET56: =DP56/DP18*100-100 -> 29.24675 | EU56: =DR56/DR18*100-100 -> 9.0899134 | EV56: =DS56/DS18*100-100 -> 8.6664982 | EW56: =DH56/DH18*100-100 -> 25.53288 | EX56: =DC56/DC18*100-100 -> 4.9411765 | EY56: =DO56/DO18*100-100 -> 26.398426 | EZ56: =EH56/EH18*100-100 -> -13.098534 | FA56: =EI56/EI18*100-100 -> -13.435828 | FB56: =ET56-ES56 -> 11.010447 | FC56: =EY56-ES56 -> 8.1621224 | FD56: 159464.3 | FE56: 159464300 | FF56: 10478810 | FG56: =(FF56/FE56)*100 -> 6.5712576 | FH56: 2.26 | FI56: 51.3 | FJ56: 808.5 | FK56: =FD56/L56 -> 0.060915015 | FL56: 5.28 | FM56: 6.33 | FN56: 3.14 | FO56: 3.71 | FP56: 132.15 | FQ56: 169.1 | FR56: =(FP56-FP18)/FP18*100 -> 1.0321101 | FS56: =(FQ56-FQ18)/FQ18*100 -> 3.6787247 | FT56: 581 | FU56: 581 | FV56: 113.2 | FW56: =FU56-FV56 -> 467.8 | FX56: 1857.6 | FY56: 5.81 | FZ56: 15254.41 | GA56: 124.4
A57: Nusa Tenggara Barat | B57: 2023 | C57: 90 | D57: 27.7 | F57: =D57-E19 -> 27.507095 | G57: 446219 | H57: =D57*L57/100 -> 801356.01 | I57: 0.60872394 | K57: =I57-J19 -> 0.080877576 | L57: 2892982 | M57: 2.8 | N57: 3.29 | O57: 2.14 | P57: 73.31 | Q57: 84.18 | R57: 62.54 | S57: 616072 | T57: 733040 | U57: 453693 | V57: 371157 | W57: =100-X57-Y57 -> 62.04 | X57: 25.13 | Y57: 12.83 | Z57: 970339 | AA57: 31806 | AB57: 357998 | AC57: 7828 | AD57: 7549 | AE57: 181985 | AF57: 529876 | AG57: 85416 | AH57: 162035 | AI57: 14366 | AJ57: 37167 | AK57: 4100 | AL57: 36068 | AM57: 111169 | AN57: 202171 | AO57: 41229 | AP57: 111880 | AQ57: =Z57/sum(Z57:AP57) -> 0.33541135 | AR57: =AA57/sum($Z57:$AP57) -> 0.010994192 | AS57: =AB57/sum($Z57:$AP57) -> 0.12374705 | AT57: =AC57/sum($Z57:$AP57) -> 0.0027058585 | AU57: =AD57/sum($Z57:$AP57) -> 0.0026094182 | AV57: =AE57/sum($Z57:$AP57) -> 0.06290568 | AW57: =AF57/sum($Z57:$AP57) -> 0.18315911 | AX57: =AG57/sum($Z57:$AP57) -> 0.029525244 | AY57: =AH57/sum($Z57:$AP57) -> 0.056009681 | ... BG57: =AP57/sum($Z57:$AP57) -> 0.038672899 | BH57: 38 | BI57: 3251.7027 | BJ57: =BI57/BI19*100-100 -> 7.7886999 | BK57: 2344661 | BL57: =BI57*1000/BK57 -> 1.3868541 | BM57: 59.65 | BN57: 72.3 | BO57: 52854 | BP57: 2667 | BQ57: 3011 | BR57: 337664 | BS57: 200296 | BT57: 2865 | BU57: 1942 | BV57: 211 | BW57: =L57/L19*100-100 -> 6.4243869 | BX57: =T57/T19*100-100 -> 17.488668 | BY57: =U57/U19*100-100 -> -3.4952406 | BZ57: =D57-D19 -> 3.06 | CB57: =W57-W19 -> 0.64 | CC57: =X57-X19 -> -0.17 | CD57: =Y57-Y19 -> -0.47 | CE57: =BH57-BH19 -> 0 | CF57: =M57-M19 -> -0.09 | CG57: =N57-N19 -> -0.32 | CH57: =O57-O19 -> 0.23 | CI57: =P57-P19 -> 2.38 | CJ57: =Q57-Q19 -> 0.91 | CK57: =R57-R19 -> 3.38 | CL57: =BK57/BK19*100-100 -> 5.6908674 | CM57: =BR57/BR19*100-100 -> 17.569393 | CN57: =BS57/BS19*100-100 -> 128.41373 | CO57: =BT57/BT19*100-100 -> 21.759456 | CP57: =BU57/BU19*100-100 -> -54.805678 | CR57: =C19 -> 396 | CS57: =D19 -> 24.64 | CU57: =BJ19 -> 0.53099103 | CV57: =BR19 -> 287204 | CW57: =BS19 -> 87690 | CX57: =BT19 -> 2353 | CY57: =BU19 -> 4297 | CZ57: =BV19 | DC57: 209 | DF57: 6203 | DG57: 2436 | DH57: 8639 | DI57: 143622054 | DJ57: 8824188 | DK57: =DI57+DJ57 -> 152446242 | DL57: 51752977 | DM57: 1460722 | DN57: 53213698 | DO57: =DN57+DK57 -> 205659940 | DP57: 3799299439 | DQ57: 5276702148 | DR57: =DQ57-DP57 -> 1477402709 | DS57: 1410994313 | DV57: =DH57/DC57 -> 41.334928 | DW57: =DF57/DH57 -> 0.71802292 | DX57: =DH57/DP57 -> 2.2738403e-06 | DY57: =DH57/DQ57 -> 1.6371968e-06 | DZ57: =DH57/DR57 -> 5.847424e-06 | EA57: =DH57/DS57 -> 6.1226328e-06 | EB57: =DO57/DP57 -> 0.054131016 | EC57: =DO57/DQ57 -> 0.03897509 | ED57: =DO57/DR57 -> 0.13920371 | EE57: =DO57/DS57 -> 0.14575533 | EF57: =DO57/DH57 -> 23805.989 | EG57: =DQ57/DH57 -> 610800.11 | EH57: =DR57/DH57 -> 171015.48 | EI57: =DS57/DH57 -> 163328.43 | EJ57: =DP57/DQ57 -> 0.720014 | EK57: =DR57/DQ57 -> 0.279986 | EL57: =DS57/DQ57 -> 0.26740079 | EM57: =DK57/DO57 -> 0.74125395 | EN57: =DN57/DO57 -> 0.25874605 | EO57: =DI57/DF57 -> 23153.644 | EP57: =DL57/DG57 -> 21245.064 | EQ57: =DT57/DC57 -> 0 | ER57: =DU57/DC57 -> 0 | ES57: =DQ57/DQ19*100-100 -> 4.160206 | ET57: =DP57/DP19*100-100 -> 10.509348 | EU57: =DR57/DR19*100-100 -> -9.2481665 | EV57: =DS57/DS19*100-100 -> -11.806874 | EW57: =DH57/DH19*100-100 -> -4.898723 | EX57: =DC57/DC19*100-100 -> -1.4150943 | EY57: =DO57/DO19*100-100 -> -7.1973633 | EZ57: =EH57/EH19*100-100 -> -4.5734858 | FA57: =EI57/EI19*100-100 -> -7.2639939 | FB57: =ET57-ES57 -> 6.349142 | FC57: =EY57-ES57 -> -11.357569 | FD57: 103906.2 | FE57: 103906200 | FF57: 4644520 | FG57: =(FF57/FE57)*100 -> 4.4699161 | FH57: 2.51 | FI57: 51.3 | FJ57: 468.4 | FK57: =FD57/L57 -> 0.035916642 | FL57: -4.35 | FM57: 6.33 | FN57: 3.35 | FO57: 3.7 | FP57: 132.15 | FQ57: 169.1 | FR57: =(FP57-FP19)/FP19*100 -> 1.0321101 | FS57: =(FQ57-FQ19)/FQ19*100 -> 3.6787247 | FT57: 2050.6 | FU57: 2050.6 | FV57: 597.8 | FW57: =FU57-FV57 -> 1452.8 | FX57: 802.5 | FY57: 5.81 | FZ57: 15254.41 | GA57: 124.4
A58: Nusa Tenggara Timur | B58: 2023 | C58: 108 | D58: 25.49 | F58: =D58-E20 -> 25.308145 | G58: 455066 | H58: =D58*L58/100 -> 738420.06 | I58: 0.651495 | K58: =I58-J20 -> 0.049886596 | L58: 2896901 | M58: 3.14 | N58: 2.95 | O58: 3.36 | P58: 75.72 | Q58: 83.03 | R58: 68.52 | S58: 708400 | T58: 698495 | U58: 713462 | V58: 310805 | W58: =100-X58-Y58 -> 52.2 | X58: 37.07 | Y58: 10.73 | Z58: 1421199 | AA58: 22086 | AB58: 273926 | AC58: 5229 | AD58: 8475 | AE58: 119612 | AF58: 339376 | AG58: 148043 | AH58: 45297 | AI58: 7243 | AJ58: 26302 | AK58: 1566 | AL58: 26428 | AM58: 164922 | AN58: 178976 | AO58: 56186 | AP58: 52035 | AQ58: =Z58/sum(Z58:AP58) -> 0.49059288 | AR58: =AA58/sum($Z58:$AP58) -> 0.0076240092 | AS58: =AB58/sum($Z58:$AP58) -> 0.094558288 | AT58: =AC58/sum($Z58:$AP58) -> 0.0018050323 | AU58: =AD58/sum($Z58:$AP58) -> 0.0029255401 | AV58: =AE58/sum($Z58:$AP58) -> 0.04128964 | AW58: =AF58/sum($Z58:$AP58) -> 0.1171514 | AX58: =AG58/sum($Z58:$AP58) -> 0.051103921 | AY58: =AH58/sum($Z58:$AP58) -> 0.015636365 | ... BG58: =AP58/sum($Z58:$AP58) -> 0.017962298 | BH58: 40 | BI58: 2608.6017 | BJ58: =BI58/BI20*100-100 -> 7.1590002 | BK58: 2339851 | BL58: =BI58*1000/BK58 -> 1.1148581 | BM58: 51.68 | BN58: 74.51 | BO58: 14640 | BP58: 3196 | BQ58: 4976 | BR58: 362631 | BS58: 155706 | BT58: 1779 | BU58: 1452 | BV58: 137 | BW58: =L58/L20*100-100 -> -0.63087998 | BX58: =T58/T20*100-100 -> 1.8511228 | BY58: =U58/U20*100-100 -> 1.5008991 | BZ58: =D58-D20 -> 0.73 | CB58: =W58-W20 -> -0.24 | CC58: =X58-X20 -> 2.01 | CD58: =Y58-Y20 -> -1.77 | CE58: =BH58-BH20 -> 0 | CF58: =M58-M20 -> -0.4 | CG58: =N58-N20 -> -0.87 | CH58: =O58-O20 -> 0.14 | CI58: =P58-P20 -> 0.49 | CJ58: =Q58-Q20 -> 0.18 | CK58: =R58-R20 -> 0.65 | CL58: =BK58/BK20*100-100 -> 11.372313 | CM58: =BR58/BR20*100-100 -> 23.427422 | CN58: =BS58/BS20*100-100 -> 46.524759 | CO58: =BT58/BT20*100-100 -> -2.0374449 | CP58: =BU58/BU20*100-100 -> -54.152195 | CR58: =C20 -> 62 | CS58: =D20 -> 24.76 | CU58: =BJ20 -> 1.4430787 | CV58: =BR20 -> 293801 | CW58: =BS20 -> 106266 | CX58: =BT20 -> 1816 | CY58: =BU20 -> 3167 | CZ58: =BV20 | DC58: 77 | DF58: 1834 | DG58: 804 | DH58: 2638 | DI58: 45555806 | DJ58: 1250879 | DK58: =DI58+DJ58 -> 46806685 | DL58: 27254561 | DM58: 532484 | DN58: 27787045 | DO58: =DN58+DK58 -> 74593730 | DP58: 174524137 | DQ58: 342401246 | DR58: =DQ58-DP58 -> 167877109 | DS58: 155142303 | DV58: =DH58/DC58 -> 34.25974 | DW58: =DF58/DH58 -> 0.69522365 | DX58: =DH58/DP58 -> 1.5115388e-05 | DY58: =DH58/DQ58 -> 7.7044112e-06 | DZ58: =DH58/DR58 -> 1.5713876e-05 | EA58: =DH58/DS58 -> 1.7003744e-05 | EB58: =DO58/DP58 -> 0.42741211 | EC58: =DO58/DQ58 -> 0.21785473 | ED58: =DO58/DR58 -> 0.44433533 | EE58: =DO58/DS58 -> 0.48080845 | EF58: =DO58/DH58 -> 28276.622 | EG58: =DQ58/DH58 -> 129795.77 | EH58: =DR58/DH58 -> 63638.025 | EI58: =DS58/DH58 -> 58810.577 | EJ58: =DP58/DQ58 -> 0.50970649 | EK58: =DR58/DQ58 -> 0.49029351 | EL58: =DS58/DQ58 -> 0.45310087 | EM58: =DK58/DO58 -> 0.6274882 | EN58: =DN58/DO58 -> 0.3725118 | EO58: =DI58/DF58 -> 24839.589 | EP58: =DL58/DG58 -> 33898.708 | EQ58: =DT58/DC58 -> 0 | ER58: =DU58/DC58 -> 0 | ES58: =DQ58/DQ20*100-100 -> 15.15543 | ET58: =DP58/DP20*100-100 -> 14.781056 | EU58: =DR58/DR20*100-100 -> 15.547225 | EV58: =DS58/DS20*100-100 -> 10.178714 | EW58: =DH58/DH20*100-100 -> 79.94543 | EX58: =DC58/DC20*100-100 -> 1.3157895 | EY58: =DO58/DO20*100-100 -> 136.23008 | EZ58: =EH58/EH20*100-100 -> -35.78763 | FA58: =EI58/EI20*100-100 -> -38.77104 | FB58: =ET58-ES58 -> -0.37437435 | FC58: =EY58-ES58 -> 121.07465 | FD58: 75246.7 | FE58: 75246700 | FF58: 944420 | FG58: =(FF58/FE58)*100 -> 1.2550982 | FH58: 7.33 | FI58: 51.3 | FJ58: 124.3 | FK58: =FD58/L58 -> 0.025974895 | FL58: 4.18 | FM58: 6.33 | FN58: 3.51 | FO58: 4.06 | FP58: 132.15 | FQ58: 169.1 | FR58: =(FP58-FP20)/FP20*100 -> 1.0321101 | FS58: =(FQ58-FQ20)/FQ20*100 -> 3.6787247 | FT58: 74.1 | FU58: 74.1 | FV58: 70.3 | FW58: =FU58-FV58 -> 3.8 | FX58: 805.8 | FY58: 5.81 | FZ58: 15254.41 | GA58: 124.4
A59: Kalimantan Barat | B59: 2023 | C59: 459 | D59: 40.31 | F59: =D59-E21 -> 40.048537 | G59: 418703 | H59: =D59*L59/100 -> 1118701.3 | I59: 0.40632433 | K59: =I59-J21 -> -0.010817065 | L59: 2775245 | M59: 5.05 | N59: 5.09 | O59: 4.98 | P59: 69.42 | Q59: 84.85 | R59: 53.11 | S59: 623168 | T59: 1030465 | U59: 436263 | V59: 188229 | W59: =100-X59-Y59 -> 65.76 | X59: 27.46 | Y59: 6.78 | Z59: 1318010 | AA59: 81696 | AB59: 138174 | AC59: 6819 | AD59: 4430 | AE59: 180309 | AF59: 408159 | AG59: 80530 | AH59: 151127 | AI59: 9598 | AJ59: 17286 | AK59: 2910 | AL59: 22012 | AM59: 103938 | AN59: 121767 | AO59: 40239 | AP59: 88241 | AQ59: =Z59/sum(Z59:AP59) -> 0.47491663 | AR59: =AA59/sum($Z59:$AP59) -> 0.029437401 | AS59: =AB59/sum($Z59:$AP59) -> 0.049788037 | AT59: =AC59/sum($Z59:$AP59) -> 0.0024570804 | AU59: =AD59/sum($Z59:$AP59) -> 0.0015962555 | AV59: =AE59/sum($Z59:$AP59) -> 0.06497048 | AW59: =AF59/sum($Z59:$AP59) -> 0.14707134 | AX59: =AG59/sum($Z59:$AP59) -> 0.029017258 | AY59: =AH59/sum($Z59:$AP59) -> 0.054455372 | ... BG59: =AP59/sum($Z59:$AP59) -> 0.031795751 | BH59: 41 | BI59: 3181.013 | BJ59: =BI59/BI21*100-100 -> 8.8450157 | BK59: 2796615 | BL59: =BI59*1000/BK59 -> 1.1374512 | BM59: 42.2 | BN59: 59.69 | BO59: 21996 | BP59: 3011 | BQ59: 4051 | BR59: 424365 | BS59: 153588 | BT59: 5742 | BU59: 4918 | BV59: 3173 | BW59: =L59/L21*100-100 -> 8.5130026 | BX59: =T59/T21*100-100 -> 5.4568211 | BY59: =U59/U21*100-100 -> 20.601261 | BZ59: =D59-D21 -> -0.92 | CB59: =W59-W21 -> 1.63 | CC59: =X59-X21 -> -1.2 | CD59: =Y59-Y21 -> -0.43 | CE59: =BH59-BH21 -> 1 | CF59: =M59-M21 -> -0.06 | CG59: =N59-N21 -> -0.02 | CH59: =O59-O21 -> -0.12 | CI59: =P59-P21 -> 0.45 | CJ59: =Q59-Q21 -> -0.16 | CK59: =R59-R21 -> 0.6 | CL59: =BK59/BK21*100-100 -> 5.6953725 | CM59: =BR59/BR21*100-100 -> 6.4812375 | CN59: =BS59/BS21*100-100 -> 69.684248 | CO59: =BT59/BT21*100-100 -> 65.332566 | CP59: =BU59/BU21*100-100 -> 11.34254 | CR59: =C21 -> 1131 | CS59: =D21 -> 41.23 | CU59: =BJ21 -> 0.66725231 | CV59: =BR21 -> 398535 | CW59: =BS21 -> 90514 | CX59: =BT21 -> 3473 | CY59: =BU21 -> 4417 | CZ59: =BV21 | DC59: 244 | DF59: 40122 | DG59: 87 | DH59: 40209 | DI59: 2194010479 | DJ59: 78159224 | DK59: =DI59+DJ59 -> 2272169703 | DL59: 631070750 | DM59: 66165248 | DN59: 697235998 | DO59: =DN59+DK59 -> 2969405701 | DP59: 62664321948 | DQ59: 101241353117 | DR59: =DQ59-DP59 -> 38577031169 | DS59: 36981115011 | DT59: 222 | DU59: 22 | DV59: =DH59/DC59 -> 164.79098 | DW59: =DF59/DH59 -> 0.99783631 | DX59: =DH59/DP59 -> 6.4165699e-07 | DY59: =DH59/DQ59 -> 3.9715984e-07 | DZ59: =DH59/DR59 -> 1.0423042e-06 | EA59: =DH59/DS59 -> 1.0872847e-06 | EB59: =DO59/DP59 -> 0.047385906 | EC59: =DO59/DQ59 -> 0.029329969 | ED59: =DO59/DR59 -> 0.076973412 | EE59: =DO59/DS59 -> 0.080295191 | EF59: =DO59/DH59 -> 73849.28 | EG59: =DQ59/DH59 -> 2517877.9 | EH59: =DR59/DH59 -> 959412.85 | EI59: =DS59/DH59 -> 919722.33 | EJ59: =DP59/DQ59 -> 0.61895974 | EK59: =DR59/DQ59 -> 0.38104026 | EL59: =DS59/DQ59 -> 0.36527678 | EM59: =DK59/DO59 -> 0.76519342 | EN59: =DN59/DO59 -> 0.23480658 | EO59: =DI59/DF59 -> 54683.477 | EP59: =DL59/DG59 -> 7253686.8 | EQ59: =DT59/DC59 -> 0.90983607 | ER59: =DU59/DC59 -> 0.090163934 | ES59: =DQ59/DQ21*100-100 -> 1.3838927 | ET59: =DP59/DP21*100-100 -> 7.0842 | EU59: =DR59/DR21*100-100 -> -6.6850332 | EV59: =DS59/DS21*100-100 -> -8.647012 | EW59: =DH59/DH21*100-100 -> -5.3393601 | EX59: =DC59/DC21*100-100 -> 5.6277056 | EY59: =DO59/DO21*100-100 -> 10.206539 | EZ59: =EH59/EH21*100-100 -> -1.4215761 | FA59: =EI59/EI21*100-100 -> -3.4942209 | FB59: =ET59-ES59 -> 5.7003073 | FC59: =EY59-ES59 -> 8.8226468 | FD59: 154980.8 | FE59: 154980800 | FF59: 24255610 | FG59: =(FF59/FE59)*100 -> 15.650719 | FH59: 2.57 | FI59: 51.3 | FJ59: 490.5 | FK59: =FD59/L59 -> 0.055844007 | FL59: -3.74 | FM59: 6.33 | FN59: 2.74 | FO59: 3.22 | FP59: 132.15 | FQ59: 169.1 | FR59: =(FP59-FP21)/FP21*100 -> 1.0321101 | FS59: =(FQ59-FQ21)/FQ21*100 -> 3.6787247 | FT59: 2124.2 | FU59: 2124.2 | FV59: 457.2 | FW59: =FU59-FV59 -> 1667 | FX59: 1300.7 | FY59: 5.81 | FZ59: 15254.41 | GA59: 124.4
A60: Kalimantan Tengah | B60: 2023 | C60: 405 | D60: 48.14 | F60: =D60-E22 -> 47.805195 | G60: 322017 | H60: =D60*L60/100 -> 649829.82 | I60: 0.53333057 | K60: =I60-J22 -> -0.024542268 | L60: 1349875 | M60: 4.1 | N60: 3.78 | O60: 4.71 | P60: 67.18 | Q60: 84.85 | R60: 48.13 | S60: 346718 | T60: 603785 | U60: 143737 | V60: 82522 | W60: =100-X60-Y60 -> 70.43 | X60: 23.46 | Y60: 6.11 | Z60: 485968 | AA60: 135522 | AB60: 61738 | AC60: 3552 | AD60: 2910 | AE60: 64004 | AF60: 219959 | AG60: 44850 | AH60: 70113 | AI60: 6096 | AJ60: 7657 | AK60: 1521 | AL60: 14978 | AM60: 85172 | AN60: 78702 | AO60: 22637 | AP60: 44496 | AQ60: =Z60/sum(Z60:AP60) -> 0.36000963 | AR60: =AA60/sum($Z60:$AP60) -> 0.10039596 | AS60: =AB60/sum($Z60:$AP60) -> 0.045736087 | AT60: =AC60/sum($Z60:$AP60) -> 0.0026313548 | AU60: =AD60/sum($Z60:$AP60) -> 0.0021557552 | AV60: =AE60/sum($Z60:$AP60) -> 0.047414761 | AW60: =AF60/sum($Z60:$AP60) -> 0.16294768 | AX60: =AG60/sum($Z60:$AP60) -> 0.033225299 | AY60: =AH60/sum($Z60:$AP60) -> 0.051940365 | ... BG60: =AP60/sum($Z60:$AP60) -> 0.032963052 | BH60: 42 | BI60: 3149.9776 | BJ60: =BI60/BI22*100-100 -> 8.3779998 | BK60: 3323457 | BL60: =BI60*1000/BK60 -> 0.94780154 | BM60: 43.63 | BN60: 51.86 | BO60: 17299 | BP60: 1407 | BQ60: 1608 | BR60: 276160 | BS60: 108540 | BT60: 2863 | BU60: 2005 | BV60: 1030 | BW60: =L60/L22*100-100 -> 0.40164376 | BX60: =T60/T22*100-100 -> -0.97632098 | BY60: =U60/U22*100-100 -> -1.7182906 | BZ60: =D60-D22 -> -0.36 | CB60: =W60-W22 -> -0.34 | CC60: =X60-X22 -> -0.39 | CD60: =Y60-Y22 -> 0.73 | CE60: =BH60-BH22 -> 1 | CF60: =M60-M22 -> -0.16 | CG60: =N60-N22 -> -0.17 | CH60: =O60-O22 -> -0.15 | CI60: =P60-P22 -> -0.05 | CJ60: =Q60-Q22 -> -0.32 | CK60: =R60-R22 -> 0.45 | CL60: =BK60/BK22*100-100 -> 4.0106018 | CM60: =BR60/BR22*100-100 -> 0.87852277 | CN60: =BS60/BS22*100-100 -> 69.355594 | CO60: =BT60/BT22*100-100 -> 35.751541 | CP60: =BU60/BU22*100-100 -> -40.309616 | CR60: =C22 -> 37 | CS60: =D22 -> 48.5 | CU60: =BJ22 -> 1.0086967 | CV60: =BR22 -> 273755 | CW60: =BS22 -> 64090 | CX60: =BT22 -> 2109 | CY60: =BU22 -> 3359 | CZ60: =BV22 | DC60: 167 | DF60: 16227 | DG60: 4676 | DH60: 20903 | DI60: 758355340 | DJ60: 78853959 | DK60: =DI60+DJ60 -> 837209299 | DL60: 332693974 | DM60: 22196476 | DN60: 354890450 | DO60: =DN60+DK60 -> 1192099749 | DP60: 90216360691 | DQ60: 121617893181 | DR60: =DQ60-DP60 -> 31401532490 | DS60: 28846604477 | DT60: 134 | DU60: 33 | DV60: =DH60/DC60 -> 125.16766 | DW60: =DF60/DH60 -> 0.77630005 | DX60: =DH60/DP60 -> 2.3169855e-07 | DY60: =DH60/DQ60 -> 1.7187438e-07 | DZ60: =DH60/DR60 -> 6.6566815e-07 | EA60: =DH60/DS60 -> 7.2462601e-07 | EB60: =DO60/DP60 -> 0.013213787 | EC60: =DO60/DQ60 -> 0.0098020095 | ED60: =DO60/DR60 -> 0.037963107 | EE60: =DO60/DS60 -> 0.041325479 | EF60: =DO60/DH60 -> 57030.079 | EG60: =DQ60/DH60 -> 5818202.8 | EH60: =DR60/DH60 -> 1502250 | EI60: =DS60/DH60 -> 1380022.2 | EJ60: =DP60/DQ60 -> 0.74180171 | EK60: =DR60/DQ60 -> 0.25819829 | EL60: =DS60/DQ60 -> 0.23719046 | EM60: =DK60/DO60 -> 0.70229802 | EN60: =DN60/DO60 -> 0.29770198 | EO60: =DI60/DF60 -> 46734.168 | EP60: =DL60/DG60 -> 71149.267 | EQ60: =DT60/DC60 -> 0.80239521 | ER60: =DU60/DC60 -> 0.19760479 | ES60: =DQ60/DQ22*100-100 -> 3.8140608 | ET60: =DP60/DP22*100-100 -> 2.1046328 | EU60: =DR60/DR22*100-100 -> 9.0597726 | EV60: =DS60/DS22*100-100 -> 8.886883 | EW60: =DH60/DH22*100-100 -> -22.31967 | EX60: =DC60/DC22*100-100 -> 0.60240964 | EY60: =DO60/DO22*100-100 -> -15.272679 | EZ60: =EH60/EH22*100-100 -> 40.395609 | FA60: =EI60/EI22*100-100 -> 40.173044 | FB60: =ET60-ES60 -> -1.7094281 | FC60: =EY60-ES60 -> -19.086739 | FD60: 113611.5 | FE60: 113611500 | FF60: 17882650 | FG60: =(FF60/FE60)*100 -> 15.740176 | FH60: 5.87 | FI60: 51.3 | FJ60: 697.6 | FK60: =FD60/L60 -> 0.08416446 | FL60: 3.72 | FM60: 6.33 | FN60: 2.82 | FO60: 3.39 | FP60: 132.15 | FQ60: 169.1 | FR60: =(FP60-FP22)/FP22*100 -> 1.0321101 | FS60: =(FQ60-FQ22)/FQ22*100 -> 3.6787247 | FT60: 4992.1 | FU60: 4992.1 | FV60: 72.7 | FW60: =FU60-FV60 -> 4919.4 | FX60: 605.7 | FY60: 5.81 | FZ60: 15254.41 | GA60: 124.4
